Workbook
Name AUHAgeBr: 'Final premium per member'!$U$5:$V$17
Name DXBAgeBr: 'Final premium per member'!$T$5:$V$17

Sheet Approved Quote
A1: Policyholder: | C1: MGH LOGISTICS L.L.C
A2: Start Date: | C2: 46105
A3: Broker Name: | C3: Savington International Insurance Brokers LLC
A6: PREMIUM OVERVIEW
A8: TOTAL PREMIUM | F8: =I35+I59+I83+I107& " members" -> 17 members | I8: =SUM(I34,I58,I82,I106) -> 165194
A9: BASMAH FEE (AED 37 / member) | F9: =I35+I59+I83+I107& " members" -> 17 members | I9: =(I35+I59+I83+I107)*37 -> 629
A10: SLASH DATA FEE (AED 25 / member) | F10: 0 Rest of UAE members | I10: 0
A11: ADDITIONAL LOADING | F11: Additional loading for pre-existing conditions
A12: VALUE ADDED TAX (VAT) | F12: 0.05 | I12: =SUM(I8:J11)*5% -> 8291.15
I13: =SUM(I8:J12) -> 174114.15
A16: Category A
B18: PRINCIPAL | G18: DEPENDENTS | P18: Cat A
A19: Age Range | B19: Premium | C19: Male | D19: Premium | E19: Female | G19: Premium | H19: Male | I19: Premium | J19: Female | P19: Principal | Q19: Dependents
A20: 0 - 10 | B20: 4600 | D20: 3600 | G20: 6499 | I20: 5234 | J20: 5 | O20: 0-10 | P20: =B20*C20+D20*E20 -> 0 | Q20: =G20*H20+I20*J20 -> 26170 | R20: 0
A21: 11 - 17 | B21: 3157 | D21: 3217 | G21: 4674 | I21: 4750 | J21: 1 | O21: 11-17 | P21: =B21*C21+D21*E21 -> 0 | Q21: =G21*H21+I21*J21 -> 4750
A22: 18 - 25 | B22: 5253 | C22: 1 | D22: 5997 | G22: 5253 | I22: 5997 | O22: 18-25 | P22: =B22*C22+D22*E22 -> 5253 | Q22: =G22*H22+I22*J22 -> 0
A23: 26 - 30 | B23: 5833 | C23: 1 | D23: 7304 | E23: 1 | G23: 5833 | I23: 7304 | J23: 2 | O23: 26-30 | P23: =B23*C23+D23*E23 -> 13137 | Q23: =G23*H23+I23*J23 -> 14608
A24: 31 - 35 | B24: 6915 | C24: 1 | D24: 8606 | G24: 6915 | I24: 8606 | O24: 31-35 | P24: =B24*C24+D24*E24 -> 6915 | Q24: =G24*H24+I24*J24 -> 0
A25: 36 - 40 | B25: 8397 | C25: 1 | D25: 10589 | G25: 8397 | I25: 10589 | M25: 2599 | O25: 36-40 | P25: =B25*C25+D25*E25 -> 8397 | Q25: =G25*H25+I25*J25 -> 0 | S25: 25596 | T25: 0 | U25: 25596
A26: 41 - 45 | B26: 8785 | C26: 1 | D26: 12068 | G26: 8795 | I26: 12068 | J26: 1 | M26: 2716 | O26: 41-45 | P26: =B26*C26+D26*E26 -> 8785 | Q26: =G26*H26+I26*J26 -> 12068
A27: 46 - 50 | B27: 11304 | D27: 14951 | G27: 11304 | I27: 14951 | M27: -117 | O27: 46-50 | P27: =B27*C27+D27*E27 -> 0 | Q27: =G27*H27+I27*J27 -> 0
A28: 51 - 55 | B28: 14946 | D28: 19507 | G28: 14946 | I28: 19507 | J28: 1 | O28: 51-55 | P28: =B28*C28+D28*E28 -> 0 | Q28: =G28*H28+I28*J28 -> 19507
A29: 56 - 59 | B29: 20128 | D29: 23729 | G29: 20128 | I29: 23729 | O29: 56-59 | P29: =B29*C29+D29*E29 -> 0 | Q29: =G29*H29+I29*J29 -> 0
A30: 60 - 64 | B30: 24628 | C30: 1 | D30: 28071 | G30: 24628 | I30: 28071 | M30: -4.5017314 | O30: 60-64 | P30: =B30*C30+D30*E30 -> 24628 | Q30: =G30*H30+I30*J30 -> 0
A31: 65 - 99 | B31: 43786 | D31: 49985 | G31: 43786 | I31: 49985 | O31: 65-99 | P31: =B31*C31+D31*E31 -> 0 | Q31: =G31*H31+I31*J31 -> 0
A32: Subtotals | C32: =SUM(C20:C31) -> 6 | E32: =SUM(E20:E31) -> 1 | H32: =SUM(H20:H31) -> 0 | J32: =SUM(J20:J31) -> 10 | O32: Subtotals | P32: =SUM(P20:P31) -> 67115 | Q32: =SUM(Q20:Q31) -> 77103
A33: For members 65 years old & above, the premium quoted is INDICATIVE only and subject to completion of the Medical Application Form (MAF), Medical Examination Report (MER). Further blood tests, and ECG are required for 70+ years old members.
A34: Maternity Premium (18-45) | C34: =C36*C35 -> 20976 | G34: Category Premium | I34: =P32+C34+Q32 -> 165194
A35: Census | C35: 4 | G35: Category Members | I35: =SUM(C20:C31,E20:E31,H20:H31,J20:J31) -> 17
A36: Average | C36: 5244 | G36: Average | I36: =I34/I35 -> 9717.2941
A40: Category B
B42: PRINCIPAL | G42: DEPENDENTS | P42: Cat B
A43: Age Range | B43: Premium | C43: Male | D43: Premium | E43: Female | G43: Premium | H43: Male | I43: Premium | J43: Female | P43: Principal | Q43: Dependents
O44: 0-10 | P44: =B44*C44+D44*E44 -> 0 | Q44: =G44*H44+I44*J44 -> 0
O45: 11-17 | P45: =B45*C45+D45*E45 -> 0 | Q45: =G45*H45+I45*J45 -> 0
O46: 18-25 | P46: =B46*C46+D46*E46 -> 0 | Q46: =G46*H46+I46*J46 -> 0
O47: 26-30 | P47: =B47*C47+D47*E47 -> 0 | Q47: =G47*H47+I47*J47 -> 0
O48: 31-35 | P48: =B48*C48+D48*E48 -> 0 | Q48: =G48*H48+I48*J48 -> 0
O49: 36-40 | P49: =B49*C49+D49*E49 -> 0 | Q49: =G49*H49+I49*J49 -> 0
O50: 41-45 | P50: =B50*C50+D50*E50 -> 0 | Q50: =G50*H50+I50*J50 -> 0
O51: 46-50 | P51: =B51*C51+D51*E51 -> 0 | Q51: =G51*H51+I51*J51 -> 0
O52: 51-55 | P52: =B52*C52+D52*E52 -> 0 | Q52: =G52*H52+I52*J52 -> 0
O53: 56-59 | P53: =B53*C53+D53*E53 -> 0 | Q53: =G53*H53+I53*J53 -> 0
O54: 60-64 | P54: =B54*C54+D54*E54 -> 0 | Q54: =G54*H54+I54*J54 -> 0
O55: 65-99 | P55: =B55*C55+D55*E55 -> 0 | Q55: =G55*H55+I55*J55 -> 0
A56: Subtotals | C56: =SUM(C44:C55) -> 0 | E56: =SUM(E44:E55) -> 0 | H56: =SUM(H44:H55) -> 0 | J56: =SUM(J44:J55) -> 0 | O56: Subtotals | P56: =SUM(P44:P55) -> 0 | Q56: =SUM(Q44:Q55) -> 0
A57: For members 65 years old & above, the premium quoted is INDICATIVE only and subject to completion of the Medical Application Form (MAF), Medical Examination Report (MER). Further blood tests, and ECG are required for 70+ years old members.
A58: Maternity Premium (18-45) | C58: =C60*C59 -> 0 | G58: Category Premium | I58: =P56+C58+Q56 -> 0 | N58: #N/A
A59: Census | G59: Category Members | I59: =SUM(C44:C55,E44:E55,H44:H55,J44:J55) -> 0
A60: Average | G60: Average | I60: =I58/I59 -> #DIV/0!
A64: Category C
B66: PRINCIPAL | G66: DEPENDENTS | P66: Cat C
A67: Age Range | B67: Premium | C67: Male | D67: Premium | E67: Female | G67: Premium | H67: Male | I67: Premium | J67: Female | P67: Principal | Q67: Dependents
O68: 0-10 | P68: =B68*C68+D68*E68 -> 0 | Q68: =G68*H68+I68*J68 -> 0
O69: 11-17 | P69: =B69*C69+D69*E69 -> 0 | Q69: =G69*H69+I69*J69 -> 0
O70: 18-25 | P70: =B70*C70+D70*E70 -> 0 | Q70: =G70*H70+I70*J70 -> 0
O71: 26-30 | P71: =B71*C71+D71*E71 -> 0 | Q71: =G71*H71+I71*J71 -> 0
O72: 31-35 | P72: =B72*C72+D72*E72 -> 0 | Q72: =G72*H72+I72*J72 -> 0
O73: 36-40 | P73: =B73*C73+D73*E73 -> 0 | Q73: =G73*H73+I73*J73 -> 0
O74: 41-45 | P74: =B74*C74+D74*E74 -> 0 | Q74: =G74*H74+I74*J74 -> 0
O75: 46-50 | P75: =B75*C75+D75*E75 -> 0 | Q75: =G75*H75+I75*J75 -> 0
O76: 51-55 | P76: =B76*C76+D76*E76 -> 0 | Q76: =G76*H76+I76*J76 -> 0
O77: 56-59 | P77: =B77*C77+D77*E77 -> 0 | Q77: =G77*H77+I77*J77 -> 0
O78: 60-64 | P78: =B78*C78+D78*E78 -> 0 | Q78: =G78*H78+I78*J78 -> 0
O79: 65-99 | P79: =B79*C79+D79*E79 -> 0 | Q79: =G79*H79+I79*J79 -> 0
A80: Subtotals | C80: 0 | E80: 0 | H80: 0 | J80: 0 | O80: Subtotals | P80: =SUM(P68:P79) -> 0 | Q80: =SUM(Q68:Q79) -> 0
A81: For members 65 years old & above, the premium quoted is INDICATIVE only and subject to completion of the Medical Application Form (MAF), Medical Examination Report (MER). Further blood tests, and ECG are required for 70+ years old members.
A82: Maternity Premium (18-45) | C82: =C84*C83 -> 0 | G82: Category Premium | I82: =P80+C82 -> 0
A83: Census | G83: Category Members | I83: =SUM(C68:C79,E68:E79,H68:H79,J68:J79) -> 0
A84: Average | G84: Average | I84: =I82/I83 -> #DIV/0!
A88: Category D
B90: PRINCIPAL | G90: DEPENDENTS | P90: Cat D
A91: Age Range | B91: Premium | C91: Male | D91: Premium | E91: Female | G91: Premium | H91: Male | I91: Premium | J91: Female | P91: Principal | Q91: Dependents
O92: 0-10 | P92: =B92*C92+D92*E92 -> 0 | Q92: =G92*H92+I92*J92 -> 0
O93: 11-17 | P93: =B93*C93+D93*E93 -> 0 | Q93: =G93*H93+I93*J93 -> 0
O94: 18-25 | P94: =B94*C94+D94*E94 -> 0 | Q94: =G94*H94+I94*J94 -> 0
O95: 26-30 | P95: =B95*C95+D95*E95 -> 0 | Q95: =G95*H95+I95*J95 -> 0
O96: 31-35 | P96: =B96*C96+D96*E96 -> 0 | Q96: =G96*H96+I96*J96 -> 0
O97: 36-40 | P97: =B97*C97+D97*E97 -> 0 | Q97: =G97*H97+I97*J97 -> 0
O98: 41-45 | P98: =B98*C98+D98*E98 -> 0 | Q98: =G98*H98+I98*J98 -> 0
O99: 46-50 | P99: =B99*C99+D99*E99 -> 0 | Q99: =G99*H99+I99*J99 -> 0
O100: 51-55 | P100: =B100*C100+D100*E100 -> 0 | Q100: =G100*H100+I100*J100 -> 0
O101: 56-59 | P101: =B101*C101+D101*E101 -> 0 | Q101: =G101*H101+I101*J101 -> 0
O102: 60-64 | P102: =B102*C102+D102*E102 -> 0 | Q102: =G102*H102+I102*J102 -> 0
O103: 65-99 | P103: =B103*C103+D103*E103 -> 0 | Q103: =G103*H103+I103*J103 -> 0
A104: Subtotals | C104: 0 | E104: 0 | H104: 0 | J104: 0 | O104: Subtotals | P104: =SUM(P92:P103) -> 0 | Q104: =SUM(Q92:Q103) -> 0
A105: For members 65 years old & above, the premium quoted is INDICATIVE only and subject to completion of the Medical Application Form (MAF), Medical Examination Report (MER). Further blood tests, and ECG are required for 70+ years old members.
A106: Maternity Premium (18-45) | C106: =C108*C107 -> 0 | G106: Category Premium | I106: =P104+C106 -> 0
A107: Census | G107: Category Members | I107: =SUM(C92:C103,E92:E103,H92:H103,J92:J103) -> 0
A108: Average | G108: Average | I108: =I106/I107 -> #DIV/0!

Sheet Confirmation Info Sheet
A1: Company Name | B1: ='Approved Quote'!C1 -> MGH LOGISTICS L.L.C | E1: Categories | F1: 1 | G1: Subgroups | H1: 1
A2: Start Date | B2: {='Approved Quote'!C2:D2} -> 46105 | C2: 0 | E2: Confirmed Premium | F2: ='Approved Quote'!I8 -> 165194 | G2: Members | H2: ='Approved Quote'!I35+'Approved Quote'!I59+'Approved Quote'!I83+'Approved Quote'!I107 -> 17
A3: Broker/Contact Person | B3: ='Approved Quote'!C3 -> Savington International Insurance Brokers LLC | E3: Confirmed Quotation No.
A4: Commission | B4: 0.1 | E4: Final Premium (if not same as confirmed census) | F4: ='Premium Table'!U14 -> Same as confirmed quote | G4: Members | H4: ='Premium Table'!U15
A5: Current insurer | E5: Over 64 | F5: =COUNTIF('Final premium per member'!L6:L506,">64") -> 0 | G5: =F5/H4 -> #VALUE!
A6: Emirate | B6: Dubai | E6: LSB (Low-salary band) members | F6: 0 | G6: No
A7: Underwriter | B7: Mabel | E7: Dubai members | F7: 14
A8: Type | B8: New Business | E8: Abu Dhabi members | F8: 0
A9: Inception premium payment | B9: Annual | E9: Northern Emirates members | F9: 0
A10: Endorsement Frequency | B10: Monthly | E10: Outside UAE members | F10: 0
B12: Documents required | C12: Status | D12: Date Received | E12: Comments
B13: Census List
B14: Medical Application Form
B15: Declaration Form | E15: Clean declaration
B16: Photographs (.jpg format, Filename - member name)
B17: Continuity Certificate from Previous Insurer
B18: eKYC Form
B19: Bank Account details with IBAN of the Group/ Sub-groups
B20: Signed and Stamped TOB
B21: Ministry of Labour List
B22: Trade License copy
B23: Vat Registration Number and Certificates
B24: Establishment ID copy
B25: Name/s and Address/es to be mentioned in the Tax Invoice
B26: Salary Declaration Form (for LSB members)
B27: Other supporting document
B30: Internal documents | C30: Status | D30: Date Received | E30: Comments
B31: Premium summary | E31: Waiting for confirmation from RGA and manual AUH rates.
B32: TOB with exclusions
B33: RGA assessment | C33: N/A
B36: Confirmation steps | C36: Status | D36: Date Sent | E36: Documents to attach | F36: Comments
B37: Documents sent to NAS | E37: TOB with exclusions, Premium Summary, Tool
B38: Documents sent to QIC
B39: Documents sent to RGA | E39: Tool, Signed Quote, Census | F39: Tool, Signed Quote, Census
B40: Policy activation
B41: E-cards issuance
B42: Policy documents issuance
A44: Subject: | B44: ="QIC-HEALTHX- UAE - QS - SME - "&B1&" - UW Review" -> QIC-HEALTHX- UAE - QS - SME - MGH LOGISTICS L.L.C - UW Review
A45: Hi Amrit/Shubham,
A47: Please find attached confirmed quote, GDF (clean), census, and RGA tool for your kind checking and confirmation:
A49: Policy Name: | B49: =B1 -> MGH LOGISTICS L.L.C
A50: Policy start date: | B50: =B2 -> 46105
A51: Broker Name: | B51: =B3 -> Savington International Insurance Brokers LLC
A52: Payment Terms: | B52: ='Premium Table'!B10 -> Annual
A54: Confirmed Premium: | B54: =F2 -> 165194
A55: Confirmed Census: | B55: =H2 -> 17
A56: Final Premium: | B56: ='Final premium per member'!R2 -> 165194
A57: Final Census: | B57: ='Final premium per member'!R3 -> 17
A59: Broker commission: | B59: ='Premium Table'!O11 -> 0.1
A60: Healthx: | B60: ='Premium Table'!O14 -> 0.05
A61: TPA Fees: | B61: ='Premium Table'!O12 -> 0.05
A62: QIC Admin Fee: | B62: ='Premium Table'!O13+'Premium Table'!O15 -> 0.005
A63: Total loading: | B63: =SUM(B59:B62) -> 0.205
A64: Comments: | B64: Confirmed premium and final premium are matching.
A66: Appreciate your usual support.

Sheet Email Helper
A2: Email documents to QIC
A4: Subject: | B4: ="Confirmation - "&'Confirmation Info Sheet'!B1&" effective on "&TEXT('Confirmation Info Sheet'!B2,"dd mmm yyy") -> Confirmation - MGH LOGISTICS L.L.C effective on 24 Mar 2026
A7: Dear Minhas,
A9: ="Healthx is pleased to share the below onboarding documents for "&'Confirmation Info Sheet'!B1&":" -> Healthx is pleased to share the below onboarding documents for MGH LOGISTICS L.L.C:
A11: =IF('Confirmation Info Sheet'!C13="Completed","- "&'Confirmation Info Sheet'!B13,"")
A12: =IF('Confirmation Info Sheet'!C14="Completed","- "&'Confirmation Info Sheet'!B14,"")
A13: =IF('Confirmation Info Sheet'!C15="Completed","- "&'Confirmation Info Sheet'!B15&" ("&'Confirmation Info Sheet'!E15&")","")
A14: =IF('Confirmation Info Sheet'!C16="Completed","- "&'Confirmation Info Sheet'!B16,"")
A15: =IF('Confirmation Info Sheet'!C17="Completed","- "&'Confirmation Info Sheet'!B17,"")
A16: - eKYC form - QIC to send the link to the client?
A17: =IF('Confirmation Info Sheet'!C19="Completed","- "&'Confirmation Info Sheet'!B19,"")
A18: =IF('Confirmation Info Sheet'!C20="Completed","- "&'Confirmation Info Sheet'!B20,"")
A19: =IF('Confirmation Info Sheet'!C21="Completed","- "&'Confirmation Info Sheet'!B21,"")
A20: =IF('Confirmation Info Sheet'!C22="Completed","- "&'Confirmation Info Sheet'!B22,"")
A21: =IF('Confirmation Info Sheet'!C23="Completed","- "&'Confirmation Info Sheet'!B23,"")
A22: =IF('Confirmation Info Sheet'!C24="Completed","- "&'Confirmation Info Sheet'!B24,"")
A23: =IF('Confirmation Info Sheet'!C25="Completed","- "&'Confirmation Info Sheet'!B25,"")
A24: =IF('Confirmation Info Sheet'!C26="Completed","- "&'Confirmation Info Sheet'!B26,"")
A25: =IF('Confirmation Info Sheet'!C27="Completed","- "&'Confirmation Info Sheet'!E27,"")
A26: - TOBs with exclusions
A27: - RGA pricing tool
A29: Policy Name | B29: ='Confirmation Info Sheet'!B1 -> MGH LOGISTICS L.L.C
A30: Policy start date | B30: ='Confirmation Info Sheet'!B2 -> 46105
A31: Broker Name | B31: ='Confirmation Info Sheet'!B3 -> Savington International Insurance Brokers LLC
A32: Payment Terms | B32: ='Confirmation Info Sheet'!B9 -> Annual
A33: Confirmed quote | B33: ='Premium Table'!U11 -> 165194
A34: Premium as per final census | B34: ='Premium Table'!U14 -> Same as confirmed quote
A36: ='Premium Table'!N11 -> Broker | B36: ='Premium Table'!O11 -> 0.1
A37: ='Premium Table'!N12 -> NAS (TPA) | B37: ='Premium Table'!O12 -> 0.05
A38: ='Premium Table'!N13 -> QIC (Insurer) | B38: ='Premium Table'!O13+'Premium Table'!O15 -> 0.005
A39: ='Premium Table'!N14 -> HealthX (Admin) | B39: ='Premium Table'!O14 -> 0.05
A41: Please advise if you require anything further.
A43: Email documents to NAS
A45: To:
A46: Healthxendorsments@nas.ae
A47: Cheri.Jijo@nas.ae
A49: Cc: QIC team
A51: Subject: | B51: ="Confirmation - "&'Confirmation Info Sheet'!B1&" effective on "&TEXT('Confirmation Info Sheet'!B2,"dd mmm yyy") -> Confirmation - MGH LOGISTICS L.L.C effective on 24 Mar 2026
A54: Dear NAS team,
A56: Healthx is pleased to share the onboarding documents for policy activation.
A58: 1. Table of Benefits with Exclusions
A59: 2. Premium summary
A60: 3. Employee census list
A61: 4. Group declaration / MAF (if available)
A63: Policy Holder | B63: ='Confirmation Info Sheet'!B1 -> MGH LOGISTICS L.L.C
A64: Policy start date | B64: ='Confirmation Info Sheet'!B2 -> 46105
A65: Broker Name | B65: ='Confirmation Info Sheet'!B3 -> Savington International Insurance Brokers LLC
A67: Looking forward to receiving the e-cards.

Sheet Premium Table
A3: Product | B3: QIC Dubai Branch - Healthx | N3: FLAT FIXED FEES
A4: Policy Holder | B4: ='Confirmation Info Sheet'!B1 -> MGH LOGISTICS L.L.C | N4: DHA Basmah Fee | O4: 19 | P4: Paid by client
N5: DHA HCV Fee | O5: 18 | P5: Paid by client
A6: Policy Start Date | B6: ='Confirmation Info Sheet'!B2 -> 46105 | N6: TruDoc Fee | O6: 12 | P6: Paid by Healthx
A7: Policy End Date | B7: =DATE(YEAR(B6)+1,MONTH(B6),DAY(B6))-1 -> 46469 | N7: Slash Data Fee | O7: 0
A8: Policy Type | B8: ='Confirmation Info Sheet'!B8 -> New Business
O9: FEES IN %
A10: Inception premium payment | B10: ='Confirmation Info Sheet'!B9 -> Annual | O10: HSB | Q10: LSB
A11: Endorsement Frequency | B11: ='Confirmation Info Sheet'!B10 -> Monthly | N11: Broker | O11: ='Confirmation Info Sheet'!B4 -> 0.1 | Q11: 0.05 | T11: Confirmed Quote | U11: ='Approved Quote'!I8 -> 165194 | W11: Per Capita | X11: =U11/U12 -> 9717.2941
N12: NAS (TPA) | O12: 0.05 | Q12: 0.05 | T12: Members | U12: ='Confirmation Info Sheet'!H2 -> 17
A13: Underwriter | B13: Mabel Orleans | G13: 46111 | N13: QIC (Insurer) | O13: 0 | Q13: =O13+((O11-Q11)/2) -> 0.025
A14: Validated by | N14: HealthX (Admin) | O14: 0.05 | Q14: =O14+((O11-Q11)/2) -> 0.075 | T14: Final Premium | U14: =IF(U11='Final premium per member'!R2,"Same as confirmed quote",'Final premium per member'!R2) -> Same as confirmed quote | W14: Per Capita | X14: =IF(U11='Final premium per member'!R2,"",U14/U15)
N15: Insurance Levy | O15: 0.005 | Q15: 0.005 | T15: Members | U15: =IF(U11='Final premium per member'!R2,"",'Final premium per member'!R3)
N16: TOTAL FEES | O16: =SUM(O11:O15) -> 0.205 | Q16: =SUM(Q11:Q15) -> 0.205
T17: Premium Variance | U17: =IF(ISERROR(U14/U11-1),"",U14/U11-1)
A19: Category | B19: Age Band | C19: =N4 -> DHA Basmah Fee | D19: =N5 -> DHA HCV Fee | E19: =N6 -> TruDoc Fee | F19: =N7 -> Slash Data Fee | G19: GROSS PREMIUM (MALE) | H19: GROSS PREMIUM (FEMALE) | I19: =N11 -> Broker | J19: =N12 -> NAS (TPA) | K19: =N13 -> QIC (Insurer) | L19: =N14 -> HealthX (Admin) | M19: =N15 -> Insurance Levy | N19: NET PREMIUM (MALE) | O19: NET PREMIUM (FEMALE) | T19: Members Variance | U19: =IF(ISERROR(U15/U12-1),"",U15/U12-1) | V19: If more than -10%, either revised quote or seek approval from RGA
A20: Category A | Q20: Net Rates Check | T20: Per Capita Variance | U20: =IF(ISERROR(X14/X11-1),"",X14/X11-1)
A21: Cat A (EMP) | B21: ='Approved Quote'!A21 -> 11 - 17 | C21: 19 | D21: 18 | E21: 12 | G21: ='Final premium per member'!W7 -> 3157 | H21: ='Final premium per member'!X7 -> 3217 | I21: =$O$11 -> 0.1 | J21: =$O$12 -> 0.05 | K21: =$O$13 -> 0 | L21: =$O$14 -> 0.05 | M21: =$O$15 -> 0.005 | N21: =IF(G21="","",G21*(1-$O$16)) -> 2509.815 | O21: =IF(H21="","",H21*(1-$O$16)) -> 2557.515 | Q21: =N21-#REF! -> #REF! | R21: =O21-#REF! -> #REF!
A22: Cat A (EMP) | B22: ='Approved Quote'!A22 -> 18 - 25 | C22: 19 | D22: 18 | E22: 12 | G22: ='Final premium per member'!W8 -> 5253 | H22: ='Final premium per member'!X8 -> 5997 | I22: =$O$11 -> 0.1 | J22: =$O$12 -> 0.05 | K22: =$O$13 -> 0 | L22: =$O$14 -> 0.05 | M22: =$O$15 -> 0.005 | N22: =IF(G22="","",G22*(1-$O$16)) -> 4176.135 | O22: =IF(H22="","",H22*(1-$O$16)) -> 4767.615 | Q22: =N22-#REF! -> #REF! | R22: =O22-#REF! -> #REF! | T22: Additional Loading
A23: Cat A (EMP) | B23: ='Approved Quote'!A23 -> 26 - 30 | C23: 19 | D23: 18 | E23: 12 | G23: ='Final premium per member'!W9 -> 5833 | H23: ='Final premium per member'!X9 -> 7304 | I23: =$O$11 -> 0.1 | J23: =$O$12 -> 0.05 | K23: =$O$13 -> 0 | L23: =$O$14 -> 0.05 | M23: =$O$15 -> 0.005 | N23: =IF(G23="","",G23*(1-$O$16)) -> 4637.235 | O23: =IF(H23="","",H23*(1-$O$16)) -> 5806.68 | Q23: =N23-#REF! -> #REF! | R23: =O23-#REF! -> #REF!
A24: Cat A (EMP) | B24: ='Approved Quote'!A24 -> 31 - 35 | C24: 19 | D24: 18 | E24: 12 | G24: ='Final premium per member'!W10 -> 6915 | H24: ='Final premium per member'!X10 -> 8606 | I24: =$O$11 -> 0.1 | J24: =$O$12 -> 0.05 | K24: =$O$13 -> 0 | L24: =$O$14 -> 0.05 | M24: =$O$15 -> 0.005 | N24: =IF(G24="","",G24*(1-$O$16)) -> 5497.425 | O24: =IF(H24="","",H24*(1-$O$16)) -> 6841.77 | Q24: =N24-#REF! -> #REF! | R24: =O24-#REF! -> #REF! | T24: Net Loading | U24: =U25*(1-O16) -> 0
A25: Cat A (EMP) | B25: ='Approved Quote'!A25 -> 36 - 40 | C25: 19 | D25: 18 | E25: 12 | G25: ='Final premium per member'!W11 -> 8397 | H25: ='Final premium per member'!X11 -> 10589 | I25: =$O$11 -> 0.1 | J25: =$O$12 -> 0.05 | K25: =$O$13 -> 0 | L25: =$O$14 -> 0.05 | M25: =$O$15 -> 0.005 | N25: =IF(G25="","",G25*(1-$O$16)) -> 6675.615 | O25: =IF(H25="","",H25*(1-$O$16)) -> 8418.255 | Q25: =N25-#REF! -> #REF! | R25: =O25-#REF! -> #REF! | T25: Gross Loading | U25: ='Approved Quote'!I11 -> 0
A26: Cat A (EMP) | B26: ='Approved Quote'!A26 -> 41 - 45 | C26: 19 | D26: 18 | E26: 12 | G26: ='Final premium per member'!W12 -> 8785 | H26: ='Final premium per member'!X12 -> 12068 | I26: =$O$11 -> 0.1 | J26: =$O$12 -> 0.05 | K26: =$O$13 -> 0 | L26: =$O$14 -> 0.05 | M26: =$O$15 -> 0.005 | N26: =IF(G26="","",G26*(1-$O$16)) -> 6984.075 | O26: =IF(H26="","",H26*(1-$O$16)) -> 9594.06 | Q26: =N26-#REF! -> #REF! | R26: =O26-#REF! -> #REF!
A27: Cat A (EMP) | B27: ='Approved Quote'!A27 -> 46 - 50 | C27: 19 | D27: 18 | E27: 12 | G27: ='Final premium per member'!W13 -> 11304 | H27: ='Final premium per member'!X13 -> 14951 | I27: =$O$11 -> 0.1 | J27: =$O$12 -> 0.05 | K27: =$O$13 -> 0 | L27: =$O$14 -> 0.05 | M27: =$O$15 -> 0.005 | N27: =IF(G27="","",G27*(1-$O$16)) -> 8986.68 | O27: =IF(H27="","",H27*(1-$O$16)) -> 11886.045 | Q27: =N27-#REF! -> #REF! | R27: =O27-#REF! -> #REF!
A28: Cat A (EMP) | B28: ='Approved Quote'!A28 -> 51 - 55 | C28: 19 | D28: 18 | E28: 12 | G28: ='Final premium per member'!W14 -> 14946 | H28: ='Final premium per member'!X14 -> 19507 | I28: =$O$11 -> 0.1 | J28: =$O$12 -> 0.05 | K28: =$O$13 -> 0 | L28: =$O$14 -> 0.05 | M28: =$O$15 -> 0.005 | N28: =IF(G28="","",G28*(1-$O$16)) -> 11882.07 | O28: =IF(H28="","",H28*(1-$O$16)) -> 15508.065 | Q28: =N28-#REF! -> #REF! | R28: =O28-#REF! -> #REF! | T28: Member | U28: DOB | V28: Gender | W28: Category | X28: Relation | Y28: Net Loading | Z28: Gross Loading | AA28: Declaration | AB28: Comments
A29: Cat A (EMP) | B29: ='Approved Quote'!A29 -> 56 - 59 | C29: 19 | D29: 18 | E29: 12 | G29: ='Final premium per member'!W15 -> 20128 | H29: ='Final premium per member'!X15 -> 23729 | I29: =$O$11 -> 0.1 | J29: =$O$12 -> 0.05 | K29: =$O$13 -> 0 | L29: =$O$14 -> 0.05 | M29: =$O$15 -> 0.005 | N29: =IF(G29="","",G29*(1-$O$16)) -> 16001.76 | O29: =IF(H29="","",H29*(1-$O$16)) -> 18864.555 | Q29: =N29-#REF! -> #REF! | R29: =O29-#REF! -> #REF!
A30: Cat A (EMP) | B30: ='Approved Quote'!A30 -> 60 - 64 | C30: 19 | D30: 18 | E30: 12 | G30: ='Final premium per member'!W16 -> 24628 | H30: ='Final premium per member'!X16 -> 28071 | I30: =$O$11 -> 0.1 | J30: =$O$12 -> 0.05 | K30: =$O$13 -> 0 | L30: =$O$14 -> 0.05 | M30: =$O$15 -> 0.005 | N30: =IF(G30="","",G30*(1-$O$16)) -> 19579.26 | O30: =IF(H30="","",H30*(1-$O$16)) -> 22316.445 | Q30: =N30-#REF! -> #REF! | R30: =O30-#REF! -> #REF!
A31: Cat A (EMP) | B31: ='Approved Quote'!A31 -> 65 - 99 | G31: ='Final premium per member'!W17 -> 43786 | H31: ='Final premium per member'!X17 -> 49985 | I31: =$O$11 -> 0.1 | J31: =$O$12 -> 0.05 | K31: =$O$13 -> 0 | L31: =$O$14 -> 0.05 | M31: =$O$15 -> 0.005 | N31: =IF(G31="","",G31*(1-$O$16)) -> 34809.87 | O31: =IF(H31="","",H31*(1-$O$16)) -> 39738.075 | Q31: =N32-#REF! -> #REF! | R31: =O32-#REF! -> #REF!
A32: Cat A (DEP) | B32: ='Approved Quote'!A20 -> 0 - 10 | C32: 19 | D32: 18 | E32: 12 | G32: ='Final premium per member'!Y6 -> 6499 | H32: ='Final premium per member'!Z6 -> 5234 | I32: =$O$11 -> 0.1 | J32: =$O$12 -> 0.05 | K32: =$O$13 -> 0 | L32: =$O$14 -> 0.05 | M32: =$O$15 -> 0.005 | N32: =IF(G32="","",G32*(1-$O$16)) -> 5166.705 | O32: =IF(H32="","",H32*(1-$O$16)) -> 4161.03 | Q32: =N33-#REF! -> #REF! | R32: =O33-#REF! -> #REF!
A33: Cat A (DEP) | B33: ='Approved Quote'!A21 -> 11 - 17 | C33: 19 | D33: 18 | E33: 12 | G33: ='Final premium per member'!Y7 -> 4674 | H33: ='Final premium per member'!Z7 -> 4750 | I33: =$O$11 -> 0.1 | J33: =$O$12 -> 0.05 | K33: =$O$13 -> 0 | L33: =$O$14 -> 0.05 | M33: =$O$15 -> 0.005 | N33: =IF(G33="","",G33*(1-$O$16)) -> 3715.83 | O33: =IF(H33="","",H33*(1-$O$16)) -> 3776.25 | Q33: =N34-#REF! -> #REF! | R33: =O34-#REF! -> #REF! | Y33: =SUM(Y29:Y32) -> 0 | Z33: =SUM(Z29:Z32) -> 0
A34: Cat A (DEP) | B34: ='Approved Quote'!A22 -> 18 - 25 | C34: 19 | D34: 18 | E34: 12 | G34: ='Final premium per member'!Y8 -> 5253 | H34: ='Final premium per member'!Z8 -> 5997 | I34: =$O$11 -> 0.1 | J34: =$O$12 -> 0.05 | K34: =$O$13 -> 0 | L34: =$O$14 -> 0.05 | M34: =$O$15 -> 0.005 | N34: =IF(G34="","",G34*(1-$O$16)) -> 4176.135 | O34: =IF(H34="","",H34*(1-$O$16)) -> 4767.615 | Q34: =N35-#REF! -> #REF! | R34: =O35-#REF! -> #REF!
A35: Cat A (DEP) | B35: ='Approved Quote'!A23 -> 26 - 30 | C35: 19 | D35: 18 | E35: 12 | G35: ='Final premium per member'!Y9 -> 5833 | H35: ='Final premium per member'!Z9 -> 7304 | I35: =$O$11 -> 0.1 | J35: =$O$12 -> 0.05 | K35: =$O$13 -> 0 | L35: =$O$14 -> 0.05 | M35: =$O$15 -> 0.005 | N35: =IF(G35="","",G35*(1-$O$16)) -> 4637.235 | O35: =IF(H35="","",H35*(1-$O$16)) -> 5806.68 | Q35: =N36-#REF! -> #REF! | R35: =O36-#REF! -> #REF!
A36: Cat A (DEP) | B36: ='Approved Quote'!A24 -> 31 - 35 | C36: 19 | D36: 18 | E36: 12 | G36: ='Final premium per member'!Y10 -> 6915 | H36: ='Final premium per member'!Z10 -> 8606 | I36: =$O$11 -> 0.1 | J36: =$O$12 -> 0.05 | K36: =$O$13 -> 0 | L36: =$O$14 -> 0.05 | M36: =$O$15 -> 0.005 | N36: =IF(G36="","",G36*(1-$O$16)) -> 5497.425 | O36: =IF(H36="","",H36*(1-$O$16)) -> 6841.77 | Q36: =N37-#REF! -> #REF! | R36: =O37-#REF! -> #REF!
A37: Cat A (DEP) | B37: ='Approved Quote'!A25 -> 36 - 40 | C37: 19 | D37: 18 | E37: 12 | G37: ='Final premium per member'!Y11 -> 8397 | H37: ='Final premium per member'!Z11 -> 10589 | I37: =$O$11 -> 0.1 | J37: =$O$12 -> 0.05 | K37: =$O$13 -> 0 | L37: =$O$14 -> 0.05 | M37: =$O$15 -> 0.005 | N37: =IF(G37="","",G37*(1-$O$16)) -> 6675.615 | O37: =IF(H37="","",H37*(1-$O$16)) -> 8418.255 | Q37: =N38-#REF! -> #REF! | R37: =O38-#REF! -> #REF!
A38: Cat A (DEP) | B38: ='Approved Quote'!A26 -> 41 - 45 | C38: 19 | D38: 18 | E38: 12 | G38: ='Final premium per member'!Y12 -> 8795 | H38: ='Final premium per member'!Z12 -> 12068 | I38: =$O$11 -> 0.1 | J38: =$O$12 -> 0.05 | K38: =$O$13 -> 0 | L38: =$O$14 -> 0.05 | M38: =$O$15 -> 0.005 | N38: =IF(G38="","",G38*(1-$O$16)) -> 6992.025 | O38: =IF(H38="","",H38*(1-$O$16)) -> 9594.06 | Q38: =N39-#REF! -> #REF! | R38: =O39-#REF! -> #REF!
A39: Cat A (DEP) | B39: ='Approved Quote'!A27 -> 46 - 50 | C39: 19 | D39: 18 | E39: 12 | G39: ='Final premium per member'!Y13 -> 11304 | H39: ='Final premium per member'!Z13 -> 14951 | I39: =$O$11 -> 0.1 | J39: =$O$12 -> 0.05 | K39: =$O$13 -> 0 | L39: =$O$14 -> 0.05 | M39: =$O$15 -> 0.005 | N39: =IF(G39="","",G39*(1-$O$16)) -> 8986.68 | O39: =IF(H39="","",H39*(1-$O$16)) -> 11886.045 | Q39: =N40-#REF! -> #REF! | R39: =O40-#REF! -> #REF!
A40: Cat A (DEP) | B40: ='Approved Quote'!A28 -> 51 - 55 | C40: 19 | D40: 18 | E40: 12 | G40: ='Final premium per member'!Y14 -> 14946 | H40: ='Final premium per member'!Z14 -> 19507 | I40: =$O$11 -> 0.1 | J40: =$O$12 -> 0.05 | K40: =$O$13 -> 0 | L40: =$O$14 -> 0.05 | M40: =$O$15 -> 0.005 | N40: =IF(G40="","",G40*(1-$O$16)) -> 11882.07 | O40: =IF(H40="","",H40*(1-$O$16)) -> 15508.065 | Q40: =N41-#REF! -> #REF! | R40: =O41-#REF! -> #REF!
A41: Cat A (DEP) | B41: ='Approved Quote'!A29 -> 56 - 59 | C41: 19 | D41: 18 | E41: 12 | G41: ='Final premium per member'!Y15 -> 20128 | H41: ='Final premium per member'!Z15 -> 23729 | I41: =$O$11 -> 0.1 | J41: =$O$12 -> 0.05 | K41: =$O$13 -> 0 | L41: =$O$14 -> 0.05 | M41: =$O$15 -> 0.005 | N41: =IF(G41="","",G41*(1-$O$16)) -> 16001.76 | O41: =IF(H41="","",H41*(1-$O$16)) -> 18864.555 | Q41: =N42-#REF! -> #REF! | R41: =O42-#REF! -> #REF!
A42: Cat A (DEP) | B42: ='Approved Quote'!A30 -> 60 - 64 | C42: 19 | D42: 18 | E42: 12 | G42: ='Final premium per member'!Y16 -> 24628 | H42: ='Final premium per member'!Z16 -> 28071 | I42: =$O$11 -> 0.1 | J42: =$O$12 -> 0.05 | K42: =$O$13 -> 0 | L42: =$O$14 -> 0.05 | M42: =$O$15 -> 0.005 | N42: =IF(G42="","",G42*(1-$O$16)) -> 19579.26 | O42: =IF(H42="","",H42*(1-$O$16)) -> 22316.445
A43: Cat A (DEP) | B43: ='Approved Quote'!A31 -> 65 - 99 | G43: ='Final premium per member'!Y17 -> 43786 | H43: ='Final premium per member'!Z17 -> 49985 | I43: =$O$11 -> 0.1 | J43: =$O$12 -> 0.05 | K43: =$O$13 -> 0 | L43: =$O$14 -> 0.05 | M43: =$O$15 -> 0.005 | N43: =IF(G43="","",G43*(1-$O$16)) -> 34809.87 | O43: =IF(H43="","",H43*(1-$O$16)) -> 39738.075
A44: Cat A (EMPDEPMAT) | B44: =MID('Approved Quote'!A34,20,5) -> 18-45 | C44: 19 | D44: 18 | E44: 12 | H44: ='Final premium per member'!W2 -> 5244 | I44: =$O$11 -> 0.1 | J44: =$O$12 -> 0.05 | K44: =$O$13 -> 0 | L44: =$O$14 -> 0.05 | M44: =$O$15 -> 0.005 | N44: =IF(G44="","",G44*(1-$O$16)) | O44: =IF(H44="","",H44*(1-$O$16)) -> 4168.98 | P44: additional maternity premium
A45: Category B
A46: Cat B (EMP) | B46: ='Approved Quote'!A45 -> 0 | C46: 19 | D46: 18 | E46: 12 | G46: ='Final premium per member'!AA7 -> 0 | H46: ='Final premium per member'!AB7 -> 0 | I46: =$O$11 -> 0.1 | J46: =$O$12 -> 0.05 | K46: =$O$13 -> 0 | L46: =$O$14 -> 0.05 | M46: =$O$15 -> 0.005 | N46: =IF(G46="","",G46*(1-$O$16)) -> 0 | O46: =IF(H46="","",H46*(1-$O$16)) -> 0 | Q46: =N46-#REF! -> #REF! | R46: =O46-#REF! -> #REF!
A47: Cat B (EMP) | B47: ='Approved Quote'!A46 -> 0 | C47: 19 | D47: 18 | E47: 12 | G47: ='Final premium per member'!AA8 -> 0 | H47: ='Final premium per member'!AB8 -> 0 | I47: =$O$11 -> 0.1 | J47: =$O$12 -> 0.05 | K47: =$O$13 -> 0 | L47: =$O$14 -> 0.05 | M47: =$O$15 -> 0.005 | N47: =IF(G47="","",G47*(1-$O$16)) -> 0 | O47: =IF(H47="","",H47*(1-$O$16)) -> 0 | Q47: =N47-#REF! -> #REF! | R47: =O47-#REF! -> #REF!
A48: Cat B (EMP) | B48: ='Approved Quote'!A47 -> 0 | C48: 19 | D48: 18 | E48: 12 | G48: ='Final premium per member'!AA9 -> 0 | H48: ='Final premium per member'!AB9 -> 0 | I48: =$O$11 -> 0.1 | J48: =$O$12 -> 0.05 | K48: =$O$13 -> 0 | L48: =$O$14 -> 0.05 | M48: =$O$15 -> 0.005 | N48: =IF(G48="","",G48*(1-$O$16)) -> 0 | O48: =IF(H48="","",H48*(1-$O$16)) -> 0 | Q48: =N48-#REF! -> #REF! | R48: =O48-#REF! -> #REF!
A49: Cat B (EMP) | B49: ='Approved Quote'!A48 -> 0 | C49: 19 | D49: 18 | E49: 12 | G49: ='Final premium per member'!AA10 -> 0 | H49: ='Final premium per member'!AB10 -> 0 | I49: =$O$11 -> 0.1 | J49: =$O$12 -> 0.05 | K49: =$O$13 -> 0 | L49: =$O$14 -> 0.05 | M49: =$O$15 -> 0.005 | N49: =IF(G49="","",G49*(1-$O$16)) -> 0 | O49: =IF(H49="","",H49*(1-$O$16)) -> 0 | Q49: =N49-#REF! -> #REF! | R49: =O49-#REF! -> #REF!
A50: Cat B (EMP) | B50: ='Approved Quote'!A49 -> 0 | C50: 19 | D50: 18 | E50: 12 | G50: ='Final premium per member'!AA11 -> 0 | H50: ='Final premium per member'!AB11 -> 0 | I50: =$O$11 -> 0.1 | J50: =$O$12 -> 0.05 | K50: =$O$13 -> 0 | L50: =$O$14 -> 0.05 | M50: =$O$15 -> 0.005 | N50: =IF(G50="","",G50*(1-$O$16)) -> 0 | O50: =IF(H50="","",H50*(1-$O$16)) -> 0 | Q50: =N50-#REF! -> #REF! | R50: =O50-#REF! -> #REF!
A51: Cat B (EMP) | B51: ='Approved Quote'!A50 -> 0 | C51: 19 | D51: 18 | E51: 12 | G51: ='Final premium per member'!AA12 -> 0 | H51: ='Final premium per member'!AB12 -> 0 | I51: =$O$11 -> 0.1 | J51: =$O$12 -> 0.05 | K51: =$O$13 -> 0 | L51: =$O$14 -> 0.05 | M51: =$O$15 -> 0.005 | N51: =IF(G51="","",G51*(1-$O$16)) -> 0 | O51: =IF(H51="","",H51*(1-$O$16)) -> 0 | Q51: =N51-#REF! -> #REF! | R51: =O51-#REF! -> #REF!
A52: Cat B (EMP) | B52: ='Approved Quote'!A51 -> 0 | C52: 19 | D52: 18 | E52: 12 | G52: ='Final premium per member'!AA13 -> 0 | H52: ='Final premium per member'!AB13 -> 0 | I52: =$O$11 -> 0.1 | J52: =$O$12 -> 0.05 | K52: =$O$13 -> 0 | L52: =$O$14 -> 0.05 | M52: =$O$15 -> 0.005 | N52: =IF(G52="","",G52*(1-$O$16)) -> 0 | O52: =IF(H52="","",H52*(1-$O$16)) -> 0 | Q52: =N52-#REF! -> #REF! | R52: =O52-#REF! -> #REF!
A53: Cat B (EMP) | B53: ='Approved Quote'!A52 -> 0 | C53: 19 | D53: 18 | E53: 12 | G53: ='Final premium per member'!AA14 -> 0 | H53: ='Final premium per member'!AB14 -> 0 | I53: =$O$11 -> 0.1 | J53: =$O$12 -> 0.05 | K53: =$O$13 -> 0 | L53: =$O$14 -> 0.05 | M53: =$O$15 -> 0.005 | N53: =IF(G53="","",G53*(1-$O$16)) -> 0 | O53: =IF(H53="","",H53*(1-$O$16)) -> 0 | Q53: =N53-#REF! -> #REF! | R53: =O53-#REF! -> #REF!
A54: Cat B (EMP) | B54: ='Approved Quote'!A53 -> 0 | C54: 19 | D54: 18 | E54: 12 | G54: ='Final premium per member'!AA15 -> 0 | H54: ='Final premium per member'!AB15 -> 0 | I54: =$O$11 -> 0.1 | J54: =$O$12 -> 0.05 | K54: =$O$13 -> 0 | L54: =$O$14 -> 0.05 | M54: =$O$15 -> 0.005 | N54: =IF(G54="","",G54*(1-$O$16)) -> 0 | O54: =IF(H54="","",H54*(1-$O$16)) -> 0 | Q54: =N54-#REF! -> #REF! | R54: =O54-#REF! -> #REF!
A55: Cat B (EMP) | B55: ='Approved Quote'!A54 -> 0 | C55: 19 | D55: 18 | E55: 12 | G55: ='Final premium per member'!AA16 -> 0 | H55: ='Final premium per member'!AB16 -> 0 | I55: =$O$11 -> 0.1 | J55: =$O$12 -> 0.05 | K55: =$O$13 -> 0 | L55: =$O$14 -> 0.05 | M55: =$O$15 -> 0.005 | N55: =IF(G55="","",G55*(1-$O$16)) -> 0 | O55: =IF(H55="","",H55*(1-$O$16)) -> 0 | Q55: =N55-#REF! -> #REF! | R55: =O55-#REF! -> #REF!
A56: Cat B (EMP) | B56: ='Approved Quote'!A55 -> 0 | G56: ='Final premium per member'!AA17 -> 0 | H56: ='Final premium per member'!AB17 -> 0 | I56: =$O$11 -> 0.1 | J56: =$O$12 -> 0.05 | K56: =$O$13 -> 0 | L56: =$O$14 -> 0.05 | M56: =$O$15 -> 0.005 | N56: =IF(G56="","",G56*(1-$O$16)) -> 0 | O56: =IF(H56="","",H56*(1-$O$16)) -> 0 | Q56: =N56-#REF! -> #REF! | R56: =O56-#REF! -> #REF!
A57: Cat B (DEP) | B57: ='Approved Quote'!A44 -> 0 | C57: 19 | D57: 18 | E57: 12 | G57: ='Final premium per member'!AC6 -> 0 | H57: ='Final premium per member'!AD6 -> 0 | I57: =$O$11 -> 0.1 | J57: =$O$12 -> 0.05 | K57: =$O$13 -> 0 | L57: =$O$14 -> 0.05 | M57: =$O$15 -> 0.005 | N57: =IF(G57="","",G57*(1-$O$16)) -> 0 | O57: =IF(H57="","",H57*(1-$O$16)) -> 0 | Q57: =N57-#REF! -> #REF! | R57: =O57-#REF! -> #REF!
A58: Cat B (DEP) | B58: ='Approved Quote'!A45 -> 0 | C58: 19 | D58: 18 | E58: 12 | G58: ='Final premium per member'!AC7 -> 0 | H58: ='Final premium per member'!AD7 -> 0 | I58: =$O$11 -> 0.1 | J58: =$O$12 -> 0.05 | K58: =$O$13 -> 0 | L58: =$O$14 -> 0.05 | M58: =$O$15 -> 0.005 | N58: =IF(G58="","",G58*(1-$O$16)) -> 0 | O58: =IF(H58="","",H58*(1-$O$16)) -> 0 | Q58: =N58-#REF! -> #REF! | R58: =O58-#REF! -> #REF!
A59: Cat B (DEP) | B59: ='Approved Quote'!A46 -> 0 | C59: 19 | D59: 18 | E59: 12 | G59: ='Final premium per member'!AC8 -> 0 | H59: ='Final premium per member'!AD8 -> 0 | I59: =$O$11 -> 0.1 | J59: =$O$12 -> 0.05 | K59: =$O$13 -> 0 | L59: =$O$14 -> 0.05 | M59: =$O$15 -> 0.005 | N59: =IF(G59="","",G59*(1-$O$16)) -> 0 | O59: =IF(H59="","",H59*(1-$O$16)) -> 0 | Q59: =N59-#REF! -> #REF! | R59: =O59-#REF! -> #REF!
A60: Cat B (DEP) | B60: ='Approved Quote'!A47 -> 0 | C60: 19 | D60: 18 | E60: 12 | G60: ='Final premium per member'!AC9 -> 0 | H60: ='Final premium per member'!AD9 -> 0 | I60: =$O$11 -> 0.1 | J60: =$O$12 -> 0.05 | K60: =$O$13 -> 0 | L60: =$O$14 -> 0.05 | M60: =$O$15 -> 0.005 | N60: =IF(G60="","",G60*(1-$O$16)) -> 0 | O60: =IF(H60="","",H60*(1-$O$16)) -> 0 | Q60: =N60-#REF! -> #REF! | R60: =O60-#REF! -> #REF!
A61: Cat B (DEP) | B61: ='Approved Quote'!A48 -> 0 | C61: 19 | D61: 18 | E61: 12 | G61: ='Final premium per member'!AC10 -> 0 | H61: ='Final premium per member'!AD10 -> 0 | I61: =$O$11 -> 0.1 | J61: =$O$12 -> 0.05 | K61: =$O$13 -> 0 | L61: =$O$14 -> 0.05 | M61: =$O$15 -> 0.005 | N61: =IF(G61="","",G61*(1-$O$16)) -> 0 | O61: =IF(H61="","",H61*(1-$O$16)) -> 0 | Q61: =N61-#REF! -> #REF! | R61: =O61-#REF! -> #REF!
A62: Cat B (DEP) | B62: ='Approved Quote'!A49 -> 0 | C62: 19 | D62: 18 | E62: 12 | G62: ='Final premium per member'!AC11 -> 0 | H62: ='Final premium per member'!AD11 -> 0 | I62: =$O$11 -> 0.1 | J62: =$O$12 -> 0.05 | K62: =$O$13 -> 0 | L62: =$O$14 -> 0.05 | M62: =$O$15 -> 0.005 | N62: =IF(G62="","",G62*(1-$O$16)) -> 0 | O62: =IF(H62="","",H62*(1-$O$16)) -> 0 | Q62: =N62-#REF! -> #REF! | R62: =O62-#REF! -> #REF!
A63: Cat B (DEP) | B63: ='Approved Quote'!A50 -> 0 | C63: 19 | D63: 18 | E63: 12 | G63: ='Final premium per member'!AC12 -> 0 | H63: ='Final premium per member'!AD12 -> 0 | I63: =$O$11 -> 0.1 | J63: =$O$12 -> 0.05 | K63: =$O$13 -> 0 | L63: =$O$14 -> 0.05 | M63: =$O$15 -> 0.005 | N63: =IF(G63="","",G63*(1-$O$16)) -> 0 | O63: =IF(H63="","",H63*(1-$O$16)) -> 0 | Q63: =N63-#REF! -> #REF! | R63: =O63-#REF! -> #REF!
A64: Cat B (DEP) | B64: ='Approved Quote'!A51 -> 0 | C64: 19 | D64: 18 | E64: 12 | G64: ='Final premium per member'!AC13 -> 0 | H64: ='Final premium per member'!AD13 -> 0 | I64: =$O$11 -> 0.1 | J64: =$O$12 -> 0.05 | K64: =$O$13 -> 0 | L64: =$O$14 -> 0.05 | M64: =$O$15 -> 0.005 | N64: =IF(G64="","",G64*(1-$O$16)) -> 0 | O64: =IF(H64="","",H64*(1-$O$16)) -> 0 | Q64: =N64-#REF! -> #REF! | R64: =O64-#REF! -> #REF!
A65: Cat B (DEP) | B65: ='Approved Quote'!A52 -> 0 | C65: 19 | D65: 18 | E65: 12 | G65: ='Final premium per member'!AC14 -> 0 | H65: ='Final premium per member'!AD14 -> 0 | I65: =$O$11 -> 0.1 | J65: =$O$12 -> 0.05 | K65: =$O$13 -> 0 | L65: =$O$14 -> 0.05 | M65: =$O$15 -> 0.005 | N65: =IF(G65="","",G65*(1-$O$16)) -> 0 | O65: =IF(H65="","",H65*(1-$O$16)) -> 0 | Q65: =N65-#REF! -> #REF! | R65: =O65-#REF! -> #REF!
A66: Cat B (DEP) | B66: ='Approved Quote'!A53 -> 0 | C66: 19 | D66: 18 | E66: 12 | G66: ='Final premium per member'!AC15 -> 0 | H66: ='Final premium per member'!AD15 -> 0 | I66: =$O$11 -> 0.1 | J66: =$O$12 -> 0.05 | K66: =$O$13 -> 0 | L66: =$O$14 -> 0.05 | M66: =$O$15 -> 0.005 | N66: =IF(G66="","",G66*(1-$O$16)) -> 0 | O66: =IF(H66="","",H66*(1-$O$16)) -> 0 | Q66: =N66-#REF! -> #REF! | R66: =O66-#REF! -> #REF!
A67: Cat B (DEP) | B67: ='Approved Quote'!A54 -> 0 | C67: 19 | D67: 18 | E67: 12 | G67: ='Final premium per member'!AC16 -> 0 | H67: ='Final premium per member'!AD16 -> 0 | I67: =$O$11 -> 0.1 | J67: =$O$12 -> 0.05 | K67: =$O$13 -> 0 | L67: =$O$14 -> 0.05 | M67: =$O$15 -> 0.005 | N67: =IF(G67="","",G67*(1-$O$16)) -> 0 | O67: =IF(H67="","",H67*(1-$O$16)) -> 0 | Q67: =N67-#REF! -> #REF! | R67: =O67-#REF! -> #REF!
A68: Cat B (DEP) | B68: ='Approved Quote'!A55 -> 0 | G68: ='Final premium per member'!AC17 -> 0 | H68: ='Final premium per member'!AD17 -> 0 | I68: =$O$11 -> 0.1 | J68: =$O$12 -> 0.05 | K68: =$O$13 -> 0 | L68: =$O$14 -> 0.05 | M68: =$O$15 -> 0.005 | N68: =IF(G68="","",G68*(1-$O$16)) -> 0 | O68: =IF(H68="","",H68*(1-$O$16)) -> 0 | Q68: =N68-#REF! -> #REF! | R68: =O68-#REF! -> #REF!
A69: Cat B (EMPDEPMAT) | B69: =MID('Approved Quote'!A58,20,5) -> 18-45 | C69: 19 | D69: 18 | E69: 12 | H69: ='Final premium per member'!X2 -> 0 | I69: =$O$11 -> 0.1 | J69: =$O$12 -> 0.05 | K69: =$O$13 -> 0 | L69: =$O$14 -> 0.05 | M69: =$O$15 -> 0.005 | N69: =IF(G69="","",G69*(1-$O$16)) | O69: =IF(H69="","",H69*(1-$O$16)) -> 0 | P69: additional maternity premium
A70: Category C
A71: Cat C (EMP) | B71: =IF(#REF!="","",#REF!) -> #REF! | C71: 19 | D71: 18 | E71: 12 | G71: =IF(#REF!="NA","",ROUND(#REF!,0)) -> #REF! | H71: =IF(#REF!="NA","",ROUND(#REF!,0)) -> #REF! | I71: =$O$11 -> 0.1 | J71: =$O$12 -> 0.05 | K71: =$O$13 -> 0 | L71: =$O$14 -> 0.05 | M71: =$O$15 -> 0.005 | N71: =IF(G71="","",G71*(1-$O$16)) -> #REF! | O71: =IF(H71="","",H71*(1-$O$16)) -> #REF! | Q71: =N71-#REF! -> #REF! | R71: =O71-#REF! -> #REF!
A72: Cat C (EMP) | B72: =IF(#REF!="","",#REF!) -> #REF! | C72: 19 | D72: 18 | E72: 12 | G72: =IF(#REF!="NA","",ROUND(#REF!,0)) -> #REF! | H72: =IF(#REF!="NA","",ROUND(#REF!,0)) -> #REF! | I72: =$O$11 -> 0.1 | J72: =$O$12 -> 0.05 | K72: =$O$13 -> 0 | L72: =$O$14 -> 0.05 | M72: =$O$15 -> 0.005 | N72: =IF(G72="","",G72*(1-$O$16)) -> #REF! | O72: =IF(H72="","",H72*(1-$O$16)) -> #REF! | Q72: =N72-#REF! -> #REF! | R72: =O72-#REF! -> #REF!
A73: Cat C (EMP) | B73: =IF(#REF!="","",#REF!) -> #REF! | C73: 19 | D73: 18 | E73: 12 | G73: =IF(#REF!="NA","",ROUND(#REF!,0)) -> #REF! | H73: =IF(#REF!="NA","",ROUND(#REF!,0)) -> #REF! | I73: =$O$11 -> 0.1 | J73: =$O$12 -> 0.05 | K73: =$O$13 -> 0 | L73: =$O$14 -> 0.05 | M73: =$O$15 -> 0.005 | N73: =IF(G73="","",G73*(1-$O$16)) -> #REF! | O73: =IF(H73="","",H73*(1-$O$16)) -> #REF! | Q73: =N73-#REF! -> #REF! | R73: =O73-#REF! -> #REF!
A74: Cat C (EMP) | B74: =IF(#REF!="","",#REF!) -> #REF! | C74: 19 | D74: 18 | E74: 12 | G74: =IF(#REF!="NA","",ROUND(#REF!,0)) -> #REF! | H74: =IF(#REF!="NA","",ROUND(#REF!,0)) -> #REF! | I74: =$O$11 -> 0.1 | J74: =$O$12 -> 0.05 | K74: =$O$13 -> 0 | L74: =$O$14 -> 0.05 | M74: =$O$15 -> 0.005 | N74: =IF(G74="","",G74*(1-$O$16)) -> #REF! | O74: =IF(H74="","",H74*(1-$O$16)) -> #REF! | Q74: =N74-#REF! -> #REF! | R74: =O74-#REF! -> #REF!
A75: Cat C (EMP) | B75: =IF(#REF!="","",#REF!) -> #REF! | C75: 19 | D75: 18 | E75: 12 | G75: =IF(#REF!="NA","",ROUND(#REF!,0)) -> #REF! | H75: =IF(#REF!="NA","",ROUND(#REF!,0)) -> #REF! | I75: =$O$11 -> 0.1 | J75: =$O$12 -> 0.05 | K75: =$O$13 -> 0 | L75: =$O$14 -> 0.05 | M75: =$O$15 -> 0.005 | N75: =IF(G75="","",G75*(1-$O$16)) -> #REF! | O75: =IF(H75="","",H75*(1-$O$16)) -> #REF! | Q75: =N75-#REF! -> #REF! | R75: =O75-#REF! -> #REF!
A76: Cat C (EMP) | B76: =IF(#REF!="","",#REF!) -> #REF! | C76: 19 | D76: 18 | E76: 12 | G76: =IF(#REF!="NA","",ROUND(#REF!,0)) -> #REF! | H76: =IF(#REF!="NA","",ROUND(#REF!,0)) -> #REF! | I76: =$O$11 -> 0.1 | J76: =$O$12 -> 0.05 | K76: =$O$13 -> 0 | L76: =$O$14 -> 0.05 | M76: =$O$15 -> 0.005 | N76: =IF(G76="","",G76*(1-$O$16)) -> #REF! | O76: =IF(H76="","",H76*(1-$O$16)) -> #REF! | Q76: =N76-#REF! -> #REF! | R76: =O76-#REF! -> #REF!
A77: Cat C (EMP) | B77: =IF(#REF!="","",#REF!) -> #REF! | C77: 19 | D77: 18 | E77: 12 | G77: =IF(#REF!="NA","",ROUND(#REF!,0)) -> #REF! | H77: =IF(#REF!="NA","",ROUND(#REF!,0)) -> #REF! | I77: =$O$11 -> 0.1 | J77: =$O$12 -> 0.05 | K77: =$O$13 -> 0 | L77: =$O$14 -> 0.05 | M77: =$O$15 -> 0.005 | N77: =IF(G77="","",G77*(1-$O$16)) -> #REF! | O77: =IF(H77="","",H77*(1-$O$16)) -> #REF! | Q77: =N77-#REF! -> #REF! | R77: =O77-#REF! -> #REF!
A78: Cat C (EMP) | B78: =IF(#REF!="","",#REF!) -> #REF! | C78: 19 | D78: 18 | E78: 12 | G78: =IF(#REF!="NA","",ROUND(#REF!,0)) -> #REF! | H78: =IF(#REF!="NA","",ROUND(#REF!,0)) -> #REF! | I78: =$O$11 -> 0.1 | J78: =$O$12 -> 0.05 | K78: =$O$13 -> 0 | L78: =$O$14 -> 0.05 | M78: =$O$15 -> 0.005 | N78: =IF(G78="","",G78*(1-$O$16)) -> #REF! | O78: =IF(H78="","",H78*(1-$O$16)) -> #REF! | Q78: =N78-#REF! -> #REF! | R78: =O78-#REF! -> #REF!
A79: Cat C (EMP) | B79: =IF(#REF!="","",#REF!) -> #REF! | C79: 19 | D79: 18 | E79: 12 | G79: =IF(#REF!="NA","",ROUND(#REF!,0)) -> #REF! | H79: =IF(#REF!="NA","",ROUND(#REF!,0)) -> #REF! | I79: =$O$11 -> 0.1 | J79: =$O$12 -> 0.05 | K79: =$O$13 -> 0 | L79: =$O$14 -> 0.05 | M79: =$O$15 -> 0.005 | N79: =IF(G79="","",G79*(1-$O$16)) -> #REF! | O79: =IF(H79="","",H79*(1-$O$16)) -> #REF! | Q79: =N79-#REF! -> #REF! | R79: =O79-#REF! -> #REF!
A80: Cat C (EMP) | B80: =IF(#REF!="","",#REF!) -> #REF! | C80: 19 | D80: 18 | E80: 12 | G80: =IF(#REF!="NA","",ROUND(#REF!,0)) -> #REF! | H80: =IF(#REF!="NA","",ROUND(#REF!,0)) -> #REF! | I80: =$O$11 -> 0.1 | J80: =$O$12 -> 0.05 | K80: =$O$13 -> 0 | L80: =$O$14 -> 0.05 | M80: =$O$15 -> 0.005 | N80: =IF(G80="","",G80*(1-$O$16)) -> #REF! | O80: =IF(H80="","",H80*(1-$O$16)) -> #REF! | Q80: =N80-#REF! -> #REF! | R80: =O80-#REF! -> #REF!
A81: Cat C (EMP) | B81: =IF(#REF!="","",#REF!) -> #REF! | G81: =IF(#REF!="NA","",ROUND(#REF!,0)) -> #REF! | H81: =IF(#REF!="NA","",ROUND(#REF!,0)) -> #REF! | I81: =$O$11 -> 0.1 | J81: =$O$12 -> 0.05 | K81: =$O$13 -> 0 | L81: =$O$14 -> 0.05 | M81: =$O$15 -> 0.005 | N81: =IF(G81="","",G81*(1-$O$16)) -> #REF! | O81: =IF(H81="","",H81*(1-$O$16)) -> #REF! | Q81: =N81-#REF! -> #REF! | R81: =O81-#REF! -> #REF!
A82: Cat C (DEP) | B82: =IF(#REF!="","",#REF!) -> #REF! | C82: 19 | D82: 18 | E82: 12 | G82: =IF(#REF!="NA","",ROUND(#REF!,0)) -> #REF! | H82: =IF(#REF!="NA","",ROUND(#REF!,0)) -> #REF! | I82: =$O$11 -> 0.1 | J82: =$O$12 -> 0.05 | K82: =$O$13 -> 0 | L82: =$O$14 -> 0.05 | M82: =$O$15 -> 0.005 | N82: =IF(G82="","",G82*(1-$O$16)) -> #REF! | O82: =IF(H82="","",H82*(1-$O$16)) -> #REF! | Q82: =N82-#REF! -> #REF! | R82: =O82-#REF! -> #REF!
A83: Cat C (DEP) | B83: =IF(#REF!="","",#REF!) -> #REF! | C83: 19 | D83: 18 | E83: 12 | G83: =IF(#REF!="NA","",ROUND(#REF!,0)) -> #REF! | H83: =IF(#REF!="NA","",ROUND(#REF!,0)) -> #REF! | I83: =$O$11 -> 0.1 | J83: =$O$12 -> 0.05 | K83: =$O$13 -> 0 | L83: =$O$14 -> 0.05 | M83: =$O$15 -> 0.005 | N83: =IF(G83="","",G83*(1-$O$16)) -> #REF! | O83: =IF(H83="","",H83*(1-$O$16)) -> #REF! | Q83: =N83-#REF! -> #REF! | R83: =O83-#REF! -> #REF!
A84: Cat C (DEP) | B84: =IF(#REF!="","",#REF!) -> #REF! | C84: 19 | D84: 18 | E84: 12 | G84: =IF(#REF!="NA","",ROUND(#REF!,0)) -> #REF! | H84: =IF(#REF!="NA","",ROUND(#REF!,0)) -> #REF! | I84: =$O$11 -> 0.1 | J84: =$O$12 -> 0.05 | K84: =$O$13 -> 0 | L84: =$O$14 -> 0.05 | M84: =$O$15 -> 0.005 | N84: =IF(G84="","",G84*(1-$O$16)) -> #REF! | O84: =IF(H84="","",H84*(1-$O$16)) -> #REF! | Q84: =N84-#REF! -> #REF! | R84: =O84-#REF! -> #REF!
A85: Cat C (DEP) | B85: =IF(#REF!="","",#REF!) -> #REF! | C85: 19 | D85: 18 | E85: 12 | G85: =IF(#REF!="NA","",ROUND(#REF!,0)) -> #REF! | H85: =IF(#REF!="NA","",ROUND(#REF!,0)) -> #REF! | I85: =$O$11 -> 0.1 | J85: =$O$12 -> 0.05 | K85: =$O$13 -> 0 | L85: =$O$14 -> 0.05 | M85: =$O$15 -> 0.005 | N85: =IF(G85="","",G85*(1-$O$16)) -> #REF! | O85: =IF(H85="","",H85*(1-$O$16)) -> #REF! | Q85: =N85-#REF! -> #REF! | R85: =O85-#REF! -> #REF!
A86: Cat C (DEP) | B86: =IF(#REF!="","",#REF!) -> #REF! | C86: 19 | D86: 18 | E86: 12 | G86: =IF(#REF!="NA","",ROUND(#REF!,0)) -> #REF! | H86: =IF(#REF!="NA","",ROUND(#REF!,0)) -> #REF! | I86: =$O$11 -> 0.1 | J86: =$O$12 -> 0.05 | K86: =$O$13 -> 0 | L86: =$O$14 -> 0.05 | M86: =$O$15 -> 0.005 | N86: =IF(G86="","",G86*(1-$O$16)) -> #REF! | O86: =IF(H86="","",H86*(1-$O$16)) -> #REF! | Q86: =N86-#REF! -> #REF! | R86: =O86-#REF! -> #REF!
A87: Cat C (DEP) | B87: =IF(#REF!="","",#REF!) -> #REF! | C87: 19 | D87: 18 | E87: 12 | G87: =IF(#REF!="NA","",ROUND(#REF!,0)) -> #REF! | H87: =IF(#REF!="NA","",ROUND(#REF!,0)) -> #REF! | I87: =$O$11 -> 0.1 | J87: =$O$12 -> 0.05 | K87: =$O$13 -> 0 | L87: =$O$14 -> 0.05 | M87: =$O$15 -> 0.005 | N87: =IF(G87="","",G87*(1-$O$16)) -> #REF! | O87: =IF(H87="","",H87*(1-$O$16)) -> #REF! | Q87: =N87-#REF! -> #REF! | R87: =O87-#REF! -> #REF!
A88: Cat C (DEP) | B88: =IF(#REF!="","",#REF!) -> #REF! | C88: 19 | D88: 18 | E88: 12 | G88: =IF(#REF!="NA","",ROUND(#REF!,0)) -> #REF! | H88: =IF(#REF!="NA","",ROUND(#REF!,0)) -> #REF! | I88: =$O$11 -> 0.1 | J88: =$O$12 -> 0.05 | K88: =$O$13 -> 0 | L88: =$O$14 -> 0.05 | M88: =$O$15 -> 0.005 | N88: =IF(G88="","",G88*(1-$O$16)) -> #REF! | O88: =IF(H88="","",H88*(1-$O$16)) -> #REF! | Q88: =N88-#REF! -> #REF! | R88: =O88-#REF! -> #REF!
A89: Cat C (DEP) | B89: =IF(#REF!="","",#REF!) -> #REF! | C89: 19 | D89: 18 | E89: 12 | G89: =IF(#REF!="NA","",ROUND(#REF!,0)) -> #REF! | H89: =IF(#REF!="NA","",ROUND(#REF!,0)) -> #REF! | I89: =$O$11 -> 0.1 | J89: =$O$12 -> 0.05 | K89: =$O$13 -> 0 | L89: =$O$14 -> 0.05 | M89: =$O$15 -> 0.005 | N89: =IF(G89="","",G89*(1-$O$16)) -> #REF! | O89: =IF(H89="","",H89*(1-$O$16)) -> #REF! | Q89: =N89-#REF! -> #REF! | R89: =O89-#REF! -> #REF!
A90: Cat C (DEP) | B90: =IF(#REF!="","",#REF!) -> #REF! | C90: 19 | D90: 18 | E90: 12 | G90: =IF(#REF!="NA","",ROUND(#REF!,0)) -> #REF! | H90: =IF(#REF!="NA","",ROUND(#REF!,0)) -> #REF! | I90: =$O$11 -> 0.1 | J90: =$O$12 -> 0.05 | K90: =$O$13 -> 0 | L90: =$O$14 -> 0.05 | M90: =$O$15 -> 0.005 | N90: =IF(G90="","",G90*(1-$O$16)) -> #REF! | O90: =IF(H90="","",H90*(1-$O$16)) -> #REF! | Q90: =N90-#REF! -> #REF! | R90: =O90-#REF! -> #REF!
A91: Cat C (DEP) | B91: =IF(#REF!="","",#REF!) -> #REF! | C91: 19 | D91: 18 | E91: 12 | G91: =IF(#REF!="NA","",ROUND(#REF!,0)) -> #REF! | H91: =IF(#REF!="NA","",ROUND(#REF!,0)) -> #REF! | I91: =$O$11 -> 0.1 | J91: =$O$12 -> 0.05 | K91: =$O$13 -> 0 | L91: =$O$14 -> 0.05 | M91: =$O$15 -> 0.005 | N91: =IF(G91="","",G91*(1-$O$16)) -> #REF! | O91: =IF(H91="","",H91*(1-$O$16)) -> #REF! | Q91: =N91-#REF! -> #REF! | R91: =O91-#REF! -> #REF!
A92: Cat C (DEP) | B92: =IF(#REF!="","",#REF!) -> #REF! | C92: 19 | D92: 18 | E92: 12 | G92: =IF(#REF!="NA","",ROUND(#REF!,0)) -> #REF! | H92: =IF(#REF!="NA","",ROUND(#REF!,0)) -> #REF! | I92: =$O$11 -> 0.1 | J92: =$O$12 -> 0.05 | K92: =$O$13 -> 0 | L92: =$O$14 -> 0.05 | M92: =$O$15 -> 0.005 | N92: =IF(G92="","",G92*(1-$O$16)) -> #REF! | O92: =IF(H92="","",H92*(1-$O$16)) -> #REF! | Q92: =N92-#REF! -> #REF! | R92: =O92-#REF! -> #REF!
A93: Cat C (DEP) | B93: =IF(#REF!="","",#REF!) -> #REF! | G93: =IF(#REF!="NA","",ROUND(#REF!,0)) -> #REF! | H93: =IF(#REF!="NA","",ROUND(#REF!,0)) -> #REF! | I93: =$O$11 -> 0.1 | J93: =$O$12 -> 0.05 | K93: =$O$13 -> 0 | L93: =$O$14 -> 0.05 | M93: =$O$15 -> 0.005 | N93: =IF(G93="","",G93*(1-$O$16)) -> #REF! | O93: =IF(H93="","",H93*(1-$O$16)) -> #REF! | Q93: =N93-#REF! -> #REF! | R93: =O93-#REF! -> #REF!
A94: Cat C (EMPMAT) | B94: =IF(#REF!="","",#REF!) -> #REF! | C94: 19 | D94: 18 | E94: 12 | H94: =ROUND(#REF!,0) -> #REF! | I94: =$O$11 -> 0.1 | J94: =$O$12 -> 0.05 | K94: =$O$13 -> 0 | L94: =$O$14 -> 0.05 | M94: =$O$15 -> 0.005 | N94: =IF(G94="","",G94*(1-$O$16)) | O94: =IF(H94="","",H94*(1-$O$16)) -> #REF! | P94: additional maternity premium | Q94: =N94-#REF! -> #VALUE! | R94: =O94-#REF! -> #REF!
A95: Category D
A96: Cat D (EMP) | B96: =IF(#REF!="","",#REF!) -> #REF! | C96: 19 | D96: 18 | E96: 12 | G96: =IF(#REF!="NA","",ROUND(#REF!,0)) -> #REF! | H96: =IF(#REF!="NA","",ROUND(#REF!,0)) -> #REF! | I96: =$O$11 -> 0.1 | J96: =$O$12 -> 0.05 | K96: =$O$13 -> 0 | L96: =$O$14 -> 0.05 | M96: =$O$15 -> 0.005 | N96: =IF(G96="","",G96*(1-$O$16)) -> #REF! | O96: =IF(H96="","",H96*(1-$O$16)) -> #REF! | Q96: =N96-#REF! -> #REF! | R96: =O96-#REF! -> #REF!
A97: Cat D (EMP) | B97: =IF(#REF!="","",#REF!) -> #REF! | C97: 19 | D97: 18 | E97: 12 | G97: =IF(#REF!="NA","",ROUND(#REF!,0)) -> #REF! | H97: =IF(#REF!="NA","",ROUND(#REF!,0)) -> #REF! | I97: =$O$11 -> 0.1 | J97: =$O$12 -> 0.05 | K97: =$O$13 -> 0 | L97: =$O$14 -> 0.05 | M97: =$O$15 -> 0.005 | N97: =IF(G97="","",G97*(1-$O$16)) -> #REF! | O97: =IF(H97="","",H97*(1-$O$16)) -> #REF! | Q97: =N97-#REF! -> #REF! | R97: =O97-#REF! -> #REF!
A98: Cat D (EMP) | B98: =IF(#REF!="","",#REF!) -> #REF! | C98: 19 | D98: 18 | E98: 12 | G98: =IF(#REF!="NA","",ROUND(#REF!,0)) -> #REF! | H98: =IF(#REF!="NA","",ROUND(#REF!,0)) -> #REF! | I98: =$O$11 -> 0.1 | J98: =$O$12 -> 0.05 | K98: =$O$13 -> 0 | L98: =$O$14 -> 0.05 | M98: =$O$15 -> 0.005 | N98: =IF(G98="","",G98*(1-$O$16)) -> #REF! | O98: =IF(H98="","",H98*(1-$O$16)) -> #REF! | Q98: =N98-#REF! -> #REF! | R98: =O98-#REF! -> #REF!
A99: Cat D (EMP) | B99: =IF(#REF!="","",#REF!) -> #REF! | C99: 19 | D99: 18 | E99: 12 | G99: =IF(#REF!="NA","",ROUND(#REF!,0)) -> #REF! | H99: =IF(#REF!="NA","",ROUND(#REF!,0)) -> #REF! | I99: =$O$11 -> 0.1 | J99: =$O$12 -> 0.05 | K99: =$O$13 -> 0 | L99: =$O$14 -> 0.05 | M99: =$O$15 -> 0.005 | N99: =IF(G99="","",G99*(1-$O$16)) -> #REF! | O99: =IF(H99="","",H99*(1-$O$16)) -> #REF! | Q99: =N99-#REF! -> #REF! | R99: =O99-#REF! -> #REF!
A100: Cat D (EMP) | B100: =IF(#REF!="","",#REF!) -> #REF! | C100: 19 | D100: 18 | E100: 12 | G100: =IF(#REF!="NA","",ROUND(#REF!,0)) -> #REF! | H100: =IF(#REF!="NA","",ROUND(#REF!,0)) -> #REF! | I100: =$O$11 -> 0.1 | J100: =$O$12 -> 0.05 | K100: =$O$13 -> 0 | L100: =$O$14 -> 0.05 | M100: =$O$15 -> 0.005 | N100: =IF(G100="","",G100*(1-$O$16)) -> #REF! | O100: =IF(H100="","",H100*(1-$O$16)) -> #REF! | Q100: =N100-#REF! -> #REF! | R100: =O100-#REF! -> #REF!
A101: Cat D (EMP) | B101: =IF(#REF!="","",#REF!) -> #REF! | C101: 19 | D101: 18 | E101: 12 | G101: =IF(#REF!="NA","",ROUND(#REF!,0)) -> #REF! | H101: =IF(#REF!="NA","",ROUND(#REF!,0)) -> #REF! | I101: =$O$11 -> 0.1 | J101: =$O$12 -> 0.05 | K101: =$O$13 -> 0 | L101: =$O$14 -> 0.05 | M101: =$O$15 -> 0.005 | N101: =IF(G101="","",G101*(1-$O$16)) -> #REF! | O101: =IF(H101="","",H101*(1-$O$16)) -> #REF! | Q101: =N101-#REF! -> #REF! | R101: =O101-#REF! -> #REF!
A102: Cat D (EMP) | B102: =IF(#REF!="","",#REF!) -> #REF! | C102: 19 | D102: 18 | E102: 12 | G102: =IF(#REF!="NA","",ROUND(#REF!,0)) -> #REF! | H102: =IF(#REF!="NA","",ROUND(#REF!,0)) -> #REF! | I102: =$O$11 -> 0.1 | J102: =$O$12 -> 0.05 | K102: =$O$13 -> 0 | L102: =$O$14 -> 0.05 | M102: =$O$15 -> 0.005 | N102: =IF(G102="","",G102*(1-$O$16)) -> #REF! | O102: =IF(H102="","",H102*(1-$O$16)) -> #REF! | Q102: =N102-#REF! -> #REF! | R102: =O102-#REF! -> #REF!
A103: Cat D (EMP) | B103: =IF(#REF!="","",#REF!) -> #REF! | C103: 19 | D103: 18 | E103: 12 | G103: =IF(#REF!="NA","",ROUND(#REF!,0)) -> #REF! | H103: =IF(#REF!="NA","",ROUND(#REF!,0)) -> #REF! | I103: =$O$11 -> 0.1 | J103: =$O$12 -> 0.05 | K103: =$O$13 -> 0 | L103: =$O$14 -> 0.05 | M103: =$O$15 -> 0.005 | N103: =IF(G103="","",G103*(1-$O$16)) -> #REF! | O103: =IF(H103="","",H103*(1-$O$16)) -> #REF! | Q103: =N103-#REF! -> #REF! | R103: =O103-#REF! -> #REF!
...

Sheet Final premium per member
O1: Premium | Q1: Maternity Premium | R1: Total Premium | V1: Additional Maternity Premium | W1: A | X1: B | Y1: C | Z1: D | AA1: E
O2: =SUBTOTAL(9,O6:O506) -> 144218 | Q2: =SUBTOTAL(9,Q6:Q506) -> 20976 | R2: =SUBTOTAL(9,R6:R506) -> 165194 | W2: ='Approved Quote'!C36 -> 5244 | X2: {='Approved Quote'!C60:D60} -> 0 | Y2: 0
Q3: Total Census | R3: =SUBTOTAL(3,C6:C506) -> 17
W4: Category A | AA4: Category B | AE4: Category C | AI4: Category D | AM4: Category E | AQ4: Category F | AU4: Category G | AY4: Category H
A5: No. | B5: Name | C5: Date of birth | D5: Gender | E5: Category | F5: Relationship | G5: Marital Status | H5: Plan | I5: Salary | J5: Column Code | K5: Column No. | L5: Age (ALB) | M5: Age Bracket | N5: Age Bracket Code | O5: Premium | P5: Maternity Age Limit | Q5: Maternity Premium | R5: Premium | T5: Dubai Age Bracket | U5: AUH Age Bracket | V5: Age Bracket | W5: M (Principal) | X5: F (Principal) | Y5: M (Dependent) | Z5: F (Dependent) | AA5: M (Principal) | AB5: F (Principal) | AC5: M (Dependent) | AD5: F (Dependent) | AE5: M (Principal) | AF5: F (Principal) | AG5: M (Dependent) | AH5: F (Dependent) | AI5: M (Principal) | AJ5: F (Principal) | AK5: M (Dependent) | AL5: F (Dependent) | AM5: M (Principal) | AN5: F (Principal) | AO5: M (Dependent) | AP5: F (Dependent) | AQ5: M (Principal) | AR5: F (Principal) | AS5: M (Dependent) | AT5: F (Dependent) | AU5: M (Principal) | AV5: F (Principal) | AW5: M (Dependent) | AX5: F (Dependent) | AY5: M (Principal) | AZ5: F (Principal) | BA5: M (Dependent) | BB5: F (Dependent)
A6: 1 | B6: Vitty Yohannan Thomas | C6: 30593 | D6: MALE | E6: A | F6: Employee | G6: Married | H6: DXB | J6: =IF(D6="","",E6&LEFT(D6)&IF(F6="Employee","E","D")) -> AME | K6: =IF(J6="","",VLOOKUP(J6,$Y$19:$Z$50,2,FALSE)) -> 2 | L6: =IF(C6="","",DATEDIF(C6,'Premium Table'!$B$6,"Y")) -> 42 | M6: =IF(L6="","",IF(H6="","Choose Plan (DXB/AUH)",IF(H6="DXB",VLOOKUP(L6,$V$55:$W$154,2,FALSE),IF(H6="AUH",VLOOKUP(L6,$V$55:$X$154,3,FALSE),"Choose Plan (DXB/AUH)")))) -> 41 - 45 | N6: =IF(L6="","",IF(M6="","",IF(H6="DXB",VLOOKUP(M6,DXBAgeBr,3,FALSE),IF(H6="AUH",VLOOKUP(M6,AUHAgeBr,2,FALSE),"")))) -> 7 | O6: =IF(M6="","",VLOOKUP(N6,$V$5:$BB$17,K6,FALSE)) -> 8785 | P6: =IF(L6="","",IF(H6="DXB",46,IF(H6="AUH",51,""))) -> 46 | Q6: =IF(AND(LEFT(D6,1)="F",G6="Married",L6>17,L6<P6),HLOOKUP(E6,$W$1:$AA$2,2,FALSE),0) -> 0 | R6: =IF(M6="","",O6+Q6) -> 8785 | T6: 0 - 10 | U6: 0 - 17 | V6: 1 | W6: NA | X6: NA | Y6: ='Approved Quote'!G20 -> 6499 | Z6: ='Approved Quote'!I20 -> 5234 | AA6: NA | AB6: NA | AC6: ='Approved Quote'!G44 -> 0 | AD6: ='Approved Quote'!I44 -> 0 | AE6: NA | AF6: NA | AG6: ='Approved Quote'!G68 -> 0 | AH6: ='Approved Quote'!I68 -> 0 | AI6: NA | AJ6: NA | AK6: ='Approved Quote'!G92 -> 0 | AL6: ='Approved Quote'!I92 -> 0 | AM6: NA | AN6: NA | AQ6: NA | AR6: NA | AU6: NA | AV6: NA | AY6: NA | AZ6: NA
A7: =IF(C7="","",A6+1) -> 2 | B7: Alice Raju | C7: 30768 | D7: FEMALE | E7: A | F7: Spouse | G7: Married | H7: DXB | J7: =IF(D7="","",E7&LEFT(D7)&IF(F7="Employee","E","D")) -> AFD | K7: =IF(J7="","",VLOOKUP(J7,$Y$19:$Z$50,2,FALSE)) -> 5 | L7: =IF(C7="","",DATEDIF(C7,'Premium Table'!$B$6,"Y")) -> 41 | M7: =IF(L7="","",IF(H7="","Choose Plan (DXB/AUH)",IF(H7="DXB",VLOOKUP(L7,$V$55:$W$154,2,FALSE),IF(H7="AUH",VLOOKUP(L7,$V$55:$X$154,3,FALSE),"Choose Plan (DXB/AUH)")))) -> 41 - 45 | N7: =IF(L7="","",IF(M7="","",IF(H7="DXB",VLOOKUP(M7,DXBAgeBr,3,FALSE),IF(H7="AUH",VLOOKUP(M7,AUHAgeBr,2,FALSE),"")))) -> 7 | O7: =IF(M7="","",VLOOKUP(N7,$V$5:$BB$17,K7,FALSE)) -> 12068 | P7: =IF(L7="","",IF(H7="DXB",46,IF(H7="AUH",51,""))) -> 46 | Q7: =IF(AND(LEFT(D7,1)="F",G7="Married",L7>17,L7<P7),HLOOKUP(E7,$W$1:$AA$2,2,FALSE),0) -> 5244 | R7: =IF(M7="","",O7+Q7) -> 17312 | T7: 11 - 17 | U7: 18 - 40 | V7: 2 | W7: ='Approved Quote'!B21 -> 3157 | X7: ='Approved Quote'!D21 -> 3217 | Y7: ='Approved Quote'!G21 -> 4674 | Z7: ='Approved Quote'!I21 -> 4750 | AA7: ='Approved Quote'!B45 -> 0 | AB7: ='Approved Quote'!D45 -> 0 | AC7: ='Approved Quote'!G45 -> 0 | AD7: ='Approved Quote'!I45 -> 0 | AE7: ='Approved Quote'!B69 -> 0 | AF7: ='Approved Quote'!D69 -> 0 | AG7: ='Approved Quote'!G69 -> 0 | AH7: ='Approved Quote'!I69 -> 0 | AI7: ='Approved Quote'!B93 -> 0 | AJ7: ='Approved Quote'!D93 -> 0 | AK7: ='Approved Quote'!G93 -> 0 | AL7: ='Approved Quote'!I93 -> 0 | AQ7: NA | AR7: NA | AU7: NA | AV7: NA | AY7: NA | AZ7: NA
A8: =IF(C8="","",A7+1) -> 3 | B8: Beulah Vitty Thomas | C8: 41596 | D8: FEMALE | E8: A | F8: Child | G8: Single | H8: DXB | J8: =IF(D8="","",E8&LEFT(D8)&IF(F8="Employee","E","D")) -> AFD | K8: =IF(J8="","",VLOOKUP(J8,$Y$19:$Z$50,2,FALSE)) -> 5 | L8: =IF(C8="","",DATEDIF(C8,'Premium Table'!$B$6,"Y")) -> 12 | M8: =IF(L8="","",IF(H8="","Choose Plan (DXB/AUH)",IF(H8="DXB",VLOOKUP(L8,$V$55:$W$154,2,FALSE),IF(H8="AUH",VLOOKUP(L8,$V$55:$X$154,3,FALSE),"Choose Plan (DXB/AUH)")))) -> 11 - 17 | N8: =IF(L8="","",IF(M8="","",IF(H8="DXB",VLOOKUP(M8,DXBAgeBr,3,FALSE),IF(H8="AUH",VLOOKUP(M8,AUHAgeBr,2,FALSE),"")))) -> 2 | O8: =IF(M8="","",VLOOKUP(N8,$V$5:$BB$17,K8,FALSE)) -> 4750 | P8: =IF(L8="","",IF(H8="DXB",46,IF(H8="AUH",51,""))) -> 46 | Q8: =IF(AND(LEFT(D8,1)="F",G8="Married",L8>17,L8<P8),HLOOKUP(E8,$W$1:$AA$2,2,FALSE),0) -> 0 | R8: =IF(M8="","",O8+Q8) -> 4750 | T8: 18 - 25 | U8: 41 -59 | V8: 3 | W8: ='Approved Quote'!B22 -> 5253 | X8: ='Approved Quote'!D22 -> 5997 | Y8: ='Approved Quote'!G22 -> 5253 | Z8: ='Approved Quote'!I22 -> 5997 | AA8: ='Approved Quote'!B46 -> 0 | AB8: ='Approved Quote'!D46 -> 0 | AC8: ='Approved Quote'!G46 -> 0 | AD8: ='Approved Quote'!I46 -> 0 | AE8: ='Approved Quote'!B70 -> 0 | AF8: ='Approved Quote'!D70 -> 0 | AG8: ='Approved Quote'!G70 -> 0 | AH8: ='Approved Quote'!I70 -> 0 | AI8: ='Approved Quote'!B94 -> 0 | AJ8: ='Approved Quote'!D94 -> 0 | AK8: ='Approved Quote'!G94 -> 0 | AL8: ='Approved Quote'!I94 -> 0
A9: =IF(C9="","",A8+1) -> 4 | B9: Charlotte Vitty Thomas | C9: 43316 | D9: FEMALE | E9: A | F9: Child | G9: Single | H9: DXB | J9: =IF(D9="","",E9&LEFT(D9)&IF(F9="Employee","E","D")) -> AFD | K9: =IF(J9="","",VLOOKUP(J9,$Y$19:$Z$50,2,FALSE)) -> 5 | L9: =IF(C9="","",DATEDIF(C9,'Premium Table'!$B$6,"Y")) -> 7 | M9: =IF(L9="","",IF(H9="","Choose Plan (DXB/AUH)",IF(H9="DXB",VLOOKUP(L9,$V$55:$W$154,2,FALSE),IF(H9="AUH",VLOOKUP(L9,$V$55:$X$154,3,FALSE),"Choose Plan (DXB/AUH)")))) -> 0 - 10 | N9: =IF(L9="","",IF(M9="","",IF(H9="DXB",VLOOKUP(M9,DXBAgeBr,3,FALSE),IF(H9="AUH",VLOOKUP(M9,AUHAgeBr,2,FALSE),"")))) -> 1 | O9: =IF(M9="","",VLOOKUP(N9,$V$5:$BB$17,K9,FALSE)) -> 5234 | P9: =IF(L9="","",IF(H9="DXB",46,IF(H9="AUH",51,""))) -> 46 | Q9: =IF(AND(LEFT(D9,1)="F",G9="Married",L9>17,L9<P9),HLOOKUP(E9,$W$1:$AA$2,2,FALSE),0) -> 0 | R9: =IF(M9="","",O9+Q9) -> 5234 | T9: 26 - 30 | U9: 60 - 64 | V9: 4 | W9: ='Approved Quote'!B23 -> 5833 | X9: ='Approved Quote'!D23 -> 7304 | Y9: ='Approved Quote'!G23 -> 5833 | Z9: ='Approved Quote'!I23 -> 7304 | AA9: ='Approved Quote'!B47 -> 0 | AB9: ='Approved Quote'!D47 -> 0 | AC9: ='Approved Quote'!G47 -> 0 | AD9: ='Approved Quote'!I47 -> 0 | AE9: ='Approved Quote'!B71 -> 0 | AF9: ='Approved Quote'!D71 -> 0 | AG9: ='Approved Quote'!G71 -> 0 | AH9: ='Approved Quote'!I71 -> 0 | AI9: ='Approved Quote'!B95 -> 0 | AJ9: ='Approved Quote'!D95 -> 0 | AK9: ='Approved Quote'!G95 -> 0 | AL9: ='Approved Quote'!I95 -> 0
A10: =IF(C10="","",A9+1) -> 5 | B10: Evelyn Vitty Thomas | C10: 43958 | D10: FEMALE | E10: A | F10: Child | G10: Single | H10: DXB | J10: =IF(D10="","",E10&LEFT(D10)&IF(F10="Employee","E","D")) -> AFD | K10: =IF(J10="","",VLOOKUP(J10,$Y$19:$Z$50,2,FALSE)) -> 5 | L10: =IF(C10="","",DATEDIF(C10,'Premium Table'!$B$6,"Y")) -> 5 | M10: =IF(L10="","",IF(H10="","Choose Plan (DXB/AUH)",IF(H10="DXB",VLOOKUP(L10,$V$55:$W$154,2,FALSE),IF(H10="AUH",VLOOKUP(L10,$V$55:$X$154,3,FALSE),"Choose Plan (DXB/AUH)")))) -> 0 - 10 | N10: =IF(L10="","",IF(M10="","",IF(H10="DXB",VLOOKUP(M10,DXBAgeBr,3,FALSE),IF(H10="AUH",VLOOKUP(M10,AUHAgeBr,2,FALSE),"")))) -> 1 | O10: =IF(M10="","",VLOOKUP(N10,$V$5:$BB$17,K10,FALSE)) -> 5234 | P10: =IF(L10="","",IF(H10="DXB",46,IF(H10="AUH",51,""))) -> 46 | Q10: =IF(AND(LEFT(D10,1)="F",G10="Married",L10>17,L10<P10),HLOOKUP(E10,$W$1:$AA$2,2,FALSE),0) -> 0 | R10: =IF(M10="","",O10+Q10) -> 5234 | T10: 31 - 35 | U10: 65 - 99 | V10: 5 | W10: ='Approved Quote'!B24 -> 6915 | X10: ='Approved Quote'!D24 -> 8606 | Y10: ='Approved Quote'!G24 -> 6915 | Z10: ='Approved Quote'!I24 -> 8606 | AA10: ='Approved Quote'!B48 -> 0 | AB10: ='Approved Quote'!D48 -> 0 | AC10: ='Approved Quote'!G48 -> 0 | AD10: ='Approved Quote'!I48 -> 0 | AE10: ='Approved Quote'!B72 -> 0 | AF10: ='Approved Quote'!D72 -> 0 | AG10: ='Approved Quote'!G72 -> 0 | AH10: ='Approved Quote'!I72 -> 0 | AI10: ='Approved Quote'!B96 -> 0 | AJ10: ='Approved Quote'!D96 -> 0 | AK10: ='Approved Quote'!G96 -> 0 | AL10: ='Approved Quote'!I96 -> 0
A11: =IF(C11="","",A10+1) -> 6 | B11: Saniya Suri | C11: 35126 | D11: FEMALE | E11: A | F11: Employee | G11: Married | H11: DXB | J11: =IF(D11="","",E11&LEFT(D11)&IF(F11="Employee","E","D")) -> AFE | K11: =IF(J11="","",VLOOKUP(J11,$Y$19:$Z$50,2,FALSE)) -> 3 | L11: =IF(C11="","",DATEDIF(C11,'Premium Table'!$B$6,"Y")) -> 30 | M11: =IF(L11="","",IF(H11="","Choose Plan (DXB/AUH)",IF(H11="DXB",VLOOKUP(L11,$V$55:$W$154,2,FALSE),IF(H11="AUH",VLOOKUP(L11,$V$55:$X$154,3,FALSE),"Choose Plan (DXB/AUH)")))) -> 26 - 30 | N11: =IF(L11="","",IF(M11="","",IF(H11="DXB",VLOOKUP(M11,DXBAgeBr,3,FALSE),IF(H11="AUH",VLOOKUP(M11,AUHAgeBr,2,FALSE),"")))) -> 4 | O11: =IF(M11="","",VLOOKUP(N11,$V$5:$BB$17,K11,FALSE)) -> 7304 | P11: =IF(L11="","",IF(H11="DXB",46,IF(H11="AUH",51,""))) -> 46 | Q11: =IF(AND(LEFT(D11,1)="F",G11="Married",L11>17,L11<P11),HLOOKUP(E11,$W$1:$AA$2,2,FALSE),0) -> 5244 | R11: =IF(M11="","",O11+Q11) -> 12548 | T11: 36 - 40 | V11: 6 | W11: ='Approved Quote'!B25 -> 8397 | X11: ='Approved Quote'!D25 -> 10589 | Y11: ='Approved Quote'!G25 -> 8397 | Z11: ='Approved Quote'!I25 -> 10589 | AA11: ='Approved Quote'!B49 -> 0 | AB11: ='Approved Quote'!D49 -> 0 | AC11: ='Approved Quote'!G49 -> 0 | AD11: ='Approved Quote'!I49 -> 0 | AE11: ='Approved Quote'!B73 -> 0 | AF11: ='Approved Quote'!D73 -> 0 | AG11: ='Approved Quote'!G73 -> 0 | AH11: ='Approved Quote'!I73 -> 0 | AI11: ='Approved Quote'!B97 -> 0 | AJ11: ='Approved Quote'!D97 -> 0 | AK11: ='Approved Quote'!G97 -> 0 | AL11: ='Approved Quote'!I97 -> 0
A12: =IF(C12="","",A11+1) -> 7 | B12: Miraya Suri Hotwani | C12: 45839 | D12: FEMALE | E12: A | F12: Child | G12: Single | H12: DXB | J12: =IF(D12="","",E12&LEFT(D12)&IF(F12="Employee","E","D")) -> AFD | K12: =IF(J12="","",VLOOKUP(J12,$Y$19:$Z$50,2,FALSE)) -> 5 | L12: =IF(C12="","",DATEDIF(C12,'Premium Table'!$B$6,"Y")) -> 0 | M12: =IF(L12="","",IF(H12="","Choose Plan (DXB/AUH)",IF(H12="DXB",VLOOKUP(L12,$V$55:$W$154,2,FALSE),IF(H12="AUH",VLOOKUP(L12,$V$55:$X$154,3,FALSE),"Choose Plan (DXB/AUH)")))) -> 0 - 10 | N12: =IF(L12="","",IF(M12="","",IF(H12="DXB",VLOOKUP(M12,DXBAgeBr,3,FALSE),IF(H12="AUH",VLOOKUP(M12,AUHAgeBr,2,FALSE),"")))) -> 1 | O12: =IF(M12="","",VLOOKUP(N12,$V$5:$BB$17,K12,FALSE)) -> 5234 | P12: =IF(L12="","",IF(H12="DXB",46,IF(H12="AUH",51,""))) -> 46 | Q12: =IF(AND(LEFT(D12,1)="F",G12="Married",L12>17,L12<P12),HLOOKUP(E12,$W$1:$AA$2,2,FALSE),0) -> 0 | R12: =IF(M12="","",O12+Q12) -> 5234 | T12: 41 - 45 | V12: 7 | W12: ='Approved Quote'!B26 -> 8785 | X12: ='Approved Quote'!D26 -> 12068 | Y12: ='Approved Quote'!G26 -> 8795 | Z12: ='Approved Quote'!I26 -> 12068 | AA12: ='Approved Quote'!B50 -> 0 | AB12: ='Approved Quote'!D50 -> 0 | AC12: ='Approved Quote'!G50 -> 0 | AD12: ='Approved Quote'!I50 -> 0 | AE12: ='Approved Quote'!B74 -> 0 | AF12: ='Approved Quote'!D74 -> 0 | AG12: ='Approved Quote'!G74 -> 0 | AH12: ='Approved Quote'!I74 -> 0 | AI12: ='Approved Quote'!B98 -> 0 | AJ12: ='Approved Quote'!D98 -> 0 | AK12: ='Approved Quote'!G98 -> 0 | AL12: ='Approved Quote'!I98 -> 0
A13: =IF(C13="","",A12+1) -> 8 | B13: Shanaf Maliyakkal | C13: 32415 | D13: MALE | E13: A | F13: Employee | G13: Married | H13: DXB | J13: =IF(D13="","",E13&LEFT(D13)&IF(F13="Employee","E","D")) -> AME | K13: =IF(J13="","",VLOOKUP(J13,$Y$19:$Z$50,2,FALSE)) -> 2 | L13: =IF(C13="","",DATEDIF(C13,'Premium Table'!$B$6,"Y")) -> 37 | M13: =IF(L13="","",IF(H13="","Choose Plan (DXB/AUH)",IF(H13="DXB",VLOOKUP(L13,$V$55:$W$154,2,FALSE),IF(H13="AUH",VLOOKUP(L13,$V$55:$X$154,3,FALSE),"Choose Plan (DXB/AUH)")))) -> 36 - 40 | N13: =IF(L13="","",IF(M13="","",IF(H13="DXB",VLOOKUP(M13,DXBAgeBr,3,FALSE),IF(H13="AUH",VLOOKUP(M13,AUHAgeBr,2,FALSE),"")))) -> 6 | O13: =IF(M13="","",VLOOKUP(N13,$V$5:$BB$17,K13,FALSE)) -> 8397 | P13: =IF(L13="","",IF(H13="DXB",46,IF(H13="AUH",51,""))) -> 46 | Q13: =IF(AND(LEFT(D13,1)="F",G13="Married",L13>17,L13<P13),HLOOKUP(E13,$W$1:$AA$2,2,FALSE),0) -> 0 | R13: =IF(M13="","",O13+Q13) -> 8397 | T13: 46 - 50 | V13: 8 | W13: ='Approved Quote'!B27 -> 11304 | X13: ='Approved Quote'!D27 -> 14951 | Y13: ='Approved Quote'!G27 -> 11304 | Z13: ='Approved Quote'!I27 -> 14951 | AA13: ='Approved Quote'!B51 -> 0 | AB13: ='Approved Quote'!D51 -> 0 | AC13: ='Approved Quote'!G51 -> 0 | AD13: ='Approved Quote'!I51 -> 0 | AE13: ='Approved Quote'!B75 -> 0 | AF13: ='Approved Quote'!D75 -> 0 | AG13: ='Approved Quote'!G75 -> 0 | AH13: ='Approved Quote'!I75 -> 0 | AI13: ='Approved Quote'!B99 -> 0 | AJ13: ='Approved Quote'!D99 -> 0 | AK13: ='Approved Quote'!G99 -> 0 | AL13: ='Approved Quote'!I99 -> 0
A14: =IF(C14="","",A13+1) -> 9 | B14: Shafna Ponnachethiyil | C14: 35014 | D14: FEMALE | E14: A | F14: Spouse | G14: Married | H14: DXB | J14: =IF(D14="","",E14&LEFT(D14)&IF(F14="Employee","E","D")) -> AFD | K14: =IF(J14="","",VLOOKUP(J14,$Y$19:$Z$50,2,FALSE)) -> 5 | L14: =IF(C14="","",DATEDIF(C14,'Premium Table'!$B$6,"Y")) -> 30 | M14: =IF(L14="","",IF(H14="","Choose Plan (DXB/AUH)",IF(H14="DXB",VLOOKUP(L14,$V$55:$W$154,2,FALSE),IF(H14="AUH",VLOOKUP(L14,$V$55:$X$154,3,FALSE),"Choose Plan (DXB/AUH)")))) -> 26 - 30 | N14: =IF(L14="","",IF(M14="","",IF(H14="DXB",VLOOKUP(M14,DXBAgeBr,3,FALSE),IF(H14="AUH",VLOOKUP(M14,AUHAgeBr,2,FALSE),"")))) -> 4 | O14: =IF(M14="","",VLOOKUP(N14,$V$5:$BB$17,K14,FALSE)) -> 7304 | P14: =IF(L14="","",IF(H14="DXB",46,IF(H14="AUH",51,""))) -> 46 | Q14: =IF(AND(LEFT(D14,1)="F",G14="Married",L14>17,L14<P14),HLOOKUP(E14,$W$1:$AA$2,2,FALSE),0) -> 5244 | R14: =IF(M14="","",O14+Q14) -> 12548 | T14: 51 - 55 | V14: 9 | W14: ='Approved Quote'!B28 -> 14946 | X14: ='Approved Quote'!D28 -> 19507 | Y14: ='Approved Quote'!G28 -> 14946 | Z14: ='Approved Quote'!I28 -> 19507 | AA14: ='Approved Quote'!B52 -> 0 | AB14: ='Approved Quote'!D52 -> 0 | AC14: ='Approved Quote'!G52 -> 0 | AD14: ='Approved Quote'!I52 -> 0 | AE14: ='Approved Quote'!B76 -> 0 | AF14: ='Approved Quote'!D76 -> 0 | AG14: ='Approved Quote'!G76 -> 0 | AH14: ='Approved Quote'!I76 -> 0 | AI14: ='Approved Quote'!B100 -> 0 | AJ14: ='Approved Quote'!D100 -> 0 | AK14: ='Approved Quote'!G100 -> 0 | AL14: ='Approved Quote'!I100 -> 0
A15: =IF(C15="","",A14+1) -> 10 | B15: Haala Sehrish Maliyakkal | C15: 43617 | D15: FEMALE | E15: A | F15: Child | G15: Single | H15: DXB | J15: =IF(D15="","",E15&LEFT(D15)&IF(F15="Employee","E","D")) -> AFD | K15: =IF(J15="","",VLOOKUP(J15,$Y$19:$Z$50,2,FALSE)) -> 5 | L15: =IF(C15="","",DATEDIF(C15,'Premium Table'!$B$6,"Y")) -> 6 | M15: =IF(L15="","",IF(H15="","Choose Plan (DXB/AUH)",IF(H15="DXB",VLOOKUP(L15,$V$55:$W$154,2,FALSE),IF(H15="AUH",VLOOKUP(L15,$V$55:$X$154,3,FALSE),"Choose Plan (DXB/AUH)")))) -> 0 - 10 | N15: =IF(L15="","",IF(M15="","",IF(H15="DXB",VLOOKUP(M15,DXBAgeBr,3,FALSE),IF(H15="AUH",VLOOKUP(M15,AUHAgeBr,2,FALSE),"")))) -> 1 | O15: =IF(M15="","",VLOOKUP(N15,$V$5:$BB$17,K15,FALSE)) -> 5234 | P15: =IF(L15="","",IF(H15="DXB",46,IF(H15="AUH",51,""))) -> 46 | Q15: =IF(AND(LEFT(D15,1)="F",G15="Married",L15>17,L15<P15),HLOOKUP(E15,$W$1:$AA$2,2,FALSE),0) -> 0 | R15: =IF(M15="","",O15+Q15) -> 5234 | T15: 56 - 59 | V15: 10 | W15: ='Approved Quote'!B29 -> 20128 | X15: ='Approved Quote'!D29 -> 23729 | Y15: ='Approved Quote'!G29 -> 20128 | Z15: ='Approved Quote'!I29 -> 23729 | AA15: ='Approved Quote'!B53 -> 0 | AB15: ='Approved Quote'!D53 -> 0 | AC15: ='Approved Quote'!G53 -> 0 | AD15: ='Approved Quote'!I53 -> 0 | AE15: ='Approved Quote'!B77 -> 0 | AF15: ='Approved Quote'!D77 -> 0 | AG15: ='Approved Quote'!G77 -> 0 | AH15: ='Approved Quote'!I77 -> 0 | AI15: ='Approved Quote'!B101 -> 0 | AJ15: ='Approved Quote'!D101 -> 0 | AK15: ='Approved Quote'!G101 -> 0 | AL15: ='Approved Quote'!I101 -> 0
A16: =IF(C16="","",A15+1) -> 11 | B16: Zuhal Fatin Maliyakkal | C16: 45668 | D16: FEMALE | E16: A | F16: Child | G16: Single | H16: DXB | J16: =IF(D16="","",E16&LEFT(D16)&IF(F16="Employee","E","D")) -> AFD | K16: =IF(J16="","",VLOOKUP(J16,$Y$19:$Z$50,2,FALSE)) -> 5 | L16: =IF(C16="","",DATEDIF(C16,'Premium Table'!$B$6,"Y")) -> 1 | M16: =IF(L16="","",IF(H16="","Choose Plan (DXB/AUH)",IF(H16="DXB",VLOOKUP(L16,$V$55:$W$154,2,FALSE),IF(H16="AUH",VLOOKUP(L16,$V$55:$X$154,3,FALSE),"Choose Plan (DXB/AUH)")))) -> 0 - 10 | N16: =IF(L16="","",IF(M16="","",IF(H16="DXB",VLOOKUP(M16,DXBAgeBr,3,FALSE),IF(H16="AUH",VLOOKUP(M16,AUHAgeBr,2,FALSE),"")))) -> 1 | O16: =IF(M16="","",VLOOKUP(N16,$V$5:$BB$17,K16,FALSE)) -> 5234 | P16: =IF(L16="","",IF(H16="DXB",46,IF(H16="AUH",51,""))) -> 46 | Q16: =IF(AND(LEFT(D16,1)="F",G16="Married",L16>17,L16<P16),HLOOKUP(E16,$W$1:$AA$2,2,FALSE),0) -> 0 | R16: =IF(M16="","",O16+Q16) -> 5234 | T16: 60 - 64 | V16: 11 | W16: ='Approved Quote'!B30 -> 24628 | X16: ='Approved Quote'!D30 -> 28071 | Y16: ='Approved Quote'!G30 -> 24628 | Z16: ='Approved Quote'!I30 -> 28071 | AA16: ='Approved Quote'!B54 -> 0 | AB16: ='Approved Quote'!D54 -> 0 | AC16: ='Approved Quote'!G54 -> 0 | AD16: ='Approved Quote'!I54 -> 0 | AE16: ='Approved Quote'!B78 -> 0 | AF16: ='Approved Quote'!D78 -> 0 | AG16: ='Approved Quote'!G78 -> 0 | AH16: ='Approved Quote'!I78 -> 0 | AI16: ='Approved Quote'!B102 -> 0 | AJ16: ='Approved Quote'!D102 -> 0 | AK16: ='Approved Quote'!G102 -> 0 | AL16: ='Approved Quote'!I102 -> 0
A17: =IF(C17="","",A16+1) -> 12 | B17: Anshuman Patnaik | C17: 36726 | D17: MALE | E17: A | F17: Employee | G17: Single | H17: DXB | J17: =IF(D17="","",E17&LEFT(D17)&IF(F17="Employee","E","D")) -> AME | K17: =IF(J17="","",VLOOKUP(J17,$Y$19:$Z$50,2,FALSE)) -> 2 | L17: =IF(C17="","",DATEDIF(C17,'Premium Table'!$B$6,"Y")) -> 25 | M17: =IF(L17="","",IF(H17="","Choose Plan (DXB/AUH)",IF(H17="DXB",VLOOKUP(L17,$V$55:$W$154,2,FALSE),IF(H17="AUH",VLOOKUP(L17,$V$55:$X$154,3,FALSE),"Choose Plan (DXB/AUH)")))) -> 18 - 25 | N17: =IF(L17="","",IF(M17="","",IF(H17="DXB",VLOOKUP(M17,DXBAgeBr,3,FALSE),IF(H17="AUH",VLOOKUP(M17,AUHAgeBr,2,FALSE),"")))) -> 3 | O17: =IF(M17="","",VLOOKUP(N17,$V$5:$BB$17,K17,FALSE)) -> 5253 | P17: =IF(L17="","",IF(H17="DXB",46,IF(H17="AUH",51,""))) -> 46 | Q17: =IF(AND(LEFT(D17,1)="F",G17="Married",L17>17,L17<P17),HLOOKUP(E17,$W$1:$AA$2,2,FALSE),0) -> 0 | R17: =IF(M17="","",O17+Q17) -> 5253 | T17: 65 - 99 | V17: 12 | W17: ='Approved Quote'!B31 -> 43786 | X17: ='Approved Quote'!D31 -> 49985 | Y17: ='Approved Quote'!G31 -> 43786 | Z17: ='Approved Quote'!I31 -> 49985 | AA17: ='Approved Quote'!B55 -> 0 | AB17: ='Approved Quote'!D55 -> 0 | AC17: ='Approved Quote'!G55 -> 0 | AD17: ='Approved Quote'!I55 -> 0 | AE17: ='Approved Quote'!B79 -> 0 | AF17: ='Approved Quote'!D79 -> 0 | AG17: ='Approved Quote'!G79 -> 0 | AH17: ='Approved Quote'!I79 -> 0 | AI17: ='Approved Quote'!B103 -> 0 | AJ17: ='Approved Quote'!D103 -> 0 | AK17: ='Approved Quote'!G103 -> 0 | AL17: ='Approved Quote'!I103 -> 0
A18: =IF(C18="","",A17+1) -> 13 | B18: Anis Ahmed | C18: 24165 | D18: MALE | E18: A | F18: Employee | G18: Married | H18: DXB | J18: =IF(D18="","",E18&LEFT(D18)&IF(F18="Employee","E","D")) -> AME | K18: =IF(J18="","",VLOOKUP(J18,$Y$19:$Z$50,2,FALSE)) -> 2 | L18: =IF(C18="","",DATEDIF(C18,'Premium Table'!$B$6,"Y")) -> 60 | M18: =IF(L18="","",IF(H18="","Choose Plan (DXB/AUH)",IF(H18="DXB",VLOOKUP(L18,$V$55:$W$154,2,FALSE),IF(H18="AUH",VLOOKUP(L18,$V$55:$X$154,3,FALSE),"Choose Plan (DXB/AUH)")))) -> 60 - 64 | N18: =IF(L18="","",IF(M18="","",IF(H18="DXB",VLOOKUP(M18,DXBAgeBr,3,FALSE),IF(H18="AUH",VLOOKUP(M18,AUHAgeBr,2,FALSE),"")))) -> 11 | O18: =IF(M18="","",VLOOKUP(N18,$V$5:$BB$17,K18,FALSE)) -> 24628 | P18: =IF(L18="","",IF(H18="DXB",46,IF(H18="AUH",51,""))) -> 46 | Q18: =IF(AND(LEFT(D18,1)="F",G18="Married",L18>17,L18<P18),HLOOKUP(E18,$W$1:$AA$2,2,FALSE),0) -> 0 | R18: =IF(M18="","",O18+Q18) -> 24628
A19: =IF(C19="","",A18+1) -> 14 | B19: Suhana Lutfa Ahmed | C19: 26031 | D19: FEMALE | E19: A | F19: Spouse | G19: Married | H19: DXB | J19: =IF(D19="","",E19&LEFT(D19)&IF(F19="Employee","E","D")) -> AFD | K19: =IF(J19="","",VLOOKUP(J19,$Y$19:$Z$50,2,FALSE)) -> 5 | L19: =IF(C19="","",DATEDIF(C19,'Premium Table'!$B$6,"Y")) -> 54 | M19: =IF(L19="","",IF(H19="","Choose Plan (DXB/AUH)",IF(H19="DXB",VLOOKUP(L19,$V$55:$W$154,2,FALSE),IF(H19="AUH",VLOOKUP(L19,$V$55:$X$154,3,FALSE),"Choose Plan (DXB/AUH)")))) -> 51 - 55 | N19: =IF(L19="","",IF(M19="","",IF(H19="DXB",VLOOKUP(M19,DXBAgeBr,3,FALSE),IF(H19="AUH",VLOOKUP(M19,AUHAgeBr,2,FALSE),"")))) -> 9 | O19: =IF(M19="","",VLOOKUP(N19,$V$5:$BB$17,K19,FALSE)) -> 19507 | P19: =IF(L19="","",IF(H19="DXB",46,IF(H19="AUH",51,""))) -> 46 | Q19: =IF(AND(LEFT(D19,1)="F",G19="Married",L19>17,L19<P19),HLOOKUP(E19,$W$1:$AA$2,2,FALSE),0) -> 0 | R19: =IF(M19="","",O19+Q19) -> 19507 | V19: A | W19: M | X19: E | Y19: =V19&W19&X19 -> AME | Z19: 2
A20: =IF(C20="","",A19+1) -> 15 | B20: Arsalan Ahmed | C20: 34737 | D20: MALE | E20: A | F20: Employee | G20: Married | H20: DXB | J20: =IF(D20="","",E20&LEFT(D20)&IF(F20="Employee","E","D")) -> AME | K20: =IF(J20="","",VLOOKUP(J20,$Y$19:$Z$50,2,FALSE)) -> 2 | L20: =IF(C20="","",DATEDIF(C20,'Premium Table'!$B$6,"Y")) -> 31 | M20: =IF(L20="","",IF(H20="","Choose Plan (DXB/AUH)",IF(H20="DXB",VLOOKUP(L20,$V$55:$W$154,2,FALSE),IF(H20="AUH",VLOOKUP(L20,$V$55:$X$154,3,FALSE),"Choose Plan (DXB/AUH)")))) -> 31 - 35 | N20: =IF(L20="","",IF(M20="","",IF(H20="DXB",VLOOKUP(M20,DXBAgeBr,3,FALSE),IF(H20="AUH",VLOOKUP(M20,AUHAgeBr,2,FALSE),"")))) -> 5 | O20: =IF(M20="","",VLOOKUP(N20,$V$5:$BB$17,K20,FALSE)) -> 6915 | P20: =IF(L20="","",IF(H20="DXB",46,IF(H20="AUH",51,""))) -> 46 | Q20: =IF(AND(LEFT(D20,1)="F",G20="Married",L20>17,L20<P20),HLOOKUP(E20,$W$1:$AA$2,2,FALSE),0) -> 0 | R20: =IF(M20="","",O20+Q20) -> 6915 | V20: A | W20: F | X20: E | Y20: =V20&W20&X20 -> AFE | Z20: 3
A21: =IF(C21="","",A20+1) -> 16 | B21: Mannal Ajaz | C21: 35922 | D21: FEMALE | E21: A | F21: Spouse | G21: Married | H21: DXB | J21: =IF(D21="","",E21&LEFT(D21)&IF(F21="Employee","E","D")) -> AFD | K21: =IF(J21="","",VLOOKUP(J21,$Y$19:$Z$50,2,FALSE)) -> 5 | L21: =IF(C21="","",DATEDIF(C21,'Premium Table'!$B$6,"Y")) -> 27 | M21: =IF(L21="","",IF(H21="","Choose Plan (DXB/AUH)",IF(H21="DXB",VLOOKUP(L21,$V$55:$W$154,2,FALSE),IF(H21="AUH",VLOOKUP(L21,$V$55:$X$154,3,FALSE),"Choose Plan (DXB/AUH)")))) -> 26 - 30 | N21: =IF(L21="","",IF(M21="","",IF(H21="DXB",VLOOKUP(M21,DXBAgeBr,3,FALSE),IF(H21="AUH",VLOOKUP(M21,AUHAgeBr,2,FALSE),"")))) -> 4 | O21: =IF(M21="","",VLOOKUP(N21,$V$5:$BB$17,K21,FALSE)) -> 7304 | P21: =IF(L21="","",IF(H21="DXB",46,IF(H21="AUH",51,""))) -> 46 | Q21: =IF(AND(LEFT(D21,1)="F",G21="Married",L21>17,L21<P21),HLOOKUP(E21,$W$1:$AA$2,2,FALSE),0) -> 5244 | R21: =IF(M21="","",O21+Q21) -> 12548 | V21: A | W21: M | X21: D | Y21: =V21&W21&X21 -> AMD | Z21: 4
A22: =IF(C22="","",A21+1) -> 17 | B22: Shayan Ahmed | C22: 35231 | D22: MALE | E22: A | F22: Employee | G22: Single | H22: DXB | J22: =IF(D22="","",E22&LEFT(D22)&IF(F22="Employee","E","D")) -> AME | K22: =IF(J22="","",VLOOKUP(J22,$Y$19:$Z$50,2,FALSE)) -> 2 | L22: =IF(C22="","",DATEDIF(C22,'Premium Table'!$B$6,"Y")) -> 29 | M22: =IF(L22="","",IF(H22="","Choose Plan (DXB/AUH)",IF(H22="DXB",VLOOKUP(L22,$V$55:$W$154,2,FALSE),IF(H22="AUH",VLOOKUP(L22,$V$55:$X$154,3,FALSE),"Choose Plan (DXB/AUH)")))) -> 26 - 30 | N22: =IF(L22="","",IF(M22="","",IF(H22="DXB",VLOOKUP(M22,DXBAgeBr,3,FALSE),IF(H22="AUH",VLOOKUP(M22,AUHAgeBr,2,FALSE),"")))) -> 4 | O22: =IF(M22="","",VLOOKUP(N22,$V$5:$BB$17,K22,FALSE)) -> 5833 | P22: =IF(L22="","",IF(H22="DXB",46,IF(H22="AUH",51,""))) -> 46 | Q22: =IF(AND(LEFT(D22,1)="F",G22="Married",L22>17,L22<P22),HLOOKUP(E22,$W$1:$AA$2,2,FALSE),0) -> 0 | R22: =IF(M22="","",O22+Q22) -> 5833 | V22: A | W22: F | X22: D | Y22: =V22&W22&X22 -> AFD | Z22: 5
A23: =IF(C23="","",A22+1) | J23: =IF(D23="","",E23&LEFT(D23)&IF(F23="Employee","E","D")) | K23: =IF(J23="","",VLOOKUP(J23,$Y$19:$Z$50,2,FALSE)) | L23: =IF(C23="","",DATEDIF(C23,'Premium Table'!$B$6,"Y")) | M23: =IF(L23="","",IF(H23="","Choose Plan (DXB/AUH)",IF(H23="DXB",VLOOKUP(L23,$V$55:$W$154,2,FALSE),IF(H23="AUH",VLOOKUP(L23,$V$55:$X$154,3,FALSE),"Choose Plan (DXB/AUH)")))) | N23: =IF(L23="","",IF(M23="","",IF(H23="DXB",VLOOKUP(M23,DXBAgeBr,3,FALSE),IF(H23="AUH",VLOOKUP(M23,AUHAgeBr,2,FALSE),"")))) | O23: =IF(M23="","",VLOOKUP(N23,$V$5:$BB$17,K23,FALSE)) | P23: =IF(L23="","",IF(H23="DXB",46,IF(H23="AUH",51,""))) | Q23: =IF(AND(LEFT(D23,1)="F",G23="Married",L23>17,L23<P23),HLOOKUP(E23,$W$1:$AA$2,2,FALSE),0) -> 0 | R23: =IF(M23="","",O23+Q23) | V23: B | W23: M | X23: E | Y23: =V23&W23&X23 -> BME | Z23: 6
A24: =IF(C24="","",A23+1) | J24: =IF(D24="","",E24&LEFT(D24)&IF(F24="Employee","E","D")) | K24: =IF(J24="","",VLOOKUP(J24,$Y$19:$Z$50,2,FALSE)) | L24: =IF(C24="","",DATEDIF(C24,'Premium Table'!$B$6,"Y")) | M24: =IF(L24="","",IF(H24="","Choose Plan (DXB/AUH)",IF(H24="DXB",VLOOKUP(L24,$V$55:$W$154,2,FALSE),IF(H24="AUH",VLOOKUP(L24,$V$55:$X$154,3,FALSE),"Choose Plan (DXB/AUH)")))) | N24: =IF(L24="","",IF(M24="","",IF(H24="DXB",VLOOKUP(M24,DXBAgeBr,3,FALSE),IF(H24="AUH",VLOOKUP(M24,AUHAgeBr,2,FALSE),"")))) | O24: =IF(M24="","",VLOOKUP(N24,$V$5:$BB$17,K24,FALSE)) | P24: =IF(L24="","",IF(H24="DXB",46,IF(H24="AUH",51,""))) | Q24: =IF(AND(LEFT(D24,1)="F",G24="Married",L24>17,L24<P24),HLOOKUP(E24,$W$1:$AA$2,2,FALSE),0) -> 0 | R24: =IF(M24="","",O24+Q24) | V24: B | W24: F | X24: E | Y24: =V24&W24&X24 -> BFE | Z24: 7
A25: =IF(C25="","",A24+1) | J25: =IF(D25="","",E25&LEFT(D25)&IF(F25="Employee","E","D")) | K25: =IF(J25="","",VLOOKUP(J25,$Y$19:$Z$50,2,FALSE)) | L25: =IF(C25="","",DATEDIF(C25,'Premium Table'!$B$6,"Y")) | M25: =IF(L25="","",IF(H25="","Choose Plan (DXB/AUH)",IF(H25="DXB",VLOOKUP(L25,$V$55:$W$154,2,FALSE),IF(H25="AUH",VLOOKUP(L25,$V$55:$X$154,3,FALSE),"Choose Plan (DXB/AUH)")))) | N25: =IF(L25="","",IF(M25="","",IF(H25="DXB",VLOOKUP(M25,DXBAgeBr,3,FALSE),IF(H25="AUH",VLOOKUP(M25,AUHAgeBr,2,FALSE),"")))) | O25: =IF(M25="","",VLOOKUP(N25,$V$5:$BB$17,K25,FALSE)) | P25: =IF(L25="","",IF(H25="DXB",46,IF(H25="AUH",51,""))) | Q25: =IF(AND(LEFT(D25,1)="F",G25="Married",L25>17,L25<P25),HLOOKUP(E25,$W$1:$AA$2,2,FALSE),0) -> 0 | R25: =IF(M25="","",O25+Q25) | V25: B | W25: M | X25: D | Y25: =V25&W25&X25 -> BMD | Z25: 8
A26: =IF(C26="","",A25+1) | J26: =IF(D26="","",E26&LEFT(D26)&IF(F26="Employee","E","D")) | K26: =IF(J26="","",VLOOKUP(J26,$Y$19:$Z$50,2,FALSE)) | L26: =IF(C26="","",DATEDIF(C26,'Premium Table'!$B$6,"Y")) | M26: =IF(L26="","",IF(H26="","Choose Plan (DXB/AUH)",IF(H26="DXB",VLOOKUP(L26,$V$55:$W$154,2,FALSE),IF(H26="AUH",VLOOKUP(L26,$V$55:$X$154,3,FALSE),"Choose Plan (DXB/AUH)")))) | N26: =IF(L26="","",IF(M26="","",IF(H26="DXB",VLOOKUP(M26,DXBAgeBr,3,FALSE),IF(H26="AUH",VLOOKUP(M26,AUHAgeBr,2,FALSE),"")))) | O26: =IF(M26="","",VLOOKUP(N26,$V$5:$BB$17,K26,FALSE)) | P26: =IF(L26="","",IF(H26="DXB",46,IF(H26="AUH",51,""))) | Q26: =IF(AND(LEFT(D26,1)="F",G26="Married",L26>17,L26<P26),HLOOKUP(E26,$W$1:$AA$2,2,FALSE),0) -> 0 | R26: =IF(M26="","",O26+Q26) | V26: B | W26: F | X26: D | Y26: =V26&W26&X26 -> BFD | Z26: 9
A27: =IF(C27="","",A26+1) | J27: =IF(D27="","",E27&LEFT(D27)&IF(F27="Employee","E","D")) | K27: =IF(J27="","",VLOOKUP(J27,$Y$19:$Z$50,2,FALSE)) | L27: =IF(C27="","",DATEDIF(C27,'Premium Table'!$B$6,"Y")) | M27: =IF(L27="","",IF(H27="","Choose Plan (DXB/AUH)",IF(H27="DXB",VLOOKUP(L27,$V$55:$W$154,2,FALSE),IF(H27="AUH",VLOOKUP(L27,$V$55:$X$154,3,FALSE),"Choose Plan (DXB/AUH)")))) | N27: =IF(L27="","",IF(M27="","",IF(H27="DXB",VLOOKUP(M27,DXBAgeBr,3,FALSE),IF(H27="AUH",VLOOKUP(M27,AUHAgeBr,2,FALSE),"")))) | O27: =IF(M27="","",VLOOKUP(N27,$V$5:$BB$17,K27,FALSE)) | P27: =IF(L27="","",IF(H27="DXB",46,IF(H27="AUH",51,""))) | Q27: =IF(AND(LEFT(D27,1)="F",G27="Married",L27>17,L27<P27),HLOOKUP(E27,$W$1:$AA$2,2,FALSE),0) -> 0 | R27: =IF(M27="","",O27+Q27) | V27: C | W27: M | X27: E | Y27: =V27&W27&X27 -> CME | Z27: 10
A28: =IF(C28="","",A27+1) | J28: =IF(D28="","",E28&LEFT(D28)&IF(F28="Employee","E","D")) | K28: =IF(J28="","",VLOOKUP(J28,$Y$19:$Z$50,2,FALSE)) | L28: =IF(C28="","",DATEDIF(C28,'Premium Table'!$B$6,"Y")) | M28: =IF(L28="","",IF(H28="","Choose Plan (DXB/AUH)",IF(H28="DXB",VLOOKUP(L28,$V$55:$W$154,2,FALSE),IF(H28="AUH",VLOOKUP(L28,$V$55:$X$154,3,FALSE),"Choose Plan (DXB/AUH)")))) | N28: =IF(L28="","",IF(M28="","",IF(H28="DXB",VLOOKUP(M28,DXBAgeBr,3,FALSE),IF(H28="AUH",VLOOKUP(M28,AUHAgeBr,2,FALSE),"")))) | O28: =IF(M28="","",VLOOKUP(N28,$V$5:$BB$17,K28,FALSE)) | P28: =IF(L28="","",IF(H28="DXB",46,IF(H28="AUH",51,""))) | Q28: =IF(AND(LEFT(D28,1)="F",G28="Married",L28>17,L28<P28),HLOOKUP(E28,$W$1:$AA$2,2,FALSE),0) -> 0 | R28: =IF(M28="","",O28+Q28) | V28: C | W28: F | X28: E | Y28: =V28&W28&X28 -> CFE | Z28: 11
A29: =IF(C29="","",A28+1) | J29: =IF(D29="","",E29&LEFT(D29)&IF(F29="Employee","E","D")) | K29: =IF(J29="","",VLOOKUP(J29,$Y$19:$Z$50,2,FALSE)) | L29: =IF(C29="","",DATEDIF(C29,'Premium Table'!$B$6,"Y")) | M29: =IF(L29="","",IF(H29="","Choose Plan (DXB/AUH)",IF(H29="DXB",VLOOKUP(L29,$V$55:$W$154,2,FALSE),IF(H29="AUH",VLOOKUP(L29,$V$55:$X$154,3,FALSE),"Choose Plan (DXB/AUH)")))) | N29: =IF(L29="","",IF(M29="","",IF(H29="DXB",VLOOKUP(M29,DXBAgeBr,3,FALSE),IF(H29="AUH",VLOOKUP(M29,AUHAgeBr,2,FALSE),"")))) | O29: =IF(M29="","",VLOOKUP(N29,$V$5:$BB$17,K29,FALSE)) | P29: =IF(L29="","",IF(H29="DXB",46,IF(H29="AUH",51,""))) | Q29: =IF(AND(LEFT(D29,1)="F",G29="Married",L29>17,L29<P29),HLOOKUP(E29,$W$1:$AA$2,2,FALSE),0) -> 0 | R29: =IF(M29="","",O29+Q29) | V29: C | W29: M | X29: D | Y29: =V29&W29&X29 -> CMD | Z29: 12
A30: =IF(C30="","",A29+1) | J30: =IF(D30="","",E30&LEFT(D30)&IF(F30="Employee","E","D")) | K30: =IF(J30="","",VLOOKUP(J30,$Y$19:$Z$50,2,FALSE)) | L30: =IF(C30="","",DATEDIF(C30,'Premium Table'!$B$6,"Y")) | M30: =IF(L30="","",IF(H30="","Choose Plan (DXB/AUH)",IF(H30="DXB",VLOOKUP(L30,$V$55:$W$154,2,FALSE),IF(H30="AUH",VLOOKUP(L30,$V$55:$X$154,3,FALSE),"Choose Plan (DXB/AUH)")))) | N30: =IF(L30="","",IF(M30="","",IF(H30="DXB",VLOOKUP(M30,DXBAgeBr,3,FALSE),IF(H30="AUH",VLOOKUP(M30,AUHAgeBr,2,FALSE),"")))) | O30: =IF(M30="","",VLOOKUP(N30,$V$5:$BB$17,K30,FALSE)) | P30: =IF(L30="","",IF(H30="DXB",46,IF(H30="AUH",51,""))) | Q30: =IF(AND(LEFT(D30,1)="F",G30="Married",L30>17,L30<P30),HLOOKUP(E30,$W$1:$AA$2,2,FALSE),0) -> 0 | R30: =IF(M30="","",O30+Q30) | V30: C | W30: F | X30: D | Y30: =V30&W30&X30 -> CFD | Z30: 13
A31: =IF(C31="","",A30+1) | J31: =IF(D31="","",E31&LEFT(D31)&IF(F31="Employee","E","D")) | K31: =IF(J31="","",VLOOKUP(J31,$Y$19:$Z$50,2,FALSE)) | L31: =IF(C31="","",DATEDIF(C31,'Premium Table'!$B$6,"Y")) | M31: =IF(L31="","",IF(H31="","Choose Plan (DXB/AUH)",IF(H31="DXB",VLOOKUP(L31,$V$55:$W$154,2,FALSE),IF(H31="AUH",VLOOKUP(L31,$V$55:$X$154,3,FALSE),"Choose Plan (DXB/AUH)")))) | N31: =IF(L31="","",IF(M31="","",IF(H31="DXB",VLOOKUP(M31,DXBAgeBr,3,FALSE),IF(H31="AUH",VLOOKUP(M31,AUHAgeBr,2,FALSE),"")))) | O31: =IF(M31="","",VLOOKUP(N31,$V$5:$BB$17,K31,FALSE)) | P31: =IF(L31="","",IF(H31="DXB",46,IF(H31="AUH",51,""))) | Q31: =IF(AND(LEFT(D31,1)="F",G31="Married",L31>17,L31<P31),HLOOKUP(E31,$W$1:$AA$2,2,FALSE),0) -> 0 | R31: =IF(M31="","",O31+Q31) | V31: D | W31: M | X31: E | Y31: =V31&W31&X31 -> DME | Z31: 14
A32: =IF(C32="","",A31+1) | J32: =IF(D32="","",E32&LEFT(D32)&IF(F32="Employee","E","D")) | K32: =IF(J32="","",VLOOKUP(J32,$Y$19:$Z$50,2,FALSE)) | L32: =IF(C32="","",DATEDIF(C32,'Premium Table'!$B$6,"Y")) | M32: =IF(L32="","",IF(H32="","Choose Plan (DXB/AUH)",IF(H32="DXB",VLOOKUP(L32,$V$55:$W$154,2,FALSE),IF(H32="AUH",VLOOKUP(L32,$V$55:$X$154,3,FALSE),"Choose Plan (DXB/AUH)")))) | N32: =IF(L32="","",IF(M32="","",IF(H32="DXB",VLOOKUP(M32,DXBAgeBr,3,FALSE),IF(H32="AUH",VLOOKUP(M32,AUHAgeBr,2,FALSE),"")))) | O32: =IF(M32="","",VLOOKUP(N32,$V$5:$BB$17,K32,FALSE)) | P32: =IF(L32="","",IF(H32="DXB",46,IF(H32="AUH",51,""))) | Q32: =IF(AND(LEFT(D32,1)="F",G32="Married",L32>17,L32<P32),HLOOKUP(E32,$W$1:$AA$2,2,FALSE),0) -> 0 | R32: =IF(M32="","",O32+Q32) | V32: D | W32: F | X32: E | Y32: =V32&W32&X32 -> DFE | Z32: 15
A33: =IF(C33="","",A32+1) | J33: =IF(D33="","",E33&LEFT(D33)&IF(F33="Employee","E","D")) | K33: =IF(J33="","",VLOOKUP(J33,$Y$19:$Z$50,2,FALSE)) | L33: =IF(C33="","",DATEDIF(C33,'Premium Table'!$B$6,"Y")) | M33: =IF(L33="","",IF(H33="","Choose Plan (DXB/AUH)",IF(H33="DXB",VLOOKUP(L33,$V$55:$W$154,2,FALSE),IF(H33="AUH",VLOOKUP(L33,$V$55:$X$154,3,FALSE),"Choose Plan (DXB/AUH)")))) | N33: =IF(L33="","",IF(M33="","",IF(H33="DXB",VLOOKUP(M33,DXBAgeBr,3,FALSE),IF(H33="AUH",VLOOKUP(M33,AUHAgeBr,2,FALSE),"")))) | O33: =IF(M33="","",VLOOKUP(N33,$V$5:$BB$17,K33,FALSE)) | P33: =IF(L33="","",IF(H33="DXB",46,IF(H33="AUH",51,""))) | Q33: =IF(AND(LEFT(D33,1)="F",G33="Married",L33>17,L33<P33),HLOOKUP(E33,$W$1:$AA$2,2,FALSE),0) -> 0 | R33: =IF(M33="","",O33+Q33) | V33: D | W33: M | X33: D | Y33: =V33&W33&X33 -> DMD | Z33: 16
A34: =IF(C34="","",A33+1) | J34: =IF(D34="","",E34&LEFT(D34)&IF(F34="Employee","E","D")) | K34: =IF(J34="","",VLOOKUP(J34,$Y$19:$Z$50,2,FALSE)) | L34: =IF(C34="","",DATEDIF(C34,'Premium Table'!$B$6,"Y")) | M34: =IF(L34="","",IF(H34="","Choose Plan (DXB/AUH)",IF(H34="DXB",VLOOKUP(L34,$V$55:$W$154,2,FALSE),IF(H34="AUH",VLOOKUP(L34,$V$55:$X$154,3,FALSE),"Choose Plan (DXB/AUH)")))) | N34: =IF(L34="","",IF(M34="","",IF(H34="DXB",VLOOKUP(M34,DXBAgeBr,3,FALSE),IF(H34="AUH",VLOOKUP(M34,AUHAgeBr,2,FALSE),"")))) | O34: =IF(M34="","",VLOOKUP(N34,$V$5:$BB$17,K34,FALSE)) | P34: =IF(L34="","",IF(H34="DXB",46,IF(H34="AUH",51,""))) | Q34: =IF(AND(LEFT(D34,1)="F",G34="Married",L34>17,L34<P34),HLOOKUP(E34,$W$1:$AA$2,2,FALSE),0) -> 0 | R34: =IF(M34="","",O34+Q34) | V34: D | W34: F | X34: D | Y34: =V34&W34&X34 -> DFD | Z34: 17
... A50: =IF(C50="","",A49+1) | J50: =IF(D50="","",E50&LEFT(D50)&IF(F50="Employee","E","D")) | K50: =IF(J50="","",VLOOKUP(J50,$Y$19:$Z$50,2,FALSE)) | L50: =IF(C50="","",DATEDIF(C50,'Premium Table'!$B$6,"Y")) | M50: =IF(L50="","",IF(H50="","Choose Plan (DXB/AUH)",IF(H50="DXB",VLOOKUP(L50,$V$55:$W$154,2,FALSE),IF(H50="AUH",VLOOKUP(L50,$V$55:$X$154,3,FALSE),"Choose Plan (DXB/AUH)")))) | N50: =IF(L50="","",IF(M50="","",IF(H50="DXB",VLOOKUP(M50,DXBAgeBr,3,FALSE),IF(H50="AUH",VLOOKUP(M50,AUHAgeBr,2,FALSE),"")))) | O50: =IF(M50="","",VLOOKUP(N50,$V$5:$BB$17,K50,FALSE)) | P50: =IF(L50="","",IF(H50="DXB",46,IF(H50="AUH",51,""))) | Q50: =IF(AND(LEFT(D50,1)="F",G50="Married",L50>17,L50<P50),HLOOKUP(E50,$W$1:$AA$2,2,FALSE),0) -> 0 | R50: =IF(M50="","",O50+Q50) | V50: H | W50: F | X50: D | Y50: =V50&W50&X50 -> HFD | Z50: 33
A51: =IF(C51="","",A50+1) | J51: =IF(D51="","",E51&LEFT(D51)&IF(F51="Employee","E","D")) | K51: =IF(J51="","",VLOOKUP(J51,$Y$19:$Z$50,2,FALSE)) | L51: =IF(C51="","",DATEDIF(C51,'Premium Table'!$B$6,"Y")) | M51: =IF(L51="","",IF(H51="","Choose Plan (DXB/AUH)",IF(H51="DXB",VLOOKUP(L51,$V$55:$W$154,2,FALSE),IF(H51="AUH",VLOOKUP(L51,$V$55:$X$154,3,FALSE),"Choose Plan (DXB/AUH)")))) | N51: =IF(L51="","",IF(M51="","",IF(H51="DXB",VLOOKUP(M51,DXBAgeBr,3,FALSE),IF(H51="AUH",VLOOKUP(M51,AUHAgeBr,2,FALSE),"")))) | O51: =IF(M51="","",VLOOKUP(N51,$V$5:$BB$17,K51,FALSE)) | P51: =IF(L51="","",IF(H51="DXB",46,IF(H51="AUH",51,""))) | Q51: =IF(AND(LEFT(D51,1)="F",G51="Married",L51>17,L51<P51),HLOOKUP(E51,$W$1:$AA$2,2,FALSE),0) -> 0 | R51: =IF(M51="","",O51+Q51)
A52: =IF(C52="","",A51+1) | J52: =IF(D52="","",E52&LEFT(D52)&IF(F52="Employee","E","D")) | K52: =IF(J52="","",VLOOKUP(J52,$Y$19:$Z$50,2,FALSE)) | L52: =IF(C52="","",DATEDIF(C52,'Premium Table'!$B$6,"Y")) | M52: =IF(L52="","",IF(H52="","Choose Plan (DXB/AUH)",IF(H52="DXB",VLOOKUP(L52,$V$55:$W$154,2,FALSE),IF(H52="AUH",VLOOKUP(L52,$V$55:$X$154,3,FALSE),"Choose Plan (DXB/AUH)")))) | N52: =IF(L52="","",IF(M52="","",IF(H52="DXB",VLOOKUP(M52,DXBAgeBr,3,FALSE),IF(H52="AUH",VLOOKUP(M52,AUHAgeBr,2,FALSE),"")))) | O52: =IF(M52="","",VLOOKUP(N52,$V$5:$BB$17,K52,FALSE)) | P52: =IF(L52="","",IF(H52="DXB",46,IF(H52="AUH",51,""))) | Q52: =IF(AND(LEFT(D52,1)="F",G52="Married",L52>17,L52<P52),HLOOKUP(E52,$W$1:$AA$2,2,FALSE),0) -> 0 | R52: =IF(M52="","",O52+Q52)
A53: =IF(C53="","",A52+1) | J53: =IF(D53="","",E53&LEFT(D53)&IF(F53="Employee","E","D")) | K53: =IF(J53="","",VLOOKUP(J53,$Y$19:$Z$50,2,FALSE)) | L53: =IF(C53="","",DATEDIF(C53,'Premium Table'!$B$6,"Y")) | M53: =IF(L53="","",IF(H53="","Choose Plan (DXB/AUH)",IF(H53="DXB",VLOOKUP(L53,$V$55:$W$154,2,FALSE),IF(H53="AUH",VLOOKUP(L53,$V$55:$X$154,3,FALSE),"Choose Plan (DXB/AUH)")))) | N53: =IF(L53="","",IF(M53="","",IF(H53="DXB",VLOOKUP(M53,DXBAgeBr,3,FALSE),IF(H53="AUH",VLOOKUP(M53,AUHAgeBr,2,FALSE),"")))) | O53: =IF(M53="","",VLOOKUP(N53,$V$5:$BB$17,K53,FALSE)) | P53: =IF(L53="","",IF(H53="DXB",46,IF(H53="AUH",51,""))) | Q53: =IF(AND(LEFT(D53,1)="F",G53="Married",L53>17,L53<P53),HLOOKUP(E53,$W$1:$AA$2,2,FALSE),0) -> 0 | R53: =IF(M53="","",O53+Q53)
A54: =IF(C54="","",A53+1) | J54: =IF(D54="","",E54&LEFT(D54)&IF(F54="Employee","E","D")) | K54: =IF(J54="","",VLOOKUP(J54,$Y$19:$Z$50,2,FALSE)) | L54: =IF(C54="","",DATEDIF(C54,'Premium Table'!$B$6,"Y")) | M54: =IF(L54="","",IF(H54="","Choose Plan (DXB/AUH)",IF(H54="DXB",VLOOKUP(L54,$V$55:$W$154,2,FALSE),IF(H54="AUH",VLOOKUP(L54,$V$55:$X$154,3,FALSE),"Choose Plan (DXB/AUH)")))) | N54: =IF(L54="","",IF(M54="","",IF(H54="DXB",VLOOKUP(M54,DXBAgeBr,3,FALSE),IF(H54="AUH",VLOOKUP(M54,AUHAgeBr,2,FALSE),"")))) | O54: =IF(M54="","",VLOOKUP(N54,$V$5:$BB$17,K54,FALSE)) | P54: =IF(L54="","",IF(H54="DXB",46,IF(H54="AUH",51,""))) | Q54: =IF(AND(LEFT(D54,1)="F",G54="Married",L54>17,L54<P54),HLOOKUP(E54,$W$1:$AA$2,2,FALSE),0) -> 0 | R54: =IF(M54="","",O54+Q54)
A55: =IF(C55="","",A54+1) | J55: =IF(D55="","",E55&LEFT(D55)&IF(F55="Employee","E","D")) | K55: =IF(J55="","",VLOOKUP(J55,$Y$19:$Z$50,2,FALSE)) | L55: =IF(C55="","",DATEDIF(C55,'Premium Table'!$B$6,"Y")) | M55: =IF(L55="","",IF(H55="","Choose Plan (DXB/AUH)",IF(H55="DXB",VLOOKUP(L55,$V$55:$W$154,2,FALSE),IF(H55="AUH",VLOOKUP(L55,$V$55:$X$154,3,FALSE),"Choose Plan (DXB/AUH)")))) | N55: =IF(L55="","",IF(M55="","",IF(H55="DXB",VLOOKUP(M55,DXBAgeBr,3,FALSE),IF(H55="AUH",VLOOKUP(M55,AUHAgeBr,2,FALSE),"")))) | O55: =IF(M55="","",VLOOKUP(N55,$V$5:$BB$17,K55,FALSE)) | P55: =IF(L55="","",IF(H55="DXB",46,IF(H55="AUH",51,""))) | Q55: =IF(AND(LEFT(D55,1)="F",G55="Married",L55>17,L55<P55),HLOOKUP(E55,$W$1:$AA$2,2,FALSE),0) -> 0 | R55: =IF(M55="","",O55+Q55) | V55: 0 | W55: 0 - 10 | X55: 0 - 17
A56: =IF(C56="","",A55+1) | J56: =IF(D56="","",E56&LEFT(D56)&IF(F56="Employee","E","D")) | K56: =IF(J56="","",VLOOKUP(J56,$Y$19:$Z$50,2,FALSE)) | L56: =IF(C56="","",DATEDIF(C56,'Premium Table'!$B$6,"Y")) | M56: =IF(L56="","",IF(H56="","Choose Plan (DXB/AUH)",IF(H56="DXB",VLOOKUP(L56,$V$55:$W$154,2,FALSE),IF(H56="AUH",VLOOKUP(L56,$V$55:$X$154,3,FALSE),"Choose Plan (DXB/AUH)")))) | N56: =IF(L56="","",IF(M56="","",IF(H56="DXB",VLOOKUP(M56,DXBAgeBr,3,FALSE),IF(H56="AUH",VLOOKUP(M56,AUHAgeBr,2,FALSE),"")))) | O56: =IF(M56="","",VLOOKUP(N56,$V$5:$BB$17,K56,FALSE)) | P56: =IF(L56="","",IF(H56="DXB",46,IF(H56="AUH",51,""))) | Q56: =IF(AND(LEFT(D56,1)="F",G56="Married",L56>17,L56<P56),HLOOKUP(E56,$W$1:$AA$2,2,FALSE),0) -> 0 | R56: =IF(M56="","",O56+Q56) | V56: 1 | W56: 0 - 10 | X56: 0 - 17
A57: =IF(C57="","",A56+1) | J57: =IF(D57="","",E57&LEFT(D57)&IF(F57="Employee","E","D")) | K57: =IF(J57="","",VLOOKUP(J57,$Y$19:$Z$50,2,FALSE)) | L57: =IF(C57="","",DATEDIF(C57,'Premium Table'!$B$6,"Y")) | M57: =IF(L57="","",IF(H57="","Choose Plan (DXB/AUH)",IF(H57="DXB",VLOOKUP(L57,$V$55:$W$154,2,FALSE),IF(H57="AUH",VLOOKUP(L57,$V$55:$X$154,3,FALSE),"Choose Plan (DXB/AUH)")))) | N57: =IF(L57="","",IF(M57="","",IF(H57="DXB",VLOOKUP(M57,DXBAgeBr,3,FALSE),IF(H57="AUH",VLOOKUP(M57,AUHAgeBr,2,FALSE),"")))) | O57: =IF(M57="","",VLOOKUP(N57,$V$5:$BB$17,K57,FALSE)) | P57: =IF(L57="","",IF(H57="DXB",46,IF(H57="AUH",51,""))) | Q57: =IF(AND(LEFT(D57,1)="F",G57="Married",L57>17,L57<P57),HLOOKUP(E57,$W$1:$AA$2,2,FALSE),0) -> 0 | R57: =IF(M57="","",O57+Q57) | V57: 2 | W57: 0 - 10 | X57: 0 - 17
A58: =IF(C58="","",A57+1) | J58: =IF(D58="","",E58&LEFT(D58)&IF(F58="Employee","E","D")) | K58: =IF(J58="","",VLOOKUP(J58,$Y$19:$Z$50,2,FALSE)) | L58: =IF(C58="","",DATEDIF(C58,'Premium Table'!$B$6,"Y")) | M58: =IF(L58="","",IF(H58="","Choose Plan (DXB/AUH)",IF(H58="DXB",VLOOKUP(L58,$V$55:$W$154,2,FALSE),IF(H58="AUH",VLOOKUP(L58,$V$55:$X$154,3,FALSE),"Choose Plan (DXB/AUH)")))) | N58: =IF(L58="","",IF(M58="","",IF(H58="DXB",VLOOKUP(M58,DXBAgeBr,3,FALSE),IF(H58="AUH",VLOOKUP(M58,AUHAgeBr,2,FALSE),"")))) | O58: =IF(M58="","",VLOOKUP(N58,$V$5:$BB$17,K58,FALSE)) | P58: =IF(L58="","",IF(H58="DXB",46,IF(H58="AUH",51,""))) | Q58: =IF(AND(LEFT(D58,1)="F",G58="Married",L58>17,L58<P58),HLOOKUP(E58,$W$1:$AA$2,2,FALSE),0) -> 0 | R58: =IF(M58="","",O58+Q58) | V58: 3 | W58: 0 - 10 | X58: 0 - 17
A59: =IF(C59="","",A58+1) | J59: =IF(D59="","",E59&LEFT(D59)&IF(F59="Employee","E","D")) | K59: =IF(J59="","",VLOOKUP(J59,$Y$19:$Z$50,2,FALSE)) | L59: =IF(C59="","",DATEDIF(C59,'Premium Table'!$B$6,"Y")) | M59: =IF(L59="","",IF(H59="","Choose Plan (DXB/AUH)",IF(H59="DXB",VLOOKUP(L59,$V$55:$W$154,2,FALSE),IF(H59="AUH",VLOOKUP(L59,$V$55:$X$154,3,FALSE),"Choose Plan (DXB/AUH)")))) | N59: =IF(L59="","",IF(M59="","",IF(H59="DXB",VLOOKUP(M59,DXBAgeBr,3,FALSE),IF(H59="AUH",VLOOKUP(M59,AUHAgeBr,2,FALSE),"")))) | O59: =IF(M59="","",VLOOKUP(N59,$V$5:$BB$17,K59,FALSE)) | P59: =IF(L59="","",IF(H59="DXB",46,IF(H59="AUH",51,""))) | Q59: =IF(AND(LEFT(D59,1)="F",G59="Married",L59>17,L59<P59),HLOOKUP(E59,$W$1:$AA$2,2,FALSE),0) -> 0 | R59: =IF(M59="","",O59+Q59) | V59: 4 | W59: 0 - 10 | X59: 0 - 17
A60: =IF(C60="","",A59+1) | J60: =IF(D60="","",E60&LEFT(D60)&IF(F60="Employee","E","D")) | K60: =IF(J60="","",VLOOKUP(J60,$Y$19:$Z$50,2,FALSE)) | L60: =IF(C60="","",DATEDIF(C60,'Premium Table'!$B$6,"Y")) | M60: =IF(L60="","",IF(H60="","Choose Plan (DXB/AUH)",IF(H60="DXB",VLOOKUP(L60,$V$55:$W$154,2,FALSE),IF(H60="AUH",VLOOKUP(L60,$V$55:$X$154,3,FALSE),"Choose Plan (DXB/AUH)")))) | N60: =IF(L60="","",IF(M60="","",IF(H60="DXB",VLOOKUP(M60,DXBAgeBr,3,FALSE),IF(H60="AUH",VLOOKUP(M60,AUHAgeBr,2,FALSE),"")))) | O60: =IF(M60="","",VLOOKUP(N60,$V$5:$BB$17,K60,FALSE)) | P60: =IF(L60="","",IF(H60="DXB",46,IF(H60="AUH",51,""))) | Q60: =IF(AND(LEFT(D60,1)="F",G60="Married",L60>17,L60<P60),HLOOKUP(E60,$W$1:$AA$2,2,FALSE),0) -> 0 | R60: =IF(M60="","",O60+Q60) | V60: 5 | W60: 0 - 10 | X60: 0 - 17
A61: =IF(C61="","",A60+1) | J61: =IF(D61="","",E61&LEFT(D61)&IF(F61="Employee","E","D")) | K61: =IF(J61="","",VLOOKUP(J61,$Y$19:$Z$50,2,FALSE)) | L61: =IF(C61="","",DATEDIF(C61,'Premium Table'!$B$6,"Y")) | M61: =IF(L61="","",IF(H61="","Choose Plan (DXB/AUH)",IF(H61="DXB",VLOOKUP(L61,$V$55:$W$154,2,FALSE),IF(H61="AUH",VLOOKUP(L61,$V$55:$X$154,3,FALSE),"Choose Plan (DXB/AUH)")))) | N61: =IF(L61="","",IF(M61="","",IF(H61="DXB",VLOOKUP(M61,DXBAgeBr,3,FALSE),IF(H61="AUH",VLOOKUP(M61,AUHAgeBr,2,FALSE),"")))) | O61: =IF(M61="","",VLOOKUP(N61,$V$5:$BB$17,K61,FALSE)) | P61: =IF(L61="","",IF(H61="DXB",46,IF(H61="AUH",51,""))) | Q61: =IF(AND(LEFT(D61,1)="F",G61="Married",L61>17,L61<P61),HLOOKUP(E61,$W$1:$AA$2,2,FALSE),0) -> 0 | R61: =IF(M61="","",O61+Q61) | V61: 6 | W61: 0 - 10 | X61: 0 - 17
A62: =IF(C62="","",A61+1) | J62: =IF(D62="","",E62&LEFT(D62)&IF(F62="Employee","E","D")) | K62: =IF(J62="","",VLOOKUP(J62,$Y$19:$Z$50,2,FALSE)) | L62: =IF(C62="","",DATEDIF(C62,'Premium Table'!$B$6,"Y")) | M62: =IF(L62="","",IF(H62="","Choose Plan (DXB/AUH)",IF(H62="DXB",VLOOKUP(L62,$V$55:$W$154,2,FALSE),IF(H62="AUH",VLOOKUP(L62,$V$55:$X$154,3,FALSE),"Choose Plan (DXB/AUH)")))) | N62: =IF(L62="","",IF(M62="","",IF(H62="DXB",VLOOKUP(M62,DXBAgeBr,3,FALSE),IF(H62="AUH",VLOOKUP(M62,AUHAgeBr,2,FALSE),"")))) | O62: =IF(M62="","",VLOOKUP(N62,$V$5:$BB$17,K62,FALSE)) | P62: =IF(L62="","",IF(H62="DXB",46,IF(H62="AUH",51,""))) | Q62: =IF(AND(LEFT(D62,1)="F",G62="Married",L62>17,L62<P62),HLOOKUP(E62,$W$1:$AA$2,2,FALSE),0) -> 0 | R62: =IF(M62="","",O62+Q62) | V62: 7 | W62: 0 - 10 | X62: 0 - 17
A63: =IF(C63="","",A62+1) | J63: =IF(D63="","",E63&LEFT(D63)&IF(F63="Employee","E","D")) | K63: =IF(J63="","",VLOOKUP(J63,$Y$19:$Z$50,2,FALSE)) | L63: =IF(C63="","",DATEDIF(C63,'Premium Table'!$B$6,"Y")) | M63: =IF(L63="","",IF(H63="","Choose Plan (DXB/AUH)",IF(H63="DXB",VLOOKUP(L63,$V$55:$W$154,2,FALSE),IF(H63="AUH",VLOOKUP(L63,$V$55:$X$154,3,FALSE),"Choose Plan (DXB/AUH)")))) | N63: =IF(L63="","",IF(M63="","",IF(H63="DXB",VLOOKUP(M63,DXBAgeBr,3,FALSE),IF(H63="AUH",VLOOKUP(M63,AUHAgeBr,2,FALSE),"")))) | O63: =IF(M63="","",VLOOKUP(N63,$V$5:$BB$17,K63,FALSE)) | P63: =IF(L63="","",IF(H63="DXB",46,IF(H63="AUH",51,""))) | Q63: =IF(AND(LEFT(D63,1)="F",G63="Married",L63>17,L63<P63),HLOOKUP(E63,$W$1:$AA$2,2,FALSE),0) -> 0 | R63: =IF(M63="","",O63+Q63) | V63: 8 | W63: 0 - 10 | X63: 0 - 17
A64: =IF(C64="","",A63+1) | J64: =IF(D64="","",E64&LEFT(D64)&IF(F64="Employee","E","D")) | K64: =IF(J64="","",VLOOKUP(J64,$Y$19:$Z$50,2,FALSE)) | L64: =IF(C64="","",DATEDIF(C64,'Premium Table'!$B$6,"Y")) | M64: =IF(L64="","",IF(H64="","Choose Plan (DXB/AUH)",IF(H64="DXB",VLOOKUP(L64,$V$55:$W$154,2,FALSE),IF(H64="AUH",VLOOKUP(L64,$V$55:$X$154,3,FALSE),"Choose Plan (DXB/AUH)")))) | N64: =IF(L64="","",IF(M64="","",IF(H64="DXB",VLOOKUP(M64,DXBAgeBr,3,FALSE),IF(H64="AUH",VLOOKUP(M64,AUHAgeBr,2,FALSE),"")))) | O64: =IF(M64="","",VLOOKUP(N64,$V$5:$BB$17,K64,FALSE)) | P64: =IF(L64="","",IF(H64="DXB",46,IF(H64="AUH",51,""))) | Q64: =IF(AND(LEFT(D64,1)="F",G64="Married",L64>17,L64<P64),HLOOKUP(E64,$W$1:$AA$2,2,FALSE),0) -> 0 | R64: =IF(M64="","",O64+Q64) | V64: 9 | W64: 0 - 10 | X64: 0 - 17
A65: =IF(C65="","",A64+1) | J65: =IF(D65="","",E65&LEFT(D65)&IF(F65="Employee","E","D")) | K65: =IF(J65="","",VLOOKUP(J65,$Y$19:$Z$50,2,FALSE)) | L65: =IF(C65="","",DATEDIF(C65,'Premium Table'!$B$6,"Y")) | M65: =IF(L65="","",IF(H65="","Choose Plan (DXB/AUH)",IF(H65="DXB",VLOOKUP(L65,$V$55:$W$154,2,FALSE),IF(H65="AUH",VLOOKUP(L65,$V$55:$X$154,3,FALSE),"Choose Plan (DXB/AUH)")))) | N65: =IF(L65="","",IF(M65="","",IF(H65="DXB",VLOOKUP(M65,DXBAgeBr,3,FALSE),IF(H65="AUH",VLOOKUP(M65,AUHAgeBr,2,FALSE),"")))) | O65: =IF(M65="","",VLOOKUP(N65,$V$5:$BB$17,K65,FALSE)) | P65: =IF(L65="","",IF(H65="DXB",46,IF(H65="AUH",51,""))) | Q65: =IF(AND(LEFT(D65,1)="F",G65="Married",L65>17,L65<P65),HLOOKUP(E65,$W$1:$AA$2,2,FALSE),0) -> 0 | R65: =IF(M65="","",O65+Q65) | V65: 10 | W65: 0 - 10 | X65: 0 - 17
A66: =IF(C66="","",A65+1) | J66: =IF(D66="","",E66&LEFT(D66)&IF(F66="Employee","E","D")) | K66: =IF(J66="","",VLOOKUP(J66,$Y$19:$Z$50,2,FALSE)) | L66: =IF(C66="","",DATEDIF(C66,'Premium Table'!$B$6,"Y")) | M66: =IF(L66="","",IF(H66="","Choose Plan (DXB/AUH)",IF(H66="DXB",VLOOKUP(L66,$V$55:$W$154,2,FALSE),IF(H66="AUH",VLOOKUP(L66,$V$55:$X$154,3,FALSE),"Choose Plan (DXB/AUH)")))) | N66: =IF(L66="","",IF(M66="","",IF(H66="DXB",VLOOKUP(M66,DXBAgeBr,3,FALSE),IF(H66="AUH",VLOOKUP(M66,AUHAgeBr,2,FALSE),"")))) | O66: =IF(M66="","",VLOOKUP(N66,$V$5:$BB$17,K66,FALSE)) | P66: =IF(L66="","",IF(H66="DXB",46,IF(H66="AUH",51,""))) | Q66: =IF(AND(LEFT(D66,1)="F",G66="Married",L66>17,L66<P66),HLOOKUP(E66,$W$1:$AA$2,2,FALSE),0) -> 0 | R66: =IF(M66="","",O66+Q66) | V66: 11 | W66: 11 - 17 | X66: 0 - 17
... A154: =IF(C154="","",A153+1) | J154: =IF(D154="","",E154&LEFT(D154)&IF(F154="Employee","E","D")) | K154: =IF(J154="","",VLOOKUP(J154,$Y$19:$Z$50,2,FALSE)) | L154: =IF(C154="","",DATEDIF(C154,'Premium Table'!$B$6,"Y")) | M154: =IF(L154="","",IF(H154="","Choose Plan (DXB/AUH)",IF(H154="DXB",VLOOKUP(L154,$V$55:$W$154,2,FALSE),IF(H154="AUH",VLOOKUP(L154,$V$55:$X$154,3,FALSE),"Choose Plan (DXB/AUH)")))) | N154: =IF(L154="","",IF(M154="","",IF(H154="DXB",VLOOKUP(M154,DXBAgeBr,3,FALSE),IF(H154="AUH",VLOOKUP(M154,AUHAgeBr,2,FALSE),"")))) | O154: =IF(M154="","",VLOOKUP(N154,$V$5:$BB$17,K154,FALSE)) | P154: =IF(L154="","",IF(H154="DXB",46,IF(H154="AUH",51,""))) | Q154: =IF(AND(LEFT(D154,1)="F",G154="Married",L154>17,L154<P154),HLOOKUP(E154,$W$1:$AA$2,2,FALSE),0) -> 0 | R154: =IF(M154="","",O154+Q154) | V154: 99 | W154: 65 - 99 | X154: 65 - 99
A155: =IF(C155="","",A154+1) | J155: =IF(D155="","",E155&LEFT(D155)&IF(F155="Employee","E","D")) | K155: =IF(J155="","",VLOOKUP(J155,$Y$19:$Z$50,2,FALSE)) | L155: =IF(C155="","",DATEDIF(C155,'Premium Table'!$B$6,"Y")) | M155: =IF(L155="","",IF(H155="","Choose Plan (DXB/AUH)",IF(H155="DXB",VLOOKUP(L155,$V$55:$W$154,2,FALSE),IF(H155="AUH",VLOOKUP(L155,$V$55:$X$154,3,FALSE),"Choose Plan (DXB/AUH)")))) | N155: =IF(L155="","",IF(M155="","",IF(H155="DXB",VLOOKUP(M155,DXBAgeBr,3,FALSE),IF(H155="AUH",VLOOKUP(M155,AUHAgeBr,2,FALSE),"")))) | O155: =IF(M155="","",VLOOKUP(N155,$V$5:$BB$17,K155,FALSE)) | P155: =IF(L155="","",IF(H155="DXB",46,IF(H155="AUH",51,""))) | Q155: =IF(AND(LEFT(D155,1)="F",G155="Married",L155>17,L155<P155),HLOOKUP(E155,$W$1:$AA$2,2,FALSE),0) -> 0 | R155: =IF(M155="","",O155+Q155)
A156: =IF(C156="","",A155+1) | J156: =IF(D156="","",E156&LEFT(D156)&IF(F156="Employee","E","D")) | K156: =IF(J156="","",VLOOKUP(J156,$Y$19:$Z$50,2,FALSE)) | L156: =IF(C156="","",DATEDIF(C156,'Premium Table'!$B$6,"Y")) | M156: =IF(L156="","",IF(H156="","Choose Plan (DXB/AUH)",IF(H156="DXB",VLOOKUP(L156,$V$55:$W$154,2,FALSE),IF(H156="AUH",VLOOKUP(L156,$V$55:$X$154,3,FALSE),"Choose Plan (DXB/AUH)")))) | N156: =IF(L156="","",IF(M156="","",IF(H156="DXB",VLOOKUP(M156,DXBAgeBr,3,FALSE),IF(H156="AUH",VLOOKUP(M156,AUHAgeBr,2,FALSE),"")))) | O156: =IF(M156="","",VLOOKUP(N156,$V$5:$BB$17,K156,FALSE)) | P156: =IF(L156="","",IF(H156="DXB",46,IF(H156="AUH",51,""))) | Q156: =IF(AND(LEFT(D156,1)="F",G156="Married",L156>17,L156<P156),HLOOKUP(E156,$W$1:$AA$2,2,FALSE),0) -> 0 | R156: =IF(M156="","",O156+Q156)
A157: =IF(C157="","",A156+1) | J157: =IF(D157="","",E157&LEFT(D157)&IF(F157="Employee","E","D")) | K157: =IF(J157="","",VLOOKUP(J157,$Y$19:$Z$50,2,FALSE)) | L157: =IF(C157="","",DATEDIF(C157,'Premium Table'!$B$6,"Y")) | M157: =IF(L157="","",IF(H157="","Choose Plan (DXB/AUH)",IF(H157="DXB",VLOOKUP(L157,$V$55:$W$154,2,FALSE),IF(H157="AUH",VLOOKUP(L157,$V$55:$X$154,3,FALSE),"Choose Plan (DXB/AUH)")))) | N157: =IF(L157="","",IF(M157="","",IF(H157="DXB",VLOOKUP(M157,DXBAgeBr,3,FALSE),IF(H157="AUH",VLOOKUP(M157,AUHAgeBr,2,FALSE),"")))) | O157: =IF(M157="","",VLOOKUP(N157,$V$5:$BB$17,K157,FALSE)) | P157: =IF(L157="","",IF(H157="DXB",46,IF(H157="AUH",51,""))) | Q157: =IF(AND(LEFT(D157,1)="F",G157="Married",L157>17,L157<P157),HLOOKUP(E157,$W$1:$AA$2,2,FALSE),0) -> 0 | R157: =IF(M157="","",O157+Q157)
A158: =IF(C158="","",A157+1) | J158: =IF(D158="","",E158&LEFT(D158)&IF(F158="Employee","E","D")) | K158: =IF(J158="","",VLOOKUP(J158,$Y$19:$Z$50,2,FALSE)) | L158: =IF(C158="","",DATEDIF(C158,'Premium Table'!$B$6,"Y")) | M158: =IF(L158="","",IF(H158="","Choose Plan (DXB/AUH)",IF(H158="DXB",VLOOKUP(L158,$V$55:$W$154,2,FALSE),IF(H158="AUH",VLOOKUP(L158,$V$55:$X$154,3,FALSE),"Choose Plan (DXB/AUH)")))) | N158: =IF(L158="","",IF(M158="","",IF(H158="DXB",VLOOKUP(M158,DXBAgeBr,3,FALSE),IF(H158="AUH",VLOOKUP(M158,AUHAgeBr,2,FALSE),"")))) | O158: =IF(M158="","",VLOOKUP(N158,$V$5:$BB$17,K158,FALSE)) | P158: =IF(L158="","",IF(H158="DXB",46,IF(H158="AUH",51,""))) | Q158: =IF(AND(LEFT(D158,1)="F",G158="Married",L158>17,L158<P158),HLOOKUP(E158,$W$1:$AA$2,2,FALSE),0) -> 0 | R158: =IF(M158="","",O158+Q158)
A159: =IF(C159="","",A158+1) | J159: =IF(D159="","",E159&LEFT(D159)&IF(F159="Employee","E","D")) | K159: =IF(J159="","",VLOOKUP(J159,$Y$19:$Z$50,2,FALSE)) | L159: =IF(C159="","",DATEDIF(C159,'Premium Table'!$B$6,"Y")) | M159: =IF(L159="","",IF(H159="","Choose Plan (DXB/AUH)",IF(H159="DXB",VLOOKUP(L159,$V$55:$W$154,2,FALSE),IF(H159="AUH",VLOOKUP(L159,$V$55:$X$154,3,FALSE),"Choose Plan (DXB/AUH)")))) | N159: =IF(L159="","",IF(M159="","",IF(H159="DXB",VLOOKUP(M159,DXBAgeBr,3,FALSE),IF(H159="AUH",VLOOKUP(M159,AUHAgeBr,2,FALSE),"")))) | O159: =IF(M159="","",VLOOKUP(N159,$V$5:$BB$17,K159,FALSE)) | P159: =IF(L159="","",IF(H159="DXB",46,IF(H159="AUH",51,""))) | Q159: =IF(AND(LEFT(D159,1)="F",G159="Married",L159>17,L159<P159),HLOOKUP(E159,$W$1:$AA$2,2,FALSE),0) -> 0 | R159: =IF(M159="","",O159+Q159)
A160: =IF(C160="","",A159+1) | J160: =IF(D160="","",E160&LEFT(D160)&IF(F160="Employee","E","D")) | K160: =IF(J160="","",VLOOKUP(J160,$Y$19:$Z$50,2,FALSE)) | L160: =IF(C160="","",DATEDIF(C160,'Premium Table'!$B$6,"Y")) | M160: =IF(L160="","",IF(H160="","Choose Plan (DXB/AUH)",IF(H160="DXB",VLOOKUP(L160,$V$55:$W$154,2,FALSE),IF(H160="AUH",VLOOKUP(L160,$V$55:$X$154,3,FALSE),"Choose Plan (DXB/AUH)")))) | N160: =IF(L160="","",IF(M160="","",IF(H160="DXB",VLOOKUP(M160,DXBAgeBr,3,FALSE),IF(H160="AUH",VLOOKUP(M160,AUHAgeBr,2,FALSE),"")))) | O160: =IF(M160="","",VLOOKUP(N160,$V$5:$BB$17,K160,FALSE)) | P160: =IF(L160="","",IF(H160="DXB",46,IF(H160="AUH",51,""))) | Q160: =IF(AND(LEFT(D160,1)="F",G160="Married",L160>17,L160<P160),HLOOKUP(E160,$W$1:$AA$2,2,FALSE),0) -> 0 | R160: =IF(M160="","",O160+Q160)
A161: =IF(C161="","",A160+1) | J161: =IF(D161="","",E161&LEFT(D161)&IF(F161="Employee","E","D")) | K161: =IF(J161="","",VLOOKUP(J161,$Y$19:$Z$50,2,FALSE)) | L161: =IF(C161="","",DATEDIF(C161,'Premium Table'!$B$6,"Y")) | M161: =IF(L161="","",IF(H161="","Choose Plan (DXB/AUH)",IF(H161="DXB",VLOOKUP(L161,$V$55:$W$154,2,FALSE),IF(H161="AUH",VLOOKUP(L161,$V$55:$X$154,3,FALSE),"Choose Plan (DXB/AUH)")))) | N161: =IF(L161="","",IF(M161="","",IF(H161="DXB",VLOOKUP(M161,DXBAgeBr,3,FALSE),IF(H161="AUH",VLOOKUP(M161,AUHAgeBr,2,FALSE),"")))) | O161: =IF(M161="","",VLOOKUP(N161,$V$5:$BB$17,K161,FALSE)) | P161: =IF(L161="","",IF(H161="DXB",46,IF(H161="AUH",51,""))) | Q161: =IF(AND(LEFT(D161,1)="F",G161="Married",L161>17,L161<P161),HLOOKUP(E161,$W$1:$AA$2,2,FALSE),0) -> 0 | R161: =IF(M161="","",O161+Q161)
A162: =IF(C162="","",A161+1) | J162: =IF(D162="","",E162&LEFT(D162)&IF(F162="Employee","E","D")) | K162: =IF(J162="","",VLOOKUP(J162,$Y$19:$Z$50,2,FALSE)) | L162: =IF(C162="","",DATEDIF(C162,'Premium Table'!$B$6,"Y")) | M162: =IF(L162="","",IF(H162="","Choose Plan (DXB/AUH)",IF(H162="DXB",VLOOKUP(L162,$V$55:$W$154,2,FALSE),IF(H162="AUH",VLOOKUP(L162,$V$55:$X$154,3,FALSE),"Choose Plan (DXB/AUH)")))) | N162: =IF(L162="","",IF(M162="","",IF(H162="DXB",VLOOKUP(M162,DXBAgeBr,3,FALSE),IF(H162="AUH",VLOOKUP(M162,AUHAgeBr,2,FALSE),"")))) | O162: =IF(M162="","",VLOOKUP(N162,$V$5:$BB$17,K162,FALSE)) | P162: =IF(L162="","",IF(H162="DXB",46,IF(H162="AUH",51,""))) | Q162: =IF(AND(LEFT(D162,1)="F",G162="Married",L162>17,L162<P162),HLOOKUP(E162,$W$1:$AA$2,2,FALSE),0) -> 0 | R162: =IF(M162="","",O162+Q162)
A163: =IF(C163="","",A162+1) | J163: =IF(D163="","",E163&LEFT(D163)&IF(F163="Employee","E","D")) | K163: =IF(J163="","",VLOOKUP(J163,$Y$19:$Z$50,2,FALSE)) | L163: =IF(C163="","",DATEDIF(C163,'Premium Table'!$B$6,"Y")) | M163: =IF(L163="","",IF(H163="","Choose Plan (DXB/AUH)",IF(H163="DXB",VLOOKUP(L163,$V$55:$W$154,2,FALSE),IF(H163="AUH",VLOOKUP(L163,$V$55:$X$154,3,FALSE),"Choose Plan (DXB/AUH)")))) | N163: =IF(L163="","",IF(M163="","",IF(H163="DXB",VLOOKUP(M163,DXBAgeBr,3,FALSE),IF(H163="AUH",VLOOKUP(M163,AUHAgeBr,2,FALSE),"")))) | O163: =IF(M163="","",VLOOKUP(N163,$V$5:$BB$17,K163,FALSE)) | P163: =IF(L163="","",IF(H163="DXB",46,IF(H163="AUH",51,""))) | Q163: =IF(AND(LEFT(D163,1)="F",G163="Married",L163>17,L163<P163),HLOOKUP(E163,$W$1:$AA$2,2,FALSE),0) -> 0 | R163: =IF(M163="","",O163+Q163)
A164: =IF(C164="","",A163+1) | J164: =IF(D164="","",E164&LEFT(D164)&IF(F164="Employee","E","D")) | K164: =IF(J164="","",VLOOKUP(J164,$Y$19:$Z$50,2,FALSE)) | L164: =IF(C164="","",DATEDIF(C164,'Premium Table'!$B$6,"Y")) | M164: =IF(L164="","",IF(H164="","Choose Plan (DXB/AUH)",IF(H164="DXB",VLOOKUP(L164,$V$55:$W$154,2,FALSE),IF(H164="AUH",VLOOKUP(L164,$V$55:$X$154,3,FALSE),"Choose Plan (DXB/AUH)")))) | N164: =IF(L164="","",IF(M164="","",IF(H164="DXB",VLOOKUP(M164,DXBAgeBr,3,FALSE),IF(H164="AUH",VLOOKUP(M164,AUHAgeBr,2,FALSE),"")))) | O164: =IF(M164="","",VLOOKUP(N164,$V$5:$BB$17,K164,FALSE)) | P164: =IF(L164="","",IF(H164="DXB",46,IF(H164="AUH",51,""))) | Q164: =IF(AND(LEFT(D164,1)="F",G164="Married",L164>17,L164<P164),HLOOKUP(E164,$W$1:$AA$2,2,FALSE),0) -> 0 | R164: =IF(M164="","",O164+Q164)
A165: =IF(C165="","",A164+1) | J165: =IF(D165="","",E165&LEFT(D165)&IF(F165="Employee","E","D")) | K165: =IF(J165="","",VLOOKUP(J165,$Y$19:$Z$50,2,FALSE)) | L165: =IF(C165="","",DATEDIF(C165,'Premium Table'!$B$6,"Y")) | M165: =IF(L165="","",IF(H165="","Choose Plan (DXB/AUH)",IF(H165="DXB",VLOOKUP(L165,$V$55:$W$154,2,FALSE),IF(H165="AUH",VLOOKUP(L165,$V$55:$X$154,3,FALSE),"Choose Plan (DXB/AUH)")))) | N165: =IF(L165="","",IF(M165="","",IF(H165="DXB",VLOOKUP(M165,DXBAgeBr,3,FALSE),IF(H165="AUH",VLOOKUP(M165,AUHAgeBr,2,FALSE),"")))) | O165: =IF(M165="","",VLOOKUP(N165,$V$5:$BB$17,K165,FALSE)) | P165: =IF(L165="","",IF(H165="DXB",46,IF(H165="AUH",51,""))) | Q165: =IF(AND(LEFT(D165,1)="F",G165="Married",L165>17,L165<P165),HLOOKUP(E165,$W$1:$AA$2,2,FALSE),0) -> 0 | R165: =IF(M165="","",O165+Q165)
A166: =IF(C166="","",A165+1) | J166: =IF(D166="","",E166&LEFT(D166)&IF(F166="Employee","E","D")) | K166: =IF(J166="","",VLOOKUP(J166,$Y$19:$Z$50,2,FALSE)) | L166: =IF(C166="","",DATEDIF(C166,'Premium Table'!$B$6,"Y")) | M166: =IF(L166="","",IF(H166="","Choose Plan (DXB/AUH)",IF(H166="DXB",VLOOKUP(L166,$V$55:$W$154,2,FALSE),IF(H166="AUH",VLOOKUP(L166,$V$55:$X$154,3,FALSE),"Choose Plan (DXB/AUH)")))) | N166: =IF(L166="","",IF(M166="","",IF(H166="DXB",VLOOKUP(M166,DXBAgeBr,3,FALSE),IF(H166="AUH",VLOOKUP(M166,AUHAgeBr,2,FALSE),"")))) | O166: =IF(M166="","",VLOOKUP(N166,$V$5:$BB$17,K166,FALSE)) | P166: =IF(L166="","",IF(H166="DXB",46,IF(H166="AUH",51,""))) | Q166: =IF(AND(LEFT(D166,1)="F",G166="Married",L166>17,L166<P166),HLOOKUP(E166,$W$1:$AA$2,2,FALSE),0) -> 0 | R166: =IF(M166="","",O166+Q166)
... A506: =IF(C506="","",A505+1) | J506: =IF(D506="","",E506&LEFT(D506)&IF(F506="Employee","E","D")) | K506: =IF(J506="","",VLOOKUP(J506,$Y$19:$Z$50,2,FALSE)) | L506: =IF(C506="","",DATEDIF(C506,'Premium Table'!$B$6,"Y")) | M506: =IF(L506="","",IF(H506="","Choose Plan (DXB/AUH)",IF(H506="DXB",VLOOKUP(L506,$V$55:$W$154,2,FALSE),IF(H506="AUH",VLOOKUP(L506,$V$55:$X$154,3,FALSE),"Choose Plan (DXB/AUH)")))) | N506: =IF(L506="","",IF(M506="","",IF(H506="DXB",VLOOKUP(M506,DXBAgeBr,3,FALSE),IF(H506="AUH",VLOOKUP(M506,AUHAgeBr,2,FALSE),"")))) | O506: =IF(M506="","",VLOOKUP(N506,$V$5:$BB$17,K506,FALSE)) | P506: =IF(L506="","",IF(H506="DXB",46,IF(H506="AUH",51,""))) | Q506: =IF(AND(LEFT(D506,1)="F",G506="Married",L506>17,L506<P506),HLOOKUP(E506,$W$1:$AA$2,2,FALSE),0) -> 0 | R506: =IF(M506="","",O506+Q506)
A507: End | B507: End | C507: End | D507: End | E507: End | F507: End | G507: End | H507: End | I507: End | J507: End | K507: End | L507: End | M507: End | N507: End | O507: End | P507: End | Q507: End | R507: End

Sheet PRD
A1: PRODUCT REQUIREMENTS DOCUMENT (PRD) — Group Health Insurance Policy Automation Platform
A2: Product | B2: Group Health Insurance Policy Automation Platform | D2: Version | E2: 1 | G2: Date | H2: 45746
A3: Prepared For | B3: Insurance Operations / RM Team | D3: Status | E3: Draft – Pending Stakeholder Review | G3: Ref File | H3: MGH LOGISTICS L.L.C
A5: 1. EXECUTIVE SUMMARY
A6: This system automates the end-to-end group health insurance policy onboarding workflow — from document upload through premium calculation, Excel report generation, Slack notification, and policy database entry. Currently manual (30–60 min/policy), error-prone, and inconsistent. MVP targets the workflow for MGH LOGISTICS L.L.C and standardises it across all new and renewal policies.
A8: 2. PROBLEM STATEMENT
A9: 2.1 Manual file saving to shared folders is inconsistent — wrong naming conventions, wrong folder location.
A10: 2.2 Premium Summary Sheets are built manually in Excel, taking 30–60 min per policy. Prone to formula errors.
A11: 2.3 Slack notifications sent ad-hoc — no standard format, no guaranteed delivery, missing key fields.
A12: 2.4 Policy database entry is fully manual — missing fields, stale data, and duplicate records are common.
A13: 2.5 No single source of truth linking the TOB, census, premium data, broker, and RM in one place.
A15: 3. GOALS & SUCCESS METRICS
A16: Goal ID | B16: Goal | C16: Success Metric | G16: Target
A17: G1 | B17: Automate file intake & saving | C17: Zero manual folder saves after upload | G17: 1
A18: G2 | B18: Auto-generate Premium Summary Excel | C18: < 2 min from upload to file ready | G18: < 2 min
A19: G3 | B19: Send structured Slack alert | C19: Slack message sent on every policy | G19: 100% delivery
A20: G4 | B20: Auto-populate policy database | C20: All required fields populated per policy | G20: Zero missing fields
A21: G5 | B21: Full audit trail | C21: Every action logged with timestamp + user | G21: Full traceability
A23: 4. SCOPE
A24: 4.1 In Scope (MVP)
A25: ✅ Document upload interface — accepts signed TOB (PDF) + Census (Excel/CSV)
A26: ✅ Automatic file naming enforcement + save to shared folder (SharePoint / Google Drive / S3)
A27: ✅ Premium calculation engine — parses census, applies age-bracket rates (ALB method), computes per-member premium incl. maternity
A28: ✅ Premium Summary Excel generation (per-member, category totals, BASMAH, Slash, VAT) matching current manual format exactly
A29: ✅ Auto-save generated Excel to correct client subfolder with standard naming convention
A30: ✅ Slack Block Kit notification to #policy-ops with company, members, total premium, RM, broker, and file link
A31: ✅ Policy database record: company, policy, broker, cost structure, RM, census with premiums, rate snapshot, document links
A33: 4.2 Out of Scope — Phase 2
A34: ❌ Automated insurer quote fetching or comparative quoting engine
A35: ❌ Member-facing self-service portal
... A40: 5. USER ROLES & PERMISSIONS
A41: Role | B41: Description | D41: Permissions
A42: Operations Admin | B42: Primary operator — uploads docs, triggers workflow | D42: Upload, view, send Slack, edit own policy records
A43: Operations Manager | B43: Reviews outputs, approves DB entries | D43: View, approve, edit all records + audit log
A44: Finance / Reporting | B44: Needs premium data and reports | D44: View & export only (read-only)
A45: System / Bot | B45: Executes the automated pipeline steps | D45: Read/write all — restricted to automation actions only
A47: 6. FUNCTIONAL REQUIREMENTS
A48: FR-1 Document Upload & File Storage
A49: Req ID | B49: Requirement | C49: Acceptance Criteria | G49: Priority | H49: Notes
A50: FR-1.1 | B50: Upload Interface | C50: Web UI or Slack/Teams bot — upload signed TOB (PDF) + Census (Excel/CSV) in one action; drag-and-drop + file picker supported | G50: MUST
A51: FR-1.2 | B51: File Naming | C51: Auto-rename: [ClientName]_TOB_[YYYY-MM-DD].pdf and [ClientName]_Census_[YYYY-MM-DD].xlsx | G51: MUST | H51: Company name from upload form
A52: FR-1.3 | B52: Folder Structure | C52: Create/navigate to /Policies/[Year]/[ClientName]/ — auto-create subfolders if absent | G52: MUST | H52: SharePoint Graph API
A53: FR-1.4 | B53: Duplicate Detection | C53: Warn if same client + date file already exists; prompt user to confirm overwrite or rename | G53: MUST
A54: FR-1.5 | B54: Upload Confirmation | C54: Return saved file URL/path; log action to audit trail with timestamp + user | G54: MUST
A56: FR-2 Premium Calculation Engine
A57: Req ID | B57: Requirement | C57: Acceptance Criteria | G57: Priority | H57: Notes
A58: FR-2.1 | B58: Census Parsing | C58: Extract: Name, DOB, Gender, Relationship, Category, Plan (Dubai/AUH/NE). Support Excel (.xlsx) and CSV formats. | G58: MUST
A59: FR-2.2 | B59: Age Calc (ALB) | C59: Compute each member's age as Age Last Birthday relative to policy inception date | G59: MUST | H59: Match logic in 'Final premium per member' sheet
A60: FR-2.3 | B60: Age Bracket Lookup | C60: Map each member to bracket (0-10, 11-17, 18-25, 26-30, 31-35, 36-40, 41-45, 46-50, 51-55, 56-59, 60-64, 65-99) by category (A/B/C), gender, and relationship type | G60: MUST | H60: Rate table from approved TOB
A61: FR-2.4 | B61: Maternity Premium | C61: Add maternity premium for Female employees/spouses aged ≤ Maternity Age Limit (default: 46 per approved quote) | G61: MUST | H61: Amount from approved quote sheet
A62: FR-2.5 | B62: Premium Rollup | C62: Per-member total → category subtotal → grand total → add BASMAH (AED 37/member) + Slash Data fee + VAT (5%) | G62: MUST | H62: All breakdowns must match Approved Quote sheet
A63: FR-2.6 | B63: Variance Check | C63: If computed total ≠ confirmed premium in TOB → flag discrepancy, halt pipeline, alert RM. Tolerance: AED 0 (exact match). | G63: MUST
A65: FR-3 Premium Summary Excel Generation
A66: Req ID | B66: Requirement | C66: Acceptance Criteria | G66: Priority | H66: Notes
A67: FR-3.1 | B67: Template Match | C67: Generated Excel replicates current manual file exactly: same sheets, columns, headers, number formats, conditional formatting | G67: MUST | H67: Use openpyxl or ExcelJS template
A68: FR-3.2 | B68: Per-Member Rows | C68: One row per member: No., Name, DOB, Gender, Category, Relationship, Marital Status, Plan, Age (ALB), Age Bracket, Base Premium, Maternity Premium, Total Premium | G68: MUST
A69: FR-3.3 | B69: Summary Totals | C69: Header totals row: Total Base Premium, Total Maternity Premium, Grand Total, Member Count | G69: MUST
A70: FR-3.4 | B70: Rate Table Panel | C70: Age-bracket rate lookup table on right-side panel (columns S–Z current layout) | G70: SHOULD | H70: Match current manual layout
A71: FR-3.5 | B71: Approved Quote Tab | C71: Generate 'Approved Quote' sheet: premium overview, BASMAH, Slash Data, VAT, category breakdown table | G71: MUST
A72: FR-3.6 | B72: Confirmation Info Tab | C72: Populate 'Confirmation Info Sheet': company, broker, RM, inception date, document checklist status | G72: MUST
A73: FR-3.7 | B73: File Save & Naming | C73: Save as [ClientName]_PremiumSummary_[YYYY-MM-DD].xlsx to client's shared folder | G73: MUST
A75: FR-4 Slack Notification
A76: Req ID | B76: Requirement | C76: Acceptance Criteria | G76: Priority | H76: Notes
A77: FR-4.1 | B77: Auto-Trigger | C77: Slack message sent automatically after Excel is saved — no manual action needed from RM | G77: MUST
A78: FR-4.2 | B78: Target Channel | C78: Post to configurable channel (e.g. #policy-ops); channel name stored in system config | G78: MUST
A79: FR-4.3 | B79: Block Kit Format | C79: Structured message: 🏢 Company | 👥 Members | 💰 Net Premium | 🧾 Grand Total incl. VAT | 🗓️ Inception | 🧑 RM | 🤝 Broker | 📋 Policy Type | 📎 Excel Link | ✅ Status | G79: MUST | H79: Slack Block Kit — not plain text
A80: FR-4.4 | B80: Excel File Link | C80: Include clickable link to the Premium Summary Excel in the shared folder | G80: MUST
A81: FR-4.5 | B81: Error Alerting | C81: Pipeline failure → auto-alert #ops-alerts with step name, error detail, and client name | G81: MUST
A83: FR-5 Policy Database Entry
A84: Req ID | B84: Requirement | C84: Acceptance Criteria | G84: Priority | H84: Notes
A85: FR-5.1 | B85: Company Record | C85: Create/update: Legal Name, Emirate, Trade License No., VAT No., Establishment ID | G85: MUST
A86: FR-5.2 | B86: Policy Record | C86: Store: Policy No., Inception Date, Expiry Date, Insurer, Type (New/Renewal), Confirmed Premium, Member Count | G86: MUST
A87: FR-5.3 | B87: Broker Record | C87: Link broker entity: Broker Name, Contact Person, Commission % | G87: MUST
A88: FR-5.4 | B88: Cost Structure | C88: Base Premium, BASMAH Fee, Slash Data Fee, VAT Amount, Grand Total — breakdown by Category (A/B/C) | G88: MUST
A89: FR-5.5 | B89: RM Assignment | C89: Record Relationship Manager (name, user ID) assigned to this policy | G89: MUST
A90: FR-5.6 | B90: Census with Premiums | C90: Per-member record: Name, DOB, Gender, Category, Relationship, Plan, Age (ALB), Age Bracket, Base Premium, Maternity Premium, Total Premium — linked via policy_id FK | G90: MUST
A91: FR-5.7 | B91: Rate Snapshot | C91: Store full rate table used at inception (category × gender × age bracket → AED) — prevents historical loss on future rate changes | G91: MUST
A92: FR-5.8 | B92: Document Links | C92: Attach file URLs: signed TOB PDF, Census file, Premium Summary Excel | G92: MUST
A93: FR-5.9 | B93: Duplicate Check | C93: If company + inception date combination already exists → prompt user: New Policy or Endorsement? | G93: MUST
A95: 7. POLICY DATABASE SCHEMA
A96: 7.1 Table Overview
A97: Table | B97: Description & Key Fields
A98: companies | B98: Legal entity. Fields: company_id (PK), legal_name, emirate, trade_license, vat_no, establishment_id
A99: policies | B99: One per policy period. Fields: policy_id (PK), company_id (FK), policy_no, inception_date, expiry_date, insurer, type, confirmed_premium, member_count, rm_id
A100: subpolicies | B100: Fields: subpolicy_id (PK),policy_id (PK), company_id (FK), policy_no, inception_date, expiry_date, insurer, type, confirmed_premium, member_count, rm_id
A101: brokers | B101: Broker entities. Fields: broker_id (PK), broker_name, contact_person, email, phone
A102: policy_brokers | B102: Junction broker ↔ policy. Fields: policy_id (FK), broker_id (FK), commission_pct
A103: members | B103: Insured persons. Fields: member_id (PK), policy_id (FK), name, dob, gender, category, relationship, plan, age_alb, age_bracket, base_premium, maternity_premium, total_premium
A104: rate_tables | B104: Rate snapshot at inception. Fields: rate_table_id (PK), policy_id (FK), category, gender, relationship_type, age_bracket, premium_aed, captured_date
A105: documents | B105: File references. Fields: doc_id (PK), policy_id (FK), doc_type (TOB/Census/PremiumSummary), file_name, file_url, uploaded_by, uploaded_at
A106: audit_log | B106: Action log. Fields: log_id (PK), user_id, action_type, entity_type, entity_id, timestamp, payload_hash, result_status
A108: 8. TECHNICAL ARCHITECTURE & RECOMMENDED STACK
A109: Component | B109: Technology / Approach
A110: Frontend / UI | B110: Web app (React/Next.js) OR Slack slash command (/newpolicy) OR Microsoft Teams bot — Admin uploads files and triggers workflow here
A111: Backend / API | B111: Python FastAPI or Node.js Express — orchestrates the full pipeline: file parsing, premium calc, DB writes, Slack calls, Excel generation
A112: Premium Calc Engine | B112: Python (openpyxl + pandas) — replicates the Excel logic: age bracket lookup (ALB method), maternity rule, BASMAH/Slash/VAT rollup. Validated against MGH LOGISTICS test case.
A113: File Storage | B113: SharePoint Online via Microsoft Graph API (recommended for UAE MS-ecosystem) — OR Google Drive API / AWS S3
A114: Excel Generation | B114: openpyxl (Python) or ExcelJS (Node.js) — populates Premium Summary workbook from locked template, preserving all formatting
A115: Slack Integration | B115: Slack Bolt SDK — sends Block Kit messages via Bot token; error alerts via Incoming Webhooks; channel name in config
A116: Database | B116: PostgreSQL on AWS RDS (recommended — relational model fits policy/member data) — OR Airtable for fast low-code MVP
...

Sheet Calculation Explainer
A1: PREMIUM CALCULATION EXPLAINER — Group Health Insurance (UAE)
A2: Step-by-step explanation of every calculation in 'Final premium per member', 'Premium Table', and 'Approved Quote' sheets | Reference: MGH LOGISTICS L.L.C
A4: HOW THE CALCULATION WORKS — OVERVIEW
A5: STEP 1 | B5: Age Calculation (ALB) | C5: For each member, compute Age Last Birthday (ALB) = full years elapsed between Date of Birth and Policy Start Date
A6: STEP 2 | B6: Age Bracket Mapping | C6: Map the ALB to an age bracket (e.g. 41–45). The bracket depends on the plan (Dubai or Abu Dhabi).
A7: STEP 3 | B7: Column Code Lookup | C7: Determine the rate column to use based on: Category (A/B/C) + Gender (M/F) + Relationship (Employee/Dependent)
A8: STEP 4 | B8: Base Premium Lookup | C8: Look up the base annual premium (AED) from the rate table using: Age Bracket Code + Column Code
A9: STEP 5 | B9: Maternity Premium | C9: Add maternity surcharge for Female + Married + Age > 17 + Age < Maternity Age Limit (46 for Dubai, 51 for Abu Dhabi)
A10: STEP 6 | B10: Total Premium per Member | C10: Base Premium + Maternity Premium = Total Annual Premium for that member
A11: STEP 7 | B11: Grand Total + Fees | C11: Sum all member premiums → add BASMAH fee (AED 37/member) → add Slash Data fee → add VAT (5%)
A13: STEP 1 — AGE CALCULATION (Age Last Birthday / ALB)
A14: What is ALB?
A15: Age Last Birthday (ALB) = the member's age in complete years on the policy start date. It does NOT round up — a person who turns 42 in 3 months is still 41. This is the standard UAE insurance age convention.
A16: Formula Used | B16: Column | C16: Excel Formula | F16: Example (Vitty Thomas) | H16: Result
A17: Age (ALB) | B17: L (col 12) | C17: =DATEDIF(C6, 'Premium Table'!$B$6, "Y") -> #VALUE! | F17: DOB: 30 Aug 1983 (serial 30593) | Policy Start: 01 Jan 2026 (serial 46105) | H17: 42 years
A18: Explanation | B18: DATEDIF(start_date, end_date, "Y") returns the number of complete years between two dates. The DOB is in column C. The policy start date is pulled from 'Premium Table'!B6 — this is a single source of truth for the policy inception date used by all members.
A20: STEP 2 — AGE BRACKET MAPPING
A21: What is it?
A22: Members are grouped into age brackets. Dubai and Abu Dhabi plans have DIFFERENT bracket ranges. The bracket label (e.g. '41 - 45') is what gets looked up in the rate table. A VLOOKUP maps the numeric ALB age to a bracket string using a lookup table at columns V–X of the 'Final premium per member' sheet.
A23: Dubai (DXB) Age Brackets | E23: Abu Dhabi (AUH) Age Brackets
A24: Bracket Code | B24: Age Range (DXB) | C24: Ages (numeric) | E24: Bracket Code | F24: Age Range (AUH) | G24: Ages (numeric)
A25: 1 | B25: 0 – 10 | C25: 0 to 10 | E25: 1 | F25: 0 – 17 | G25: 0 to 17
A26: 2 | B26: 11 – 17 | C26: 11 to 17 | E26: 2 | F26: 18 – 40 | G26: 18 to 40
A27: 3 | B27: 18 – 25 | C27: 18 to 25 | E27: 3 | F27: 41 – 59 | G27: 41 to 59
A28: 4 | B28: 26 – 30 | C28: 26 to 30 | E28: 4 | F28: 60 – 64 | G28: 60 to 64
A29: 5 | B29: 31 – 35 | C29: 31 to 35 | E29: 5 | F29: 65 – 99 | G29: 65+
A30: 6 | B30: 36 – 40 | C30: 36 to 40
A31: 7 | B31: 41 – 45 | C31: 41 to 45
A32: 8 | B32: 46 – 50 | C32: 46 to 50
A33: 9 | B33: 51 – 55 | C33: 51 to 55
A34: 10 | B34: 56 – 59 | C34: 56 to 59
A35: 11 | B35: 60 – 64 | C35: 60 to 64
A36: 12 | B36: 65 – 99 | C36: 65+
A38: Formula Used | B38: Column | C38: Excel Formula | F38: Notes
A39: Age Bracket | B39: M (col 13) | C39: =IF(H6="DXB", VLOOKUP(L6,$V$55:$W$154,2,FALSE), IF(H6="AUH", VLOOKUP(L6,$V$55:$X$154,3,FALSE), "Choose Plan")) -> Choose Plan | F39: Lookup table at cols V–X maps numeric age → bracket string. Col W = DXB brackets, Col X = AUH brackets.
A41: STEP 3 — COLUMN CODE LOOKUP (Which rate column to use?)
A42: What is it?
A43: The rate table has different columns for each combination of Category (A, B, C) × Gender (M, F) × Relationship (Employee/Principal, Dependent). A short code like 'AME' = Category A, Male, Employee. A number (2–13) tells the VLOOKUP which column of the rate table to pull from.
A44: Code | B44: Category | C44: Gender | D44: Relationship | E44: Column # | F44: Example Member | H44: Meaning
A45: AME | B45: A | C45: Male | D45: Employee (Principal) | E45: 2 | F45: Vitty Yohannan Thomas | H45: → Male employee under Category A plan
A46: AFE | B46: A | C46: Female | D46: Employee (Principal) | E46: 3 | F46: Saniya Suri | H46: → Female employee under Category A plan
A47: AMD | B47: A | C47: Male | D47: Dependent | E47: 4 | F47: — | H47: → Male dependent (child/spouse) under Category A
A48: AFD | B48: A | C48: Female | D48: Dependent | E48: 5 | F48: Alice Raju, all female children | H48: → Female dependent under Category A
A49: BME | B49: B | C49: Male | D49: Employee (Principal) | E49: 6 | F49: (not in this policy) | H49: → Male employee under Category B plan
A50: BFE | B50: B | C50: Female | D50: Employee (Principal) | E50: 7 | F50: (not in this policy) | H50: → Female employee under Category B plan
A51: BMD | B51: B | C51: Male | D51: Dependent | E51: 8 | F51: (not in this policy) | H51: → Male dependent under Category B
A52: BFD | B52: B | C52: Female | D52: Dependent | E52: 9 | F52: (not in this policy) | H52: → Female dependent under Category B
A53: CME | B53: C | C53: Male | D53: Employee (Principal) | E53: 10 | F53: (not in this policy) | H53: → Male employee under Category C plan
A54: CFE | B54: C | C54: Female | D54: Employee (Principal) | E54: 11 | F54: (not in this policy) | H54: → Female employee under Category C plan
A55: CMD | B55: C | C55: Male | D55: Dependent | E55: 12 | F55: (not in this policy) | H55: → Male dependent under Category C
A56: CFD | B56: C | C56: Female | D56: Dependent | E56: 13 | F56: (not in this policy) | H56: → Female dependent under Category C
A58: Formula Used | B58: Column | C58: Excel Formula | F58: How the code is constructed
A59: Column Code | B59: J (col 10) | C59: =CONCATENATE(E6, IF(D6="MALE","M","F"), IF(F6="Employee","E","D")) -> FD | F59: Concatenates: Category letter + M/F from Gender + E/D from Relationship. E.g. Cat A + Male + Employee = 'AME'
A60: Column Number | B60: K (col 11) | C60: =VLOOKUP(J6, $Y$19:$Z$50, 2, FALSE) -> #N/A | F60: Looks up the code (e.g. 'AME') in the code-to-number mapping table at cols Y–Z to get the column number (e.g. 2)
A62: STEP 4 — BASE PREMIUM LOOKUP (From the Rate Table)
A63: What is it?
A64: The rate table (columns V–BB, rows 5–17) contains all annual premiums in AED. The row is selected by the Age Bracket Code (1–12). The column is selected by the Column Number (2–13 = AME, AFE, AMD, AFD…). A single VLOOKUP retrieves the exact AED premium for that member's combination.
A65: Category A Rate Table (AED Annual Premiums) — Extracted from 'Final premium per member' sheet cols V–BB
A66: Bracket Code | B66: Age Bracket | C66: M Principal (AME col 2) | D66: F Principal (AFE col 3) | E66: M Dependent (AMD col 4) | F66: F Dependent (AFD col 5) | G66: Notes
A67: 1 | B67: 0 – 10 | C67: NA | D67: NA | E67: 6499 | F67: 5234 | G67: NA = not applicable for employees/principal in this bracket
A68: 2 | B68: 11 – 17 | C68: 3157 | D68: 3217 | E68: 4674 | F68: 4750
A69: 3 | B69: 18 – 25 | C69: 5253 | D69: 5997 | E69: 5253 | F69: 5997
A70: 4 | B70: 26 – 30 | C70: 5833 | D70: 7304 | E70: 5833 | F70: 7304
A71: 5 | B71: 31 – 35 | C71: 6915 | D71: 8606 | E71: 6915 | F71: 8606
A72: 6 | B72: 36 – 40 | C72: 8397 | D72: 10589 | E72: 8397 | F72: 10589
A73: 7 | B73: 41 – 45 | C73: 8785 | D73: 12068 | E73: 8795 | F73: 12068 | G73: Note: col 4 (AMD) has 8,795 — slightly different from AME 8,785
A74: 8 | B74: 46 – 50 | C74: 11304 | D74: 14951 | E74: 11304 | F74: 14951
A75: 9 | B75: 51 – 55 | C75: 14946 | D75: 19507 | E75: 14946 | F75: 19507
A76: 10 | B76: 56 – 59 | C76: 20128 | D76: 23729 | E76: 20128 | F76: 23729
A77: 11 | B77: 60 – 64 | C77: 24628 | D77: 28071 | E77: 24628 | F77: 28071
A78: 12 | B78: 65 – 99 | C78: 43786 | D78: 49985 | E78: 43786 | F78: 49985 | G78: Indicative only — requires MAF & MER
A80: Formula Used | B80: Column | C80: Excel Formula | F80: Inputs required | H80: Output
A81: Base Premium | B81: O (col 15) | C81: =VLOOKUP(N6, $V$5:$BB$17, K6, FALSE) -> #N/A | F81: N6 = Age Bracket Code (row index) | K6 = Column Number (e.g. 2 for AME) | H81: AED annual base premium
A82: Worked Example | B82: Vitty Thomas: Age=42 → Bracket='41-45' → Bracket Code=7 | Code=AME → Column No.=2 → VLOOKUP(7, rate_table, 2, FALSE) = AED 8,785
A84: STEP 5 — MATERNITY PREMIUM
A85: What is it?
A86: A fixed annual maternity surcharge (AED 5,244 for Dubai) is added on top of the base premium for eligible female members. The rules check ALL four conditions simultaneously. If any condition fails, the maternity premium is AED 0.
A87: Condition | B87: Criterion | C87: Column / Source | F87: Example — Alice Raju (row 7) | H87: Pass?
A88: 1 | B88: Gender = FEMALE | C88: Column D (Gender). Checks LEFT(D6,1)="F" | F88: Alice Raju = FEMALE | H88: ✅ PASS
A89: 2 | B89: Marital Status = Married | C89: Column G (Marital Status). Checks G6="Married" | F89: Alice Raju = Married | H89: ✅ PASS
A90: 3 | B90: Age > 17 (above minor threshold) | C90: Column L (Age ALB). Checks L6>17 | F90: Alice Raju = 41 years old | H90: ✅ PASS
A91: 4 | B91: Age < Maternity Age Limit | C91: Col P = 46 (Dubai) or 51 (Abu Dhabi). Checks L6<P6 | F91: Alice Raju = 41 < 46 | H91: ✅ PASS → AED 5,244 added
A93: Formula Used | B93: Column | C93: Excel Formula | F93: Amount | H93: Notes
A94: Maternity Premium | B94: Q (col 17) | C94: =IF(AND(LEFT(D6,1)="F", G6="Married", L6>17, L6<P6), HLOOKUP(E6,$W$1:$AA$2,2,FALSE), 0) -> 0 | F94: AED 5,244 (Dubai) / AED 0 (if any condition fails) | H94: HLOOKUP looks up maternity amount by Category across row 1 of cols W–AA
A95: Maternity Age Limit | B95: P (col 16) | C95: =IF(H6="DXB", 46, IF(H6="AUH", 51, "")) | F95: Dubai plan: age limit 46 | Abu Dhabi plan: age limit 51 | H95: Members at or above this age get AED 0 maternity premium
A96: Worked Example | B96: Alice Raju (row 7): Female + Married + Age 41 > 17 + Age 41 < 46 (limit) → ALL 4 conditions pass → HLOOKUP('A', maternity_amounts, 2, FALSE) = AED 5,244
A97: Counter-Example | B97: Vitty Thomas (row 6): MALE → first condition fails immediately → Maternity Premium = AED 0. Suhana Ahmed (row 14): Female + Married + Age 54 > 46 (limit) → condition 4 fails → AED 0.
A99: STEP 6 — TOTAL PREMIUM PER MEMBER
A100: Formula | B100: Column | C100: Excel Formula
A101: Total Premium | B101: R (col 18) | C101: =IF(M6="", "", O6 + Q6)
A103: STEP 7 — GRAND TOTAL + FEES + VAT (Approved Quote Sheet)
A104: Line Item
A105: Base Net Premium
A106: Maternity Premium | B106: SUM of 4 eligible female members x AED 5,244 | D106: 20976 | F106: Client
A107: Total Premium (Net) | B107: 144,218 + 20,976 = Confirmed Premium in TOB | D107: 165194 | F107: Client | H107: KEY TOTAL
A108: BASMAH Fee | B108: AED 37 x 17 members (DHA regulatory fee) | D108: 629 | F108: Client
A109: Slash Data Fee | B109: AED 25 x 0 Rest-of-UAE members | D109: 0 | F109: Client | H109: 0 members outside Dubai
A110: VAT (5%) | B110: (165,194 + 629 + 0) x 5% | D110: 8291.15 | F110: Client | H110: Applied to Premium + BASMAH + Slash
A111: GRAND TOTAL | B111: 165,194 + 629 + 0 + 8,291.15 | D111: 174114.15 | F111: Client | H111: Final invoiceable amount
A113: FULL WORKED EXAMPLE — All 17 Members of MGH LOGISTICS L.L.C
...
